Workbook
Name _____________IV65675: '[1]2-Conc'!#REF!
Name ____________IV65675: '[1]2-Conc'!#REF!
Name ___________IV65675: '[1]2-Conc'!#REF!
Name __________IV65675: #REF!
Name _________IV65675: '[1]2-Conc'!#REF!
Name _______IV65675: '[1]2-Conc'!#REF!
Name ______IV65675: #REF!
Name _____IV65675: '[1]2-Conc'!#REF!
Name ____IV65675: '[1]2-Conc'!#REF!
Name ___IV65675: '[1]2-Conc'!#REF!
Name __IV65675: '[1]2-Conc'!#REF!
Name _boq1: [2]BOQ!#REF!
Name _IV65675: '[1]2-Conc'!#REF!
Name A: #REF!
Name aa: #REF!
Name aaa: #REF!
Name b: #REF!
Name beam: [3]Lstsub!#REF!
Name Beamupper: [2]BOQ!#REF!
Name boqformat: [4]BOQ!#REF!
Name CA: [3]Lstsub!#REF!
Name Excluded: [4]BOQ!#REF!
Name FH: '[5]2-Conc'!#REF!
Name gd: [3]Lstsub!#REF!
Name GFJHN: '[1]2-Conc'!#REF!
Name H: #REF!
Name Included: [4]BOQ!#REF!
Name jh: #REF!
Name jhiuyhip: #REF!
Name kFOB: '[6]CIF COST ITEM'!#REF!
Name kIF: '[6]CIF COST ITEM'!#REF!
Name KK: #REF!
Name kloc: '[6]CIF COST ITEM'!#REF!
Name mez: [4]BOQ!#REF!
Name nw: [3]Lstsub!#REF!
Name OO: #REF!
Name QR.: [4]BOQ!#REF!
Name RA: [3]Lstsub!#REF!
Name RAPS: [3]Lstsub!#REF!
Name RCD: [3]Lstsub!#REF!
Name RCS: [3]Lstsub!#REF!
Name rgt: '[1]2-Conc'!#REF!
Name RL: [3]Lstsub!#REF!
Name RLPS: [3]Lstsub!#REF!
Name SS: '[7]2-Conc'!#REF!
Name SSS: #REF!
Name TSD: [3]Lstsub!#REF!
Name TSS: [3]Lstsub!#REF!
Name tyfy: #REF!
Name xxxx: [3]Lstsub!#REF!

Sheet Grand summary
B2: PROPOSED RESIDENTIAL DEVELOPMENT PROVIDENT ECOPOLITAN, BENGALURU
B3: INSTRUCTIONS TO TENDER
B4: 1 | C4: The Schedule of Rate shall be read with all the other sections of this bidding document including technical specification, general and special conditions of contract, safety requirements, EHS norms etc.
B5: 2 | C5: All the works shall be measured upon completion and paid for at the rate quoted and accepted in the “Schedule of Price”. In case any activity though specifically not covered in schedule of rates descriptions but the same is covered under scope of work/scope of supply/specification drawings etc. no extra claim on this account shall be entertained, since schedule of price is to be read in conjunction with all other documents forming part of the contract.
B6: 3 | C6: Written approval for the aggregates, materials used for construction to be obtained from the client /the Engineer prior to commencement of work.
B7: 4 | C7: All items of work mentioned in the Schedule of Rates shall be carried out as per the specifications, drawings and instructions of Client/the Engineer and the rates are deemed to be inclusive of material, consumable, labour, supervision, testing, tools and tackles and detailing of construction/fabrication drawings, wherever required as called for in the detail specification and conditions of the Contract.
B8: 5 | C8: This is an item rate tender and quantities are tentative. The Contractor's unit rates quoted shall not change for any variation in quantities.
B9: 6 | C9: Suitable barricading, warning systems, signages, sand cushing. Multiple handling of materials shall be taken into account in view of restricted area availabe for contruction. Extra claim for cost and time will not be accepted on account of failure to take into account the above factors prior to quoting.
B10: 7 | C10: Tests on materials shall confirm to IS Specification and the test shall be carried out as directed either at site Laboratory or at any approved test laboratory.
B11: 8 | C11: Material shall be of good, approved, acceptable quality & purchased from approved source; got approved from the Engineer prior to usage and meeting all relevant codal norms.
B12: 9 | C12: Work shall be carried out as per latest good for construction drawings, specifications & carried out to the satisfaction of the engineer.
B13: 10 | C13: Work will be measured and paid only as shown on the drawing as per applicable clause in IS 1200 unless or otherwise specified elsewhere.
B15: SUMMARY
B16: Sl.No. | C16: Description | D16: Amount (Rs.) (Incl Course Putty)
D17: Ph - 1 | E17: Ph 2 | F17: Total
B18: A | C18: CIVIL & STRUCTURAL WORKS
B20: 1 | C20: Earthwork & Antitermite Works | D20: ='Part-A & B_BOQ'!H33+'Part-A & B_BOQ'!H37 -> 4906025.7 | E20: ='Part-A & B_BOQ'!I33+'Part-A & B_BOQ'!I37 -> 943346.34 | F20: =SUM(D20:E20) -> 5849372
B21: =B20+1 -> 2 | C21: Plain cement concrete works | D21: ='Part-A & B_BOQ'!H58 -> 10582619 | E21: ='Part-A & B_BOQ'!I58 -> 2536822.6 | F21: =SUM(D21:E21) -> 13119442
B22: =B21+1 -> 3 | C22: Reinforced cement concrete works | D22: ='Part-A & B_BOQ'!H332 -> 5.52034e+08 | E22: ='Part-A & B_BOQ'!I332 -> 1.4781665e+08 | F22: =SUM(D22:E22) -> 6.9985065e+08
B23: =B22+1 -> 4 | C23: Form work | D23: ='Part-A & B_BOQ'!H463 -> 4.3673365e+08 | E23: ='Part-A & B_BOQ'!I463 -> 1.1260815e+08 | F23: =SUM(D23:E23) -> 5.493418e+08
B24: =B23+1 -> 5 | C24: Reinforcement Steel Works | D24: ='Part-A & B_BOQ'!H496 -> 5.921355e+08 | E24: ='Part-A & B_BOQ'!I496 -> 1.1638253e+08 | F24: =SUM(D24:E24) -> 7.0851803e+08
B25: =B24+1 -> 6 | C25: Concrete Flooring works | D25: ='Part-A & B_BOQ'!H548 -> 71378947 | E25: ='Part-A & B_BOQ'!I548 -> 10371681 | F25: =SUM(D25:E25) -> 81750628
B26: =B25+1 -> 7 | C26: Waterproofing works (through NSC) | D26: ='Part-A & B_BOQ'!H625 -> 80780574 | E26: ='Part-A & B_BOQ'!I625 -> 17186503 | F26: =SUM(D26:E26) -> 97967076
B27: =B26+1 -> 8 | C27: Expansion Joints (through NSC) | D27: ='Part-A & B_BOQ'!H671 -> 24090074 | E27: ='Part-A & B_BOQ'!I671 -> 1226506.8 | F27: =SUM(D27:E27) -> 25316581
B28: =B27+1 -> 9 | C28: Miscellaneous works | D28: ='Part-A & B_BOQ'!H750 -> 6149479.9 | E28: ='Part-A & B_BOQ'!I750 -> 782887.34 | F28: =SUM(D28:E28) -> 6932367.2
B29: =B28+1 -> 10 | C29: Conduit with accessories | D29: ='Part-A & B_BOQ'!H765 -> 6127294.2 | E29: ='Part-A & B_BOQ'!I765 -> 1372044.3 | F29: =SUM(D29:E29) -> 7499338.5
B30: =B29+1 -> 11 | C30: Masonry works | D30: ='Part-A & B_BOQ'!H827 -> 13659266 | E30: ='Part-A & B_BOQ'!I827 -> 1997022.4 | F30: =SUM(D30:E30) -> 15656289
B31: =B30+1 -> 12 | C31: Plastering works | D31: ='Part-A & B_BOQ'!H933 -> 39215475 | E31: ='Part-A & B_BOQ'!I933 -> 8563678 | F31: =SUM(D31:E31) -> 47779153
C32: Sub-Total | D32: =SUM(D19:D31) -> 1.8377929e+09 | E32: =SUM(E19:E31) -> 4.2178782e+08 | F32: =SUM(F19:F31) -> 2.2595807e+09
B34: B | C34: FINISHING WORKS
B36: 1 | C36: Gypsum Plastering works | D36: ='Part-A & B_BOQ'!H1001 -> 81720366 | E36: ='Part-A & B_BOQ'!I1001 -> 24225197 | F36: =SUM(D36:E36) -> 1.0594556e+08
B37: 2 | C37: Painting works | D37: ='Part-A & B_BOQ'!H1171 -> 1.2197576e+08 | E37: ='Part-A & B_BOQ'!I1171 -> 36679464 | F37: =SUM(D37:E37) -> 1.5865522e+08
B38: 3 | C38: Flooring, Dadoing, Skirting works | D38: ='Part-A & B_BOQ'!H1644 -> 2.333963e+08 | E38: ='Part-A & B_BOQ'!I1644 -> 78290369 | F38: =SUM(D38:E38) -> 3.1168667e+08
B39: 4 | C39: Structural Steel works | D39: ='Part-A & B_BOQ'!H1738 -> 29568146 | E39: ='Part-A & B_BOQ'!I1738 -> 6885942.7 | F39: =SUM(D39:E39) -> 36454089
B40: 5 | C40: Miscellaneous works | D40: ='Part-A & B_BOQ'!H1778 -> 48407816 | E40: ='Part-A & B_BOQ'!I1778 -> 9807160.4 | F40: =SUM(D40:E40) -> 58214976
B41: 6 | C41: Joinery works | D41: ='Part-A & B_BOQ'!H1954 -> 88350480 | E41: ='Part-A & B_BOQ'!I1954 -> 28616662 | F41: =SUM(D41:E41) -> 116967142
B42: 7 | C42: UPVC Works | D42: ='Part-A & B_BOQ'!H2389 -> 0 | E42: ='Part-A & B_BOQ'!I2389 -> 0 | F42: =SUM(D42:E42) -> 0
B43: 8 | C43: False ceiling works | D43: ='Part-A & B_BOQ'!H2418 -> 9848691.3 | E43: ='Part-A & B_BOQ'!I2418 -> 3134128.2 | F43: =SUM(D43:E43) -> 12982820
C44: Sub-Total | D44: =SUM(D36:D43) -> 6.1326756e+08 | E44: =SUM(E36:E43) -> 1.8763892e+08 | F44: =SUM(F36:F43) -> 8.0090648e+08
C46: Total Excluding Taxes | D46: =D32+D44 -> 2.4510605e+09 | E46: =E32+E44 -> 6.0942675e+08 | F46: =F32+F44 -> 3.0604872e+09
C47: GST 18% | D47: =D46*18% -> 4.4119088e+08 | E47: =E46*18% -> 1.0969681e+08 | F47: =F46*18% -> 5.508877e+08
C48: Total Including Taxes | D48: =D46+D47 -> 2.8922513e+09 | E48: =E46+E47 -> 7.1912356e+08 | F48: =F46+F47 -> 3.6113749e+09

Sheet Summary_Final
A1: Project - Provident Ecopolitan, Aerospace Park, Bangalore.
A2: Summary - Structure & Finishing Works
A3: Sl.No. | B3: Description | C3: As per VO#02 | D3: As per Actual | E3: Present Variation | F3: Remarks
C5: Amount (Rs.)
A6: A | B6: CIVIL & STRUCTURAL WORKS
A7: 1 | B7: Earthwork & Antitermite Works | C7: ='Grand summary'!F20 -> 5849372 | D7: =E7-C7 -> 3595399.4 | E7: ='Part-A & B_BOQ'!O33+'Part-A & B_BOQ'!O37 -> 9444771.4 | J7: 21706453 | L7: =D7-J7 -> -18111054
A8: =A7+1 -> 2 | B8: Plain cement concrete works | C8: ='Grand summary'!F21 -> 13119442 | D8: =E8-C8 -> 6010316.7 | E8: ='Part-A & B_BOQ'!O58 -> 19129759 | J8: 28217815 | L8: =D8-J8 -> -22207498
A9: =A8+1 -> 3 | B9: Reinforced cement concrete works | C9: ='Grand summary'!F22 -> 6.9985065e+08 | D9: =E9-C9 -> -20811382 | E9: ='Part-A & B_BOQ'!O332 -> 6.7903927e+08 | J9: 6.4073192e+08 | L9: =D9-J9 -> -6.615433e+08
A10: =A9+1 -> 4 | B10: Form work | C10: ='Grand summary'!F23 -> 5.493418e+08 | D10: =E10-C10 -> 17278454 | E10: ='Part-A & B_BOQ'!O463 -> 5.6662026e+08 | J10: 5.2012134e+08 | L10: =D10-J10 -> -5.0284289e+08
A11: =A10+1 -> 5 | B11: Reinforcement Steel Works | C11: ='Grand summary'!F24 -> 7.0851803e+08 | D11: =E11-C11 -> -2340950.2 | E11: ='Part-A & B_BOQ'!O496 -> 7.0617708e+08 | J11: 729720015 | L11: =D11-J11 -> -7.3206097e+08
A12: =A11+1 -> 6 | B12: Concrete Flooring works | C12: ='Grand summary'!F25 -> 81750628 | D12: =E12-C12 -> -6695511.3 | E12: ='Part-A & B_BOQ'!O548 -> 75055117 | J12: 85598862 | L12: =D12-J12 -> -92294373
A13: =A12+1 -> 7 | B13: Waterproofing works | C13: ='Grand summary'!F26 -> 97967076 | D13: =E13-C13 -> 474215.11 | E13: ='Part-A & B_BOQ'!O625 -> 98441292 | J13: 122161309 | L13: =D13-J13 -> -1.2168709e+08
A14: =A13+1 -> 8 | B14: Expansion Joints | C14: ='Grand summary'!F27 -> 25316581 | D14: =E14-C14 -> 0 | E14: ='Part-A & B_BOQ'!O671 -> 25316581 | J14: 25833910 | L14: =D14-J14 -> -25833910
A15: =A14+1 -> 9 | B15: Miscellaneous works | C15: ='Grand summary'!F28 -> 6932367.2 | D15: =E15-C15 -> -2074452.3 | E15: ='Part-A & B_BOQ'!O750 -> 4857914.9 | J15: 8982055 | L15: =D15-J15 -> -11056507
A16: =A15+1 -> 10 | B16: Conduit with accessories | C16: ='Grand summary'!F29 -> 7499338.5 | D16: =E16-C16 -> -1150248.7 | E16: ='Part-A & B_BOQ'!O765 -> 6349089.8 | J16: 24362630 | L16: =D16-J16 -> -25512879
A17: =A16+1 -> 11 | B17: Masonry works | C17: ='Grand summary'!F30 -> 15656289 | D17: =E17-C17 -> -227732.82 | E17: ='Part-A & B_BOQ'!O827 -> 15428556 | J17: 19477735 | L17: =D17-J17 -> -19705468
A18: =A17+1 -> 12 | B18: Plastering works | C18: ='Grand summary'!F31 -> 47779153 | D18: =E18-C18 -> -244144.25 | E18: ='Part-A & B_BOQ'!O933 -> 47535009 | J18: 46436588 | L18: =D18-J18 -> -46680732
B19: Sub-Total - A | C19: =SUM(C7:C18) -> 2.2595807e+09 | D19: =SUM(D7:D18) -> -6186036 | E19: =SUM(E7:E18) -> 2.2533947e+09 | J19: =SUM(J7:J18) -> 2.2733506e+09 | L19: =SUM(L7:L18) -> -2.2795367e+09
A20: B | B20: FINISHING WORKS | L20: =D20-J20 -> 0
A21: 1 | B21: Gypsum Plastering works | C21: ='Grand summary'!F36 -> 1.0594556e+08 | D21: =E21-C21 -> -6040315.6 | E21: ='Part-A & B_BOQ'!O1001 -> 99905248 | J21: 80879463 | L21: =D21-J21 -> -86919779
A22: 2 | B22: Painting works | C22: ='Part-A & B_BOQ'!O1171 -> 1.5865522e+08 | D22: =E22-C22 -> 0 | E22: ='Part-A & B_BOQ'!O1171 -> 1.5865522e+08 | J22: 138465821 | L22: =D22-J22 -> -138465821
A23: 3 | B23: Flooring, Dadoing, Skirting works | C23: ='Part-A & B_BOQ'!J1644 -> 3.1168667e+08 | D23: =E23-C23 -> 3429530.8 | E23: ='Part-A & B_BOQ'!O1644 -> 3.151162e+08 | J23: 298669783 | L23: =D23-J23 -> -2.9524025e+08
A24: 4 | B24: Structural Steel works | C24: ='Grand summary'!F39 -> 36454089 | D24: =E24-C24 -> -4840100 | E24: ='Part-A & B_BOQ'!O1738 -> 31613989 | J24: 27158421 | L24: =D24-J24 -> -31998521
A25: 5 | B25: Miscellaneous works | C25: ='Grand summary'!F40 -> 58214976 | D25: =E25-C25 -> -21785979 | E25: ='Part-A & B_BOQ'!O1778 -> 36428998 | J25: 43257223 | L25: =D25-J25 -> -65043202
A26: 6 | B26: Joinery works | C26: ='Grand summary'!F41 -> 116967142 | D26: =E26-C26 -> 4261950 | E26: ='Part-A & B_BOQ'!O1954 -> 121229092 | J26: 128956950 | L26: =D26-J26 -> -124695000
A27: 7 | B27: UPVC Works | C27: ='Grand summary'!F42 -> 0 | D27: =E27-C27 -> 0 | E27: ='Part-A & B_BOQ'!O2389 -> 0 | J27: 106523340 | L27: =D27-J27 -> -106523340
A28: 8 | B28: False ceiling works | C28: ='Grand summary'!F43 -> 12982820 | D28: =E28-C28 -> -203999.25 | E28: ='Part-A & B_BOQ'!O2418 -> 12778820 | J28: 9511224 | L28: =D28-J28 -> -9715223.2
B29: Sub-Total - B | C29: =SUM(C21:C28) -> 8.0090648e+08 | D29: =SUM(D21:D28) -> -25178913 | E29: =SUM(E21:E28) -> 7.7572757e+08 | J29: =SUM(J21:J28) -> 833422225 | L29: =D29-J29 -> -8.5860114e+08
B30: Grand Toral (A + B) | C30: =C29+C19 -> 3.0604872e+09 | D30: =D29+D19 -> -31364949 | E30: =E29+E19 -> 3.0291223e+09
A31: C | B31: NT #01
A32: 1 | B32: Additional Aluminium Formwork | C32: =NT_01!F8 -> 1000000 | D32: =E32-C32 -> 0 | E32: =NT_01!F8 -> 1000000
B33: Sub-Total - C | C33: =SUM(C32) -> 1000000 | D33: =SUM(D32:D32) -> 0 | E33: =SUM(E32:E32) -> 1000000 | J33: =SUM(#REF!) -> #REF! | L33: =D33-J33 -> #REF!
A34: D | B34: NT #02 | C34: =NT_02!F21 -> 25404407 | D34: =E34-C34 -> 0 | E34: =NT_02!F21 -> 25404407 | J34: 1.2126816e+08 | L34: =D34-J34 -> -1.2126816e+08
B35: Sub-Total - D | C35: =SUM(C34:C34) -> 25404407 | D35: =SUM(D34:D34) -> 0 | E35: =SUM(E34:E34) -> 25404407 | J35: =SUM(J34:J34) -> 1.2126816e+08 | L35: =D35-J35 -> -1.2126816e+08
A36: E | B36: Derived Items (UPVC doors & Windows) | C36: ='Derived Items_UPVC'!F40 -> 1.0921928e+08 | D36: =E36-C36 -> 0 | E36: ='Derived Items_UPVC'!F40 -> 1.0921928e+08
B37: Sub-Total - E | C37: =SUM(C36:C36) -> 1.0921928e+08 | D37: =SUM(D36:D36) -> 0 | E37: =SUM(E36:E36) -> 1.0921928e+08
A38: F | B38: Derived Items (RMC & other Misc Works) | D38: =E38-C38 -> 41887062 | E38: ='Derived Items_RMC & Others'!O45 -> 41887062
B39: Sub-Total - F | C39: =SUM(C38:C38) -> 0 | D39: =SUM(D38:D38) -> 41887062 | E39: =SUM(E38:E38) -> 41887062
A40: G | B40: NT #03 | D40: =E40-C40 -> 8502749.3 | E40: =NT_03!J10 -> 8502749.3
B41: Sub-Total - G | C41: =SUM(C40:C40) -> 0 | D41: =SUM(D40:D40) -> 8502749.3 | E41: =SUM(E40:E40) -> 8502749.3
A42: H | B42: Compound Wall Works | D42: =E42-C42 -> 42099257 | E42: ='Compound Wall Works'!G43 -> 42099257
B43: Sub-Total - H | C43: =SUM(C42:C42) -> 0 | D43: =SUM(D42:D42) -> 42099257 | E43: =SUM(E42:E42) -> 42099257
A44: I | B44: External Development Works | D44: =E44-C44 -> 107750645 | E44: ='Ext Dev. Works'!F89 -> 107750645
B45: Sub-Total - I | C45: =SUM(C44:C44) -> 0 | D45: =SUM(D44) -> 107750645 | E45: =SUM(E44) -> 107750645
B47: NT, Derived & Additional Scope of Works (VO#03) | C47: =C45+C43+C41+C39 -> 0 | D47: =D45+D43+D41+D39 -> 2.0023971e+08 | E47: =E45+E43+E41+E39 -> 2.0023971e+08
B49: Total Amount (Excl GST) | C49: =C47+C37+C35+C33+C30 -> 3.1961109e+09 | D49: =D47+D37+D35+D33+D30 -> 1.6887476e+08 | E49: =E47+E37+E35+E33+E30 -> 3.3649857e+09 | J49: =J19+J29+J35+#REF! -> #REF! | L49: =L19+L29+L35+#REF! -> #REF!

Sheet Part-A & B_BOQ
A1: BOQ FOR CIVIL & FINISHING WORKS
A2: Item No. | B2: Description of works | C2: UOM | D2: Rate | E2: As per VO#02 | K2: Current Variation | M2: As per Actual
E3: Quantity | H3: Amount (Rs.) | K3: Quantity | M3: Quantity | O3: Amount
E4: Ph - 1 | F4: Ph -2 | G4: Total | H4: Ph - 1 | I4: Ph -2 | J4: Total | K4: Ph 1 | L4: Ph 2 | M4: Ph 1 | N4: Ph 2
A5: A | B5: STRUCTURE WORKS
A7: 1 | B7: EARTHWORKS
B8: General Notes for all Excavation Items: Contractor shall take all required permissions from the appropriate authorities for Excavation, Blasting, Carting away materials etc. and shall bear all the expenses for the same.
B9: Rate shall include 1. Removal of all kinds of vegetation, small shrubs etc. If there are any shrubs, bushes, roots of the trees to be removed for min depth 1.5m including all necessary permissions. Lift & lead outside campus are to be considered to suit the local regulations. The necessary approval shall be taken for removal of trees with the consent of the clients if applicable. The contractor shall be fully responsible for liasoning with local authoritites, compliance to all the statutory obligations, including all labour lanes in force, facilities, policies etc. towards all employees , labour and under no circumstance nor any acting party pass on the responsiblitites of the contractor to the other contractor/clients.
B10: 2. Contractor shall get acquainted with site conditions, nature of soil and adopt suitable dewatering system as deemed fit for the nature of soil and prevailing water table and water collected by runoff or rain needs to be disposed off from the site. The rate shall include keeping the excavated surface dry till completion of the scope of work. Dewatered water/ Slush shall be drained out by suitable means to places not objected by civic authorities. The contractor shall submit the method statement for dewatering and the same shall be let out of the building premises through proper pipes & channels as required.
B11: 3. The rate shall include necessary general shoring, strutting with approved timber/steel accessories wherever necessary as approved by the Client / the Engineer.
B12: 4. Contour level to be taken jointly with the Project Manager and prior written approval be taken before starting any excavation/ filling at every 3 / 5 mt grids for arriving at the actual quantity using simpsons rule. Cost to include all and necessary royalty and other permission charges required to execute the works.
B13: 5. The rate shall include all necessary setting out of building, excavation line, barrication by grid/plot marking, survey by Total station, transfer of bench mark, etc., complete
B14: 6.The quoted rates includes seggregating of good quality excavated earth from the clay / silty soil and storing in designted area for further treatment within the site premises for future landscape purposes including preserving top 300 mm layer of existing soil to meet MOEF requirements.. No extra is payable towards double handling.
B15: 7. Quoted rates shall incldue the preparation of temporary access road / Pathways, cross over, foot path, tracks, hard standings, temporary ramp to approach the excavated level etc, and temporary drains, rerouting of existing roads, supporting systems for existing MEP services if any and re-routing if required, etc. complete. at no extra cost.
B16: 8. Carting away all types of excavated earth outside or within the site shall be included and environmental norms to be followed for discarding excavated material with submission of document of proof.
B17: 9. Soil shall be classified as three types for billing purpose.
B18: a.Classification under hard rock excavation item which requires chiselling with compressed air/mechanical equipment's,controlled blasting, chemical splitting, diamond cutting etc. with necessary mechanical equipment's and loose boulders which requires splitting and handling.
B19: b. Classification under soft/medium/ weathered rock excavation item which is non poclainable, can be excavated using rock breaker attachments to JCB/Poclain, manual chiselling, etc. and loose boulders removal without spliting etc.
... B25: 14. Qty. shall be arrived at after taking block levels taken prior to and after excavation. The below mentioned quantities are based on soil report and the quantities may vary as per site condition. Quantity mentioned is tentative and may vary to any extent depending upon underlying ground profile to be exposed during excavation.
A26: 1.01 | B26: INDIVIDUAL FOOTING / POCKET EXCAVATION
B27: Excavation in all types of soil including dense soil, laterite reddish brown/Laterite reddish brown with patches/ dense soildisintegrated/ weathered/ soft rock (Poclainable) for Footings / RAFT of columns, trenches for drains, etc., by mechanical means including manual excavation for levelling, dressing the edges, with all leads and lifts. Dewatering of both ground and surface water, removal of slurry generated while excavation and keeping the area free of water with necessary shoring, strutting, required for keeping earth in position etc, Note: PCC area shall be considered for measurement (Working space & provision of slopes if required for execution shall not be paid separately). Footings/ Rafts etc | C27: Cum | D27: 243 | E27: 2578.46 | F27: 1018.5 | G27: =SUM(E27:F27) -> 3596.96 | H27: =$D27*E27 -> 626565.78 | I27: =$D27*F27 -> 247495.5 | J27: =SUBTOTAL(9,H27:I27) -> 874061.28 | K27: =M27-E27 -> 9936.6924 | L27: =N27-F27 -> 5143.556 | M27: 12515.152 | N27: 6162.056 | O27: =(M27+N27)*$D27 -> 4538561.6
A28: 1.02 | B28: Specification & scope of work same as 1.01 but for Excavation in Hard rock / boulders (more than 1/2 Cum in size -Un poclainable) by chiselling/ wedging to required level for Raft, Footings of columns, Retaining walls, Core walls, catch pits, Lift pits,STP,UG tanks, trenches for drains, etc. to the required depth including all leads and lifts, dressing, grading, cleaning, excavating loose pockets directed and disposing etc. as per detailed specification and conforming to safety rules of Authority during the progress of work. Note: The percentage of voids to be deducted from stack measurement is 40% for hardrock or Initial levels will be taken before blasting hard rock and final levels will be taken after achieving required levels in presence of PIC. Note:PCC area shall be considered for measurement (Working space & provision of slopes if required for execution shall not be paid separately. Mode of measurement shall be by joint measurements/ levels before and after excavation). | C28: Cum | D28: 2774 | E28: 97 | F28: 48.5 | G28: =SUM(E28:F28) -> 145.5 | H28: =$D28*E28 -> 269078 | I28: =$D28*F28 -> 134539 | J28: =SUBTOTAL(9,H28:I28) -> 403617 | K28: =M28-E28 -> -97 | L28: =N28-F28 -> -48.5 | M28: 0 | N28: 0 | O28: =(M28+N28)*$D28 -> 0
A29: 1.02 | B29: BACKFILLING (with available earth) | D29: 0 | E29: 0 | F29: 0 | K29: =M29-E29 -> 0 | L29: =N29-F29 -> 0 | O29: =(M29+N29)*$D29 -> 0
B30: Supply and filling in foundations and the area whereever specified with approved good quality filling materials in plinths, area development etc. wherever specified in layers of not exceeding 150 mm thick including breaking clods,storing,transportation, double handling, watering, compacting each layer with vibratory compactor and at unaccessible places with wooden/steel rammers to achieve 90 to 95% proctor density at optimum moisture content, all leads and lifts, bailing/ pumping out of water to keep site dry while backfilling; cost shall include conveyance of all materials, labour, machinery etc. complete as directed.The rate to includes loading,unloading, hire and fuel charges for tools and plants and other incidental charges etc., complete. Cost to include all necessary royalty and other permission charges required to execute the works. With excavated earth available at site | C30: Cum | D30: 150 | E30: 15633.13 | F30: 2425 | G30: =SUM(E30:F30) -> 18058.13 | H30: =$D30*E30 -> 2344969.5 | I30: =$D30*F30 -> 363750 | J30: =SUBTOTAL(9,H30:I30) -> 2708719.5 | K30: =M30-E30 -> 0 | L30: =N30-F30 -> 0 | M30: 15633.13 | N30: 2425 | O30: =(M30+N30)*$D30 -> 2708719.5
A31: 1.03 | B31: Carting away surplus earth/excavated material/debris/rock and like materials outside the plot and disposing off the same to the designated areas identified by the local authorities / project managers for dumping of such material, including spreading, compacting etc.,as per the norms by the local authorities. Mode of measurement- where measurement is not possible by level. i) Soil - truck measurement less 20% for voids. ii) Hard Rock - truck measurement less 50% for voids iii) Debris - truck measurement less 30% for voids. | C31: Cum | D31: 278 | E31: 2425 | F31: 97 | G31: =SUM(E31:F31) -> 2522 | H31: =$D31*E31 -> 674150 | I31: =$D31*F31 -> 26966 | J31: =SUBTOTAL(9,H31:I31) -> 701116 | K31: =M31-E31 -> 0 | L31: =N31-F31 -> 0 | M31: 2425 | N31: 97 | O31: =(M31+N31)*$D31 -> 701116
E32: 0 | F32: 0 | K32: =M32-E32 -> 0 | L32: =N32-F32 -> 0 | O32: =(M32+N32)*$D32 -> 0
B33: Sub-Total | E33: 0 | F33: 0 | G33: 0 | H33: =SUM(H12:H32) -> 3914763.3 | I33: =SUM(I12:I32) -> 772750.5 | J33: =SUM(J12:J32) -> 4687513.8 | K33: =M33-E33 -> 0 | L33: =N33-F33 -> 0 | O33: =SUM(O12:O32) -> 7948397.1
A34: 2 | B34: ANTI-TERMITE TREATMENT WORKS | E34: 0 | F34: 0 | K34: =M34-E34 -> 0 | L34: =N34-F34 -> 0 | O34: =(M34+N34)*$D34 -> 0
A35: i | B35: Providing Pre-constructional anti- termite treatment and creating a chemical barrier to the building by injecting chemical emulsion of required concentrations under grade slab and Grade beam, around the Plinth, Plinth filling, trenches, junction of wall and floor, Retaining / side walls of basement floor, external perimeter of building, surrounding of pipes, expansion joints, below UG sump and etc.as per instructions of chemical manufacturer and all as directed. The treatment shall be carried out strictly in accordance with the technical specification and conforming to IS 6313 or equivalent BS specification. The chemical to be used as insecticides for the treatment shall be 50% EC (Imidacloprid 30.5 SC)and the application shall be dilute one part of chemical 50% EC with 49 parts of water to get 1% emulsion and strictly in accordance with the manufacturer's specification. Note : Measurement taken along external periphery of the building. Treatment shall extend to a width of 1m around the building. (Including 10 years warranty). | C35: Sqm | D35: 96 | E35: 10325.65 | F35: 1777.04 | G35: =SUM(E35:F35) -> 12102.69 | H35: =$D35*E35 -> 991262.4 | I35: =$D35*F35 -> 170595.84 | J35: =SUBTOTAL(9,H35:I35) -> 1161858.2 | K35: =M35-E35 -> 0 | L35: =N35-F35 -> 3484.542 | M35: 10325.65 | N35: 5261.582 | O35: =(M35+N35)*$D35 -> 1496374.3
E36: 0 | F36: 0 | G36: 0 | K36: =M36-E36 -> 0 | L36: =N36-F36 -> 0 | O36: =(M36+N36)*$D36 -> 0
B37: Sub-Total | E37: 0 | F37: 0 | G37: 0 | H37: =SUM(H35:H36) -> 991262.4 | I37: =SUM(I35:I36) -> 170595.84 | J37: =SUM(J35:J36) -> 1161858.2 | K37: =M37-E37 -> 0 | L37: =N37-F37 -> 0 | O37: =SUM(O35:O36) -> 1496374.3
E38: 0 | F38: 0 | G38: 0 | K38: =M38-E38 -> 0 | L38: =N38-F38 -> 0 | O38: =(M38+N38)*$D38 -> 0
A39: 2 | B39: PLAIN CEMENT CONCRETE WORKS | E39: 0 | F39: 0 | G39: 0 | J39: =SUM(H39+I39) -> 0 | K39: =M39-E39 -> 0 | L39: =N39-F39 -> 0 | O39: =(M39+N39)*$D39 -> 0
B40: Unless otherwise specified rates quoted for all PCC works shall include the following : | E40: 0 | F40: 0 | G40: 0 | J40: =SUM(H40+I40) -> 0 | K40: =M40-E40 -> 0 | L40: =N40-F40 -> 0 | O40: =(M40+N40)*$D40 -> 0
B41: Cost of all materials, labour, equipment / tools & plants required, lead and lifts, conveyance, infrastructure facilities required etc. | E41: 0 | F41: 0 | G41: 0 | J41: =SUM(H41+I41) -> 0 | K41: =M41-E41 -> 0 | L41: =N41-F41 -> 0 | O41: =(M41+N41)*$D41 -> 0
B42: The contractors are particularly advised to study the relevant drawings carefully before quoting. | E42: 0 | F42: 0 | G42: 0 | J42: =SUM(H42+I42) -> 0 | K42: =M42-E42 -> 0 | L42: =N42-F42 -> 0 | O42: =(M42+N42)*$D42 -> 0
B43: Minimum cement content for concrete shall be as per cement constants specified in the Technical specification. | E43: 0 | F43: 0 | G43: 0 | J43: =SUM(H43+I43) -> 0 | K43: =M43-E43 -> 0 | L43: =N43-F43 -> 0 | O43: =(M43+N43)*$D43 -> 0
B44: Cost of suitable form work as per site requirement. | E44: 0 | F44: 0 | G44: 0 | J44: =SUM(H44+I44) -> 0 | K44: =M44-E44 -> 0 | L44: =N44-F44 -> 0 | O44: =(M44+N44)*$D44 -> 0
B45: Adequate protection to edges and corners of Plain Cement Concrete works from damage during construction. | E45: 0 | F45: 0 | G45: 0 | J45: =SUM(H45+I45) -> 0 | K45: =M45-E45 -> 0 | L45: =N45-F45 -> 0 | O45: =(M45+N45)*$D45 -> 0
B46: Keeping the work, well watered for 3-5 days for plain cement concrete works after casting and it shall confirm to IS Specification. | E46: 0 | F46: 0 | G46: 0 | J46: =SUM(H46+I46) -> 0 | K46: =M46-E46 -> 0 | L46: =N46-F46 -> 0 | O46: =(M46+N46)*$D46 -> 0
B47: Coarse graded sand/ manufactured sand of approved make shall be used for all concrete works. | E47: 0 | F47: 0 | G47: 0 | J47: =SUM(H47+I47) -> 0 | K47: =M47-E47 -> 0 | L47: =N47-F47 -> 0 | O47: =(M47+N47)*$D47 -> 0
B48: Machine crushed coarse graded aggregate shall be hard broken blue granite of sizes specified. | E48: 0 | F48: 0 | G48: 0 | J48: =SUM(H48+I48) -> 0 | K48: =M48-E48 -> 0 | L48: =N48-F48 -> 0 | O48: =(M48+N48)*$D48 -> 0
B49: Cement for all concrete works shall only be High strength ordinary portland cement Grade-53. | E49: 0 | F49: 0 | G49: 0 | J49: =SUM(H49+I49) -> 0 | K49: =M49-E49 -> 0 | L49: =N49-F49 -> 0 | O49: =(M49+N49)*$D49 -> 0
B50: Minimum cement content for specified design mix shall be in accordance with specification. Minimum cement content will be the same as specified in the Technical specification Irrespective of grade of cement used. (Design mix shall be as approved by the Structural Consultant. GGBS can be considered up to 50% of the overall cementious content in concrete mix design for structural elements.) | E50: 0 | F50: 0 | G50: 0 | J50: =SUM(H50+I50) -> 0 | K50: =M50-E50 -> 0 | L50: =N50-F50 -> 0 | O50: =(M50+N50)*$D50 -> 0
B51: Providing and laying plain cement concrete at any heights and levels including the cost of all materials , labour, leads and lifts, tools and plant, machinery as per specification with necessary shuttering etc complete. In the concreting works if water table is encountered or water collected by surface runoff, then the rate for concreting should include the cost of dewatering up to the final set of cement. The concrete shall be produced at site using batching plant / weigh batcher at site including any pumping if required. The fine aggregates shall be manufactured sand. | E51: 0 | F51: 0 | G51: 0 | J51: =SUM(H51+I51) -> 0 | K51: =M51-E51 -> 0 | L51: =N51-F51 -> 0 | O51: =(M51+N51)*$D51 -> 0
B52: All plain cement concrete works shall be done in accordance with technical specification. | E52: 0 | F52: 0 | G52: 0 | J52: =SUM(H52+I52) -> 0 | K52: =M52-E52 -> 0 | L52: =N52-F52 -> 0 | O52: =(M52+N52)*$D52 -> 0
A53: 2.1 | B53: Providing and laying Plum concrete using lean concrete of grade M5 wherever specified using cement, fine aggregates, 40mm down size metal and boulders of 150mm (proportion 60: 40 for concrete : boulder) including sub grade base preparation, levelling, laying and placing of concrete and boulders in sequential manner to achieve a solid mass including all leads and lifts, rough finishing at the top surface, curing and temporary formwork if necessary etc., complete at all levels as directed by Client / the Engineer and as per drawings. | C53: Cum | D53: 5787 | E53: 183.33 | F53: 40.74 | G53: =SUM(E53:F53) -> 224.07 | H53: =$D53*E53 -> 1060930.7 | I53: =$D53*F53 -> 235762.38 | J53: =SUBTOTAL(9,H53:I53) -> 1296693.1 | K53: =M53-E53 -> 1115.823 | L53: =N53-F53 -> 15 | M53: 1299.153 | N53: 55.74 | O53: =(M53+N53)*$D53 -> 7840765.9
A54: 2.2 | B54: Providing and laying plain cement concrete of grade M10 at all levels using coarse graded aggregate of 20mm and down size, fine aggregates, cement for levelling course under footings, flooring, steps, walls, platform, for external development works and at locations specified etc. including sub grade base preparation, form work wherever necessary, levelling, compacting, curing, including all leads and lifts, rough finishing at the top surface etc. all complete, as directed by Client / the Engineer and as per drawings. | D54: 0 | E54: 0 | F54: 0 | G54: =SUM(E54:F54) -> 0 | H54: =E54*$D54 -> 0 | I54: =F54*$D54 -> 0 | J54: =SUM(H54+I54) -> 0 | K54: =M54-E54 -> 0 | L54: =N54-F54 -> 0 | O54: =(M54+N54)*$D54 -> 0
A55: i | B55: Below raft, Footings, Grade Slab etc | C55: Cum | D55: 6027 | E55: 1507.38 | F55: 365.69 | G55: =SUM(E55:F55) -> 1873.07 | H55: =$D55*E55 -> 9084979.3 | I55: =$D55*F55 -> 2204013.6 | J55: =SUBTOTAL(9,H55:I55) -> 11288993 | K55: =M55-E55 -> 0 | L55: =N55-F55 -> 0 | M55: 1507.38 | N55: 365.69 | O55: =(M55+N55)*$D55 -> 11288993
A56: 2.3 | B56: Providing and laying P.C.C.of grade M15 of specified thickness wherever specified at all levels using fine aggregate, cement, 20mm and downsize aggregate including cleaning, subgrade preparation, compaction, levelling, all leads and lifts, rough finishing at the top surface, curing and shuttering if necessary etc., complete as per drawings and as directed by Client / the Engineer. | D56: 0 | E56: 0 | F56: 0 | G56: =SUM(E56:F56) -> 0 | H56: =E56*$D56 -> 0 | I56: =F56*$D56 -> 0 | J56: =SUM(H56+I56) -> 0 | K56: =M56-E56 -> 0 | L56: =N56-F56 -> 0 | O56: =(M56+N56)*$D56 -> 0
A57: i | B57: DPC , Copings, shaft screed, cill concrete, filled up ramps etc., | C57: Cum | D57: 6253 | E57: 69.84 | F57: 15.52 | G57: =SUM(E57:F57) -> 85.36 | H57: =$D57*E57 -> 436709.52 | I57: =$D57*F57 -> 97046.56 | J57: =SUBTOTAL(9,H57:I57) -> 533756.08 | K57: =M57-E57 -> -69.84 | L57: =N57-F57 -> -15.52 | N57: 0 | O57: =(M57+N57)*$D57 -> 0
B58: Sub-Total | E58: 0 | F58: 0 | G58: 0 | H58: =SUM(H39:H57) -> 10582619 | I58: =SUM(I39:I57) -> 2536822.6 | J58: =SUM(J39:J57) -> 13119442 | K58: =M58-E58 -> 0 | L58: =N58-F58 -> 0 | O58: =SUM(O39:O57) -> 19129759
E59: 0 | F59: 0 | G59: 0 | K59: =M59-E59 -> 0 | L59: =N59-F59 -> 0 | O59: =(M59+N59)*$D59 -> 0
A60: 3 | B60: REINFORCED CEMENT CONCRETE | E60: 0 | F60: 0 | G60: 0 | K60: =M60-E60 -> 0 | L60: =N60-F60 -> 0 | O60: =(M60+N60)*$D60 -> 0
B61: Unless otherwise specified rates quoted for all RCC works shall include the following: | E61: 0 | F61: 0 | G61: 0 | K61: =M61-E61 -> 0 | L61: =N61-F61 -> 0 | O61: =(M61+N61)*$D61 -> 0
B62: Cost of all materials, labour, equipment / tools & plants required, conveyance, infrastructure facilities required etc. | E62: 0 | F62: 0 | G62: 0 | K62: =M62-E62 -> 0 | L62: =N62-F62 -> 0 | O62: =(M62+N62)*$D62 -> 0
B63: All RCC items include batch weighing of cement and aggregates. | E63: 0 | F63: 0 | G63: 0 | K63: =M63-E63 -> 0 | L63: =N63-F63 -> 0 | O63: =(M63+N63)*$D63 -> 0
B64: For all RCC works cement concrete shall be of approved design mix. | E64: 0 | F64: 0 | G64: 0 | K64: =M64-E64 -> 0 | L64: =N64-F64 -> 0 | O64: =(M64+N64)*$D64 -> 0
B65: All concrete used for reinforced concrete work (structural concrete) shall be "Controlled concrete". Contractors shall submit drawings showing the scheme of form work system adopted (shuttering) for all structural elements at various levels as indicated in drawings and this shall be obligatory. 'The Contractor shall maintain at site, cube testing machine in good working order, sieves, slump cone, graduated cylinder and weights, verticality laser machine, scales and other equipment's for material testing. | E65: 0 | F65: 0 | G65: 0 | K65: =M65-E65 -> 0 | L65: =N65-F65 -> 0 | O65: =(M65+N65)*$D65 -> 0
B66: Form work (which shall be measured and paid separately under relevant item) include splayed edges, notching, allowances for overlaps and passing at angles, battens, strutting, bolting, wedging, casing, rocking, centring, boxing, shuttering, propping strut braces etc., removal thereof and dressing the shuttering with oil to prevent, cement sticking to shutter faces. Form work shall be either straight, curved, plain or tapered and also with provision for specified slopes, if directed. Wind tie bolts for wall shuttering. | E66: 0 | F66: 0 | G66: 0 | K66: =M66-E66 -> 0 | L66: =N66-F66 -> 0 | O66: =(M66+N66)*$D66 -> 0
B67: Keeping the work, well watered for 10 days after casting and it shall confirm to IS Specification. | E67: 0 | F67: 0 | G67: 0 | K67: =M67-E67 -> 0 | L67: =N67-F67 -> 0 | O67: =(M67+N67)*$D67 -> 0
B68: Placing in position any inserts like bolts, plates, sleeves, plugs for fixing window frames in RCC members, pipes etc. | E68: 0 | F68: 0 | G68: 0 | K68: =M68-E68 -> 0 | L68: =N68-F68 -> 0 | O68: =(M68+N68)*$D68 -> 0
B69: The contractors are particularly advised to study the relevant drawings carefully before quoting. | E69: 0 | F69: 0 | G69: 0 | K69: =M69-E69 -> 0 | L69: =N69-F69 -> 0 | O69: =(M69+N69)*$D69 -> 0
B70: Adequate protection to corners and sides from damage during the construction. | E70: 0 | F70: 0 | G70: 0 | K70: =M70-E70 -> 0 | L70: =N70-F70 -> 0 | O70: =(M70+N70)*$D70 -> 0
B71: Consolidation using vibrators of approved type as directed. | E71: 0 | F71: 0 | G71: 0 | K71: =M71-E71 -> 0 | L71: =N71-F71 -> 0 | O71: =(M71+N71)*$D71 -> 0
B72: Work on all floors at levels as per drawing. | E72: 0 | F72: 0 | G72: 0 | K72: =M72-E72 -> 0 | L72: =N72-F72 -> 0 | O72: =(M72+N72)*$D72 -> 0
... B99: All Reinforced cement concrete works shall be done in accordance with technical specification. | E99: 0 | F99: 0 | G99: 0 | K99: =M99-E99 -> 0 | L99: =N99-F99 -> 0 | O99: =(M99+N99)*$D99 -> 0
E100: 0 | F100: 0 | G100: 0 | K100: =M100-E100 -> 0 | L100: =N100-F100 -> 0 | O100: =(M100+N100)*$D100 -> 0
B101: Providing & laying plant mixed design mix reinforced cement concrete conforming to grades as specified in (IS 456 - 2000) and as per specifications mentioned below at all levels using 20mm & down size aggregates, fine aggregates, OPC, necessary admixtures approved by Consultants (Conplast SP 430SRV from Fosroc or equivalent), including designing the mix, trial cubes, accelerated curing, weigh batching, mechanical mixing, transporting, pumping and placing at all levels, excluding the cost of steel reinforcement, centring, shuttering but inclusive of cost towards pumping using line pump or boom placer, scaffolding, compacting with vibrators, construction joint treatments, curing and hacking the exposed surfaces wherever required to receive plaster or floated steel trowelled surface whenever specified. The rate shall include cost of arrangements to provide recesses to slabs, columns, walls and placing and securing properly within the formwork sleeves and / or opening in slabs, construction joints, laying to required shape, size and slope all as per drawings. The mix proportion of cement with that of GGBS shall be confirming to latest IS standards. | E101: 0 | F101: 0 | G101: 0 | K101: =M101-E101 -> 0 | L101: =N101-F101 -> 0 | O101: =(M101+N101)*$D101 -> 0
B102: The rate shall include providing and fixing the required PVC sleeves up to 200 mm dia pockets and opening etc., cleaning the site debris stacking the material, hoisting equipment's, shutter accessories and fixing pipe / plates / inserts in perfect size level , plumb etc. as directed by Engineer In Charge and as per technical specifications in the tender. Repairing / replacing the formwork, filling all the holes created due to shuttering / sleeves provided for passage of plumbing, FF pipes / Electrical cables with approved non shrink filler material etc. complete to the satisfaction of Client / the Engineer. Hacking of RCC faces as specified and directed by Engineer In Charge to be included in quoted rate of RCC. | E102: 0 | F102: 0 | G102: 0 | K102: =M102-E102 -> 0 | L102: =N102-F102 -> 0 | O102: =(M102+N102)*$D102 -> 0
B103: Cost to include appropriate dewatering wherever necessary, cost of all materials, labours, all lead and lifts, tools, plant and machinery, hire and fuel charges and all other incidental charges etc., all as per specifications, drawings and as directed. | E103: 0 | F103: 0 | G103: 0 | K103: =M103-E103 -> 0 | L103: =N103-F103 -> 0 | O103: =(M103+N103)*$D103 -> 0
E104: 0 | F104: 0 | G104: 0 | K104: =M104-E104 -> 0 | L104: =N104-F104 -> 0 | O104: =(M104+N104)*$D104 -> 0
A105: 3.1 | B105: REINFORCED CEMENT CONCRETE WORKS : | E105: 0 | F105: 0 | G105: 0 | K105: =M105-E105 -> 0 | L105: =N105-F105 -> 0 | O105: =(M105+N105)*$D105 -> 0
B106: M30 Grade for all structural elements unless specified otherwise | E106: 0 | F106: 0 | G106: 0 | K106: =M106-E106 -> 0 | L106: =N106-F106 -> 0 | O106: =(M106+N106)*$D106 -> 0
A107: 3.1.1a | B107: Foundations for all vertical elements including independent, combined, raft, etc; | C107: Cum | D107: 6835 | E107: 10859.15 | F107: 2518.12 | G107: =SUM(E107:F107) -> 13377.27 | H107: =$D107*E107 -> 74222290 | I107: =$D107*F107 -> 17211350 | J107: =SUBTOTAL(9,H107:I107) -> 91433640 | K107: =M107-E107 -> -545.11564 | L107: =N107-F107 -> 580.958 | M107: 10314.034 | N107: 3099.078 | O107: =(M107+N107)*$D107 -> 91678623
A108: b | B108: Grade slab | C108: Cum | D108: 6835 | E108: 1132.96 | F108: 251.23 | G108: =SUM(E108:F108) -> 1384.19 | H108: =$D108*E108 -> 7743781.6 | I108: =$D108*F108 -> 1717157 | J108: =SUBTOTAL(9,H108:I108) -> 9460938.7 | K108: =M108-E108 -> 0 | L108: =N108-F108 -> 0 | M108: 1132.96 | N108: 251.23 | O108: =(M108+N108)*$D108 -> 9460938.7
A109: c | B109: Retaining Wall | C109: Cum | D109: 6835 | E109: 386.5 | F109: 463.66 | G109: =SUM(E109:F109) -> 850.16 | H109: =$D109*E109 -> 2641727.5 | I109: =$D109*F109 -> 3169116.1 | J109: =SUBTOTAL(9,H109:I109) -> 5810843.6 | K109: =M109-E109 -> 0 | L109: =N109-F109 -> 0 | M109: 386.5 | N109: 463.66 | O109: =(M109+N109)*$D109 -> 5810843.6
A110: d | B110: Ramp Beam | C110: Cum | D110: 6835 | E110: 29.1 | F110: 19.4 | G110: =SUM(E110:F110) -> 48.5 | H110: =$D110*E110 -> 198898.5 | I110: =$D110*F110 -> 132599 | J110: =SUBTOTAL(9,H110:I110) -> 331497.5 | K110: =M110-E110 -> 163.881 | L110: =N110-F110 -> 0 | M110: 192.981 | N110: 19.4 | O110: =(M110+N110)*$D110 -> 1451624.1
A111: e | B111: Ramp slab | C111: Cum | D111: 6835 | E111: 549.02 | F111: 0 | G111: =SUM(E111:F111) -> 549.02 | H111: =$D111*E111 -> 3752551.7 | I111: =$D111*F111 -> 0 | J111: =SUBTOTAL(9,H111:I111) -> 3752551.7 | K111: =M111-E111 -> -162.131 | L111: =N111-F111 -> 0 | M111: 386.889 | N111: 0 | O111: =(M111+N111)*$D111 -> 2644386.3
A112: f | B112: Pedestals | C112: Cum | D112: 6835 | E112: 161.99 | F112: 40.74 | G112: =SUM(E112:F112) -> 202.73 | H112: =$D112*E112 -> 1107201.7 | I112: =$D112*F112 -> 278457.9 | J112: =SUBTOTAL(9,H112:I112) -> 1385659.6 | K112: =M112-E112 -> 0 | L112: =N112-F112 -> 0 | M112: 161.99 | N112: 40.74 | O112: =(M112+N112)*$D112 -> 1385659.5
A113: g | B113: Trenches / Ramp drain | C113: Cum | D113: 6835 | E113: 69.84 | F113: 34.92 | G113: =SUM(E113:F113) -> 104.76 | H113: =$D113*E113 -> 477356.4 | I113: =$D113*F113 -> 238678.2 | J113: =SUBTOTAL(9,H113:I113) -> 716034.6 | K113: =M113-E113 -> 0 | L113: =N113-F113 -> 0 | M113: 69.84 | N113: 34.92 | O113: =(M113+N113)*$D113 -> 716034.6
A114: h | B114: Lintels | C114: Cum | D114: 6835 | E114: 53.35 | F114: 9.7 | G114: =SUM(E114:F114) -> 63.05 | H114: =$D114*E114 -> 364647.25 | I114: =$D114*F114 -> 66299.5 | J114: =SUBTOTAL(9,H114:I114) -> 430946.75 | K114: =M114-E114 -> 0 | L114: =N114-F114 -> 0 | M114: 53.35 | N114: 9.7 | O114: =(M114+N114)*$D114 -> 430946.75
A115: i | B115: Parapet wall | C115: Cum | D115: 6835 | E115: 353.08 | F115: 79.54 | G115: =SUM(E115:F115) -> 432.62 | H115: =$D115*E115 -> 2413301.8 | I115: =$D115*F115 -> 543655.9 | J115: =SUBTOTAL(9,H115:I115) -> 2956957.7 | K115: =M115-E115 -> 0 | L115: =N115-F115 -> 0 | M115: 353.08 | N115: 79.54 | O115: =(M115+N115)*$D115 -> 2956957.7
A116: 3.1.2 | B116: Domestic and Fire Fighting Underground Sumps | D116: 0 | E116: 0 | F116: 0 | G116: =SUM(E116:F116) -> 0 | H116: =E116*$D116 -> 0 | I116: =F116*$D116 -> 0 | J116: =SUM(H116+I116) -> 0 | K116: =M116-E116 -> 0 | L116: =N116-F116 -> 0 | M116: 0 | N116: 0 | O116: =(M116+N116)*$D116 -> 0
A117: a | B117: Bottom Slab | C117: Cum | D117: 6835 | E117: 399.64 | F117: 0 | G117: =SUM(E117:F117) -> 399.64 | H117: =$D117*E117 -> 2731539.4 | I117: =$D117*F117 -> 0 | J117: =SUBTOTAL(9,H117:I117) -> 2731539.4 | K117: =M117-E117 -> 0.002 | L117: =N117-F117 -> 0 | M117: 399.642 | N117: 0 | O117: =(M117+N117)*$D117 -> 2731553.1
A118: b | B118: Walls | C118: Cum | D118: 6835 | E118: 379.27 | F118: 0 | G118: =SUM(E118:F118) -> 379.27 | H118: =$D118*E118 -> 2592310.4 | I118: =$D118*F118 -> 0 | J118: =SUBTOTAL(9,H118:I118) -> 2592310.4 | K118: =M118-E118 -> 0 | L118: =N118-F118 -> 0 | M118: 379.27 | N118: 0 | O118: =(M118+N118)*$D118 -> 2592310.4
A119: c | B119: Top Slab | C119: Cum | D119: 6835 | E119: 160.05 | F119: 0 | G119: =SUM(E119:F119) -> 160.05 | H119: =$D119*E119 -> 1093941.8 | I119: =$D119*F119 -> 0 | J119: =SUBTOTAL(9,H119:I119) -> 1093941.8 | K119: =M119-E119 -> 0 | L119: =N119-F119 -> 0 | M119: 160.05 | N119: 0 | O119: =(M119+N119)*$D119 -> 1093941.7
A120: d | B120: Staircase | C120: Cum | D120: 6835 | E120: 7.76 | F120: 0 | G120: =SUM(E120:F120) -> 7.76 | H120: =$D120*E120 -> 53039.6 | I120: =$D120*F120 -> 0 | J120: =SUBTOTAL(9,H120:I120) -> 53039.6 | K120: =M120-E120 -> 0 | L120: =N120-F120 -> 0 | M120: 7.76 | N120: 0 | O120: =(M120+N120)*$D120 -> 53039.6
A121: 3.1.3 | B121: STP | D121: 0 | E121: 0 | F121: 0 | G121: =SUM(E121:F121) -> 0 | H121: =E121*$D121 -> 0 | I121: =F121*$D121 -> 0 | J121: =SUM(H121+I121) -> 0 | K121: =M121-E121 -> 0 | L121: =N121-F121 -> 0 | N121: 0 | O121: =(M121+N121)*$D121 -> 0
A122: a | B122: Bottom Slab | C122: Cum | D122: 6835 | E122: 649.9 | F122: 0 | G122: =SUM(E122:F122) -> 649.9 | H122: =$D122*E122 -> 4442066.5 | I122: =$D122*F122 -> 0 | J122: =SUBTOTAL(9,H122:I122) -> 4442066.5 | K122: =M122-E122 -> -310.817 | L122: =N122-F122 -> 0 | M122: 339.083 | N122: 0 | O122: =(M122+N122)*$D122 -> 2317632.3
A123: b | B123: Walls | C123: Cum | D123: 6835 | E123: 634.38 | F123: 0 | G123: =SUM(E123:F123) -> 634.38 | H123: =$D123*E123 -> 4335987.3 | I123: =$D123*F123 -> 0 | J123: =SUBTOTAL(9,H123:I123) -> 4335987.3 | K123: =M123-E123 -> 4.563 | L123: =N123-F123 -> 0 | M123: 638.943 | N123: 0 | O123: =(M123+N123)*$D123 -> 4367175.4
A124: c | B124: Top Slab | C124: Cum | D124: 6835 | E124: 259.96 | F124: 0 | G124: =SUM(E124:F124) -> 259.96 | H124: =$D124*E124 -> 1776826.6 | I124: =$D124*F124 -> 0 | J124: =SUBTOTAL(9,H124:I124) -> 1776826.6 | K124: =M124-E124 -> 8.806 | L124: =N124-F124 -> 0 | M124: 268.766 | N124: 0 | O124: =(M124+N124)*$D124 -> 1837015.6
A125: 3.1.4 | B125: OHT | D125: 0 | E125: 0 | F125: 0 | G125: 0 | H125: =E125*$D125 -> 0 | I125: =F125*$D125 -> 0 | J125: =SUM(H125+I125) -> 0 | K125: =M125-E125 -> 0 | L125: =N125-F125 -> 0 | N125: 0 | O125: =(M125+N125)*$D125 -> 0
A126: a | B126: Bottom Slab | C126: Cum | D126: 6835 | E126: 67.9 | F126: 19.4 | G126: =SUM(E126:F126) -> 87.3 | H126: =$D126*E126 -> 464096.5 | I126: =$D126*F126 -> 132599 | J126: =SUBTOTAL(9,H126:I126) -> 596695.5 | K126: =M126-E126 -> 0 | L126: =N126-F126 -> 0 | M126: 67.9 | N126: 19.4 | O126: =(M126+N126)*$D126 -> 596695.5
A127: b | B127: Walls | C127: Cum | D127: 6835 | E127: 176.54 | F127: 50.44 | G127: =SUM(E127:F127) -> 226.98 | H127: =$D127*E127 -> 1206650.9 | I127: =$D127*F127 -> 344757.4 | J127: =SUBTOTAL(9,H127:I127) -> 1551408.3 | K127: =M127-E127 -> 0 | L127: =N127-F127 -> 0 | M127: 176.54 | N127: 50.44 | O127: =(M127+N127)*$D127 -> 1551408.3
A128: c | B128: Top Slab | C128: Cum | D128: 6835 | E128: 67.9 | F128: 19.4 | G128: =SUM(E128:F128) -> 87.3 | H128: =$D128*E128 -> 464096.5 | I128: =$D128*F128 -> 132599 | J128: =SUBTOTAL(9,H128:I128) -> 596695.5 | K128: =M128-E128 -> 0 | L128: =N128-F128 -> 0 | M128: 67.9 | N128: 19.4 | O128: =(M128+N128)*$D128 -> 596695.5
A129: 3.1.5 | B129: Sub-Soil Well along with the retaining wall including bottom and top slabs | D129: 0 | E129: 0 | F129: 0 | G129: =SUM(E129:F129) -> 0 | H129: =E129*$D129 -> 0 | I129: =F129*$D129 -> 0 | J129: =SUM(H129+I129) -> 0 | K129: =M129-E129 -> 0 | L129: =N129-F129 -> 0 | N129: 0 | O129: =(M129+N129)*$D129 -> 0
A130: a | B130: Bottom Slab | C130: Cum | D130: 6835 | E130: 14.55 | F130: 9.7 | G130: =SUM(E130:F130) -> 24.25 | H130: =$D130*E130 -> 99449.25 | I130: =$D130*F130 -> 66299.5 | J130: =SUBTOTAL(9,H130:I130) -> 165748.75 | K130: =M130-E130 -> -14.54 | L130: =N130-F130 -> -9.7 | M130: 0.01 | N130: 0 | O130: =(M130+N130)*$D130 -> 68.35
A131: b | B131: Walls | C131: Cum | D131: 6835 | E131: 29.1 | F131: 19.4 | G131: =SUM(E131:F131) -> 48.5 | H131: =$D131*E131 -> 198898.5 | I131: =$D131*F131 -> 132599 | J131: =SUBTOTAL(9,H131:I131) -> 331497.5 | K131: =M131-E131 -> -29.09 | L131: =N131-F131 -> -19.4 | M131: 0.01 | N131: 0 | O131: =(M131+N131)*$D131 -> 68.35
A132: c | B132: Top Slab | C132: Cum | D132: 6835 | E132: 14.55 | F132: 9.7 | G132: =SUM(E132:F132) -> 24.25 | H132: =$D132*E132 -> 99449.25 | I132: =$D132*F132 -> 66299.5 | J132: =SUBTOTAL(9,H132:I132) -> 165748.75 | K132: =M132-E132 -> -14.54 | L132: =N132-F132 -> -9.7 | M132: 0.01 | N132: 0 | O132: =(M132+N132)*$D132 -> 68.35
...

Sheet Derived Items_RMC & Others
A1: Project - Provident Ecopolitan - Ph 1 & Ph 2
A2: Subject - Derived Items
A3: Item No. | B3: Description of works | C3: UOM | D3: Rate | E3: As per VO#02 | K3: Current Variation | M3: As per Actual
E4: Quantity | H4: Amount (Rs.) | K4: Quantity | M4: Quantity | O4: Amount
E5: Ph 1 | F5: Ph 2 | G5: Total Qty | H5: Ph - 1 | I5: Ph -2 | J5: Total | K5: Ph 1 | L5: Ph 2 | M5: Ph 1 | N5: Ph 2
B6: Derived Items | E6: 0 | F6: 0 | G6: 0 | H6: 0 | I6: 0 | J6: 0
A7: 3.2.1 | B7: Columns and Shear walls at all levels
B8: M40 grade (Item Description same as Sl No. 3.2.1 f)
A9: d | B9: 2nd floor | C9: Cum | D9: 7386 | E9: 0 | F9: 0 | G9: 0 | H9: 0 | I9: 0 | K9: =M9-E9 -> 371.51 | L9: =N9-F9 -> 0 | M9: 371.51 | N9: 0 | O9: =(M9+N9)*D9 -> 2743972.9
A10: e | B10: 3rd floor | C10: Cum | D10: 7386 | E10: 0 | F10: 0 | G10: 0 | H10: 0 | I10: 0 | K10: =M10-E10 -> 371.51 | L10: =N10-F10 -> 0 | M10: 371.51 | N10: 0 | O10: =(M10+N10)*D10 -> 2743972.9
A11: 3.2.2 | B11: Core Walls and Staircase walls at RCC core area in all levels | E11: 0 | F11: 0 | G11: 0 | H11: 0 | I11: 0 | K11: =M11-E11 -> 0 | L11: =N11-F11 -> 0 | M11: 0 | N11: 0 | O11: =(M11+N11)*D11 -> 0
B12: M30 Grade (Item Description same as Sl No. 3.2.2 i) | E12: 0 | F12: 0 | G12: 0 | H12: 0 | I12: 0 | K12: =M12-E12 -> 0 | L12: =N12-F12 -> 0 | M12: 0 | N12: 0 | O12: =(M12+N12)*D12 -> 0
A13: c | B13: 1st Floor | C13: Cum | D13: 7066 | E13: 0 | F13: 0 | G13: 0 | H13: 0 | I13: 0 | K13: =M13-E13 -> 0 | L13: =N13-F13 -> 67.951 | M13: 0 | N13: 67.951 | O13: =(M13+N13)*D13 -> 480141.77
A14: d | B14: 2nd Floor | C14: Cum | D14: 7066 | E14: 0 | F14: 0 | G14: 0 | H14: 0 | I14: 0 | K14: =M14-E14 -> 0 | L14: =N14-F14 -> 61.448 | M14: 0 | N14: 61.448 | O14: =(M14+N14)*D14 -> 434191.57
A15: e | B15: 3rd Floor | C15: Cum | D15: 7066 | E15: 0 | F15: 0 | G15: 0 | H15: 0 | I15: 0 | K15: =M15-E15 -> 0 | L15: =N15-F15 -> 61.448 | M15: 0 | N15: 61.448 | O15: =(M15+N15)*D15 -> 434191.57
A16: f | B16: 4th Floor | C16: Cum | D16: 7066 | E16: 0 | F16: 0 | G16: 0 | H16: 0 | I16: 0 | K16: =M16-E16 -> 0 | L16: =N16-F16 -> 61.448 | M16: 0 | N16: 61.448 | O16: =(M16+N16)*D16 -> 434191.57
A17: g | B17: 5th Floor | C17: Cum | D17: 7066 | E17: 0 | F17: 0 | G17: 0 | H17: 0 | I17: 0 | K17: =M17-E17 -> 0 | L17: =N17-F17 -> 61.448 | M17: 0 | N17: 61.448 | O17: =(M17+N17)*D17 -> 434191.57
A18: h | B18: 6th floor | C18: Cum | D18: 7066 | E18: 0 | F18: 0 | G18: 0 | H18: 0 | I18: 0 | K18: =M18-E18 -> 228.64467 | L18: =N18-F18 -> 61.448 | M18: 228.64467 | N18: 61.448 | O18: =(M18+N18)*D18 -> 2049794.8
A19: 3.2.3 | B19: RC Walls | E19: 0 | F19: 0 | G19: 0 | H19: 0 | I19: 0 | K19: =M19-E19 -> 0 | L19: =N19-F19 -> 0 | M19: 0 | N19: 0 | O19: =(M19+N19)*D19 -> 0
B20: M30 grade- (Item Description same as Sl No. 3.2.3 C) | E20: 0 | F20: 0 | G20: 0 | H20: 0 | I20: 0 | K20: =M20-E20 -> 0 | L20: =N20-F20 -> 0 | M20: 0 | N20: 0 | O20: =(M20+N20)*D20 -> 0
A21: a | B21: 1st floor | C21: Cum | D21: 7066 | E21: 0 | F21: 0 | G21: 0 | H21: 0 | I21: 0 | K21: =M21-E21 -> 620.38 | L21: =N21-F21 -> 380.45 | M21: 620.38 | N21: 380.45 | O21: =(M21+N21)*D21 -> 7071864.8
A22: b | B22: 2nd floor | C22: Cum | D22: 7066 | E22: 0 | F22: 0 | G22: 0 | H22: 0 | I22: 0 | K22: =M22-E22 -> 812.44 | L22: =N22-F22 -> 380.45 | M22: 812.44 | N22: 380.45 | O22: =(M22+N22)*D22 -> 8428960.7
A23: 3.2.4 | B23: Non Structural - RC Walls | E23: 0 | F23: 0 | G23: 0 | H23: 0 | I23: 0 | K23: =M23-E23 -> 0 | L23: =N23-F23 -> 0 | M23: 0 | N23: 0 | O23: =(M23+N23)*D23 -> 0
B24: M30 grade | E24: 0 | F24: 0 | G24: 0 | H24: 0 | I24: 0 | K24: =M24-E24 -> 0 | L24: =N24-F24 -> 0 | M24: 0 | N24: 0 | O24: =(M24+N24)*D24 -> 0
A25: a | B25: 1st floor | C25: Cum | D25: 7066 | E25: 0 | F25: 0 | G25: 0 | H25: 0 | I25: 0 | K25: =M25-E25 -> 66.73 | L25: =N25-F25 -> 26.19 | M25: 66.73 | N25: 26.19 | O25: =(M25+N25)*D25 -> 656572.72
A26: b | B26: 2nd floor | C26: Cum | D26: 7066 | E26: 0 | F26: 0 | G26: 0 | H26: 0 | I26: 0 | K26: =M26-E26 -> 89.31 | L26: =N26-F26 -> 26.19 | M26: 89.31 | N26: 26.19 | O26: =(M26+N26)*D26 -> 816123
A27: 3.2.1 | B27: MLCP Columns at all levels | E27: 0 | F27: 0 | G27: 0 | H27: 0 | I27: 0 | K27: =M27-E27 -> 0 | L27: =N27-F27 -> 0 | M27: 0 | N27: 0 | O27: =(M27+N27)*D27 -> 0
B28: M30 grade- (Item Description same as Sl No. 3.1.9) | E28: 0 | F28: 0 | G28: 0 | H28: 0 | I28: 0 | K28: =M28-E28 -> 0 | L28: =N28-F28 -> 0 | M28: 0 | N28: 0 | O28: =(M28+N28)*D28 -> 0
A29: g | B29: Foundation to Stilt | C29: Cum | D29: 7066 | E29: 0 | F29: 0 | G29: 0 | H29: 0 | I29: 0 | K29: =M29-E29 -> 316.286 | L29: =N29-F29 -> 86.666 | M29: 316.286 | N29: 86.666 | O29: =(M29+N29)*D29 -> 2847258.8
A30: h | B30: Stilt floor | C30: Cum | D30: 7066 | E30: 0 | F30: 0 | G30: 0 | H30: 0 | I30: 0 | K30: =M30-E30 -> 233.993 | L30: =N30-F30 -> 0 | M30: 233.993 | N30: 0 | O30: =(M30+N30)*D30 -> 1653394.5
A31: i | B31: 1st floor | C31: Cum | D31: 7066 | E31: 0 | F31: 0 | G31: 0 | H31: 0 | I31: 0 | K31: =M31-E31 -> 265.386 | L31: =N31-F31 -> 0 | M31: 265.386 | N31: 0 | O31: =(M31+N31)*D31 -> 1875217.5
A32: j | B32: 2nd floor | C32: Cum | D32: 7066 | E32: 0 | F32: 0 | G32: 0 | H32: 0 | I32: 0 | K32: =M32-E32 -> 249.386 | L32: =N32-F32 -> 0 | M32: 249.386 | N32: 0 | O32: =(M32+N32)*D32 -> 1762161.5
A33: k | B33: 3rd floor | C33: Cum | D33: 7066 | E33: 0 | F33: 0 | G33: 0 | H33: 0 | I33: 0 | K33: =M33-E33 -> 233.028 | L33: =N33-F33 -> 0 | M33: 233.028 | N33: 0 | O33: =(M33+N33)*D33 -> 1646575.8
A34: l | B34: 4th floor | C34: Cum | D34: 7066 | E34: 0 | F34: 0 | G34: 0 | H34: 0 | I34: 0 | K34: =M34-E34 -> 234.441 | L34: =N34-F34 -> 0 | M34: 234.441 | N34: 0 | O34: =(M34+N34)*D34 -> 1656560.1
A35: m | B35: 5th floor | C35: Cum | D35: 7066 | E35: 0 | F35: 0 | G35: 0 | H35: 0 | I35: 0 | K35: =M35-E35 -> 234.623 | L35: =N35-F35 -> 0 | M35: 234.623 | N35: 0 | O35: =(M35+N35)*D35 -> 1657846.1
A36: 9.5 | B36: UG SUMP | E36: 0 | F36: 0 | G36: 0 | H36: 0 | I36: 0 | K36: =M36-E36 -> 0 | L36: =N36-F36 -> 0 | M36: 0 | N36: 0 | O36: =(M36+N36)*D36 -> 0
A37: j | B37: 50∅ Puddle Flange | C37: Nos. | D37: 4500 | E37: 0 | F37: 0 | G37: 0 | H37: 0 | I37: 0 | K37: =M37-E37 -> 6 | L37: =N37-F37 -> 0 | M37: 6 | N37: 0 | O37: =(M37+N37)*D37 -> 27000
A38: k | B38: 65∅ Puddle Flange | C38: Nos. | D38: 5790 | E38: 0 | F38: 0 | G38: 0 | H38: 0 | I38: 0 | K38: =M38-E38 -> 2 | L38: =N38-F38 -> 0 | M38: 2 | N38: 0 | O38: =(M38+N38)*D38 -> 11580
A39: 9.6 | B39: STP WORKS | E39: 0 | F39: 0 | G39: 0 | H39: 0 | I39: 0 | K39: =M39-E39 -> 0 | L39: =N39-F39 -> 0 | M39: 0 | N39: 0 | O39: =(M39+N39)*D39 -> 0
A40: e | B40: Retail STP 50∅ Drain Out Pipe . length - 750mm-(Item Description same as Sl No. 9.4.2 I c) | C40: Nos. | D40: 4500 | E40: 0 | F40: 0 | G40: 0 | H40: 0 | I40: 0 | K40: =M40-E40 -> 1 | L40: =N40-F40 -> 0 | M40: 1 | N40: 0 | O40: =(M40+N40)*D40 -> 4500
A41: f | B41: MBR Outlet Puddle Flanges - 80 mm dia-750mm-Item Description same as Sl No. 9.4.2 i(e) | C41: Nos. | D41: 7140 | E41: 0 | F41: 0 | G41: 0 | H41: 0 | I41: 0 | K41: =M41-E41 -> 3 | L41: =N41-F41 -> 0 | M41: 3 | N41: 0 | O41: =(M41+N41)*D41 -> 21420
A42: g | B42: MBR Outlet Puddle Flanges - 200mm dia, length - 750mm-Item Description same as Sl No. 9.5 e (i) | C42: Nos. | D42: 14772 | E42: 0 | F42: 0 | G42: 0 | H42: 0 | I42: 0 | K42: =M42-E42 -> 1 | L42: =N42-F42 -> 0 | M42: 1 | N42: 0 | O42: =(M42+N42)*D42 -> 14772
A43: h | B43: MBR Outlet Puddle Flanges - 250mm dia, length - 750mm-Item Description same as Sl No. 9.5 e (ii) | C43: Nos. | D43: 17641 | E43: 0 | F43: 0 | G43: 0 | H43: 0 | I43: 0 | K43: =M43-E43 -> 5 | L43: =N43-F43 -> 0 | M43: 5 | N43: 0 | O43: =(M43+N43)*D43 -> 88205
A44: 11.01 | B44: Providing and Constructing of 200mm thk Solid Cement Concrete Block Masonry work at all levels in cement mortar 1:6 (1Cement: 6 Manufactured Sand) using standard sizes of 400mm X 200mm X 200mm of solid cement concrete blocks of thickness, with a minimum compressive strength of 35 Kg/Sq Cm conforming to IS 2185, including all scaffolding, staging, wastages, labour, curing, all Lead & lifts, raking, pointing the joints to at least 10mm depth, cleaning surroundings at all time, using proper tools (block cutting machine, spirit level, Right angle (BIG) and tackles, etc. complete and as directed and as per specification & drawings and as per the directions of Client / the Engineer. Lift wall & Control Room | C44: Sqm | D44: 1469 | E44: 0 | F44: 0 | G44: 0 | H44: 0 | I44: 0 | K44: =M44-E44 -> 1288.224 | L44: =N44-F44 -> 0 | M44: 1288.224 | N44: 0 | O44: =(M44+N44)*D44 -> 1892401.1
B45: Total Amount (Excl GST) | E45: 0 | F45: 0 | G45: 0 | H45: 0 | I45: 0 | J45: 0 | O45: =SUM(O9:O44) -> 41887062

Sheet Derived Items_UPVC
A1: Project - Provident Ecopolitan - Ph 1 & Ph 2
A2: Subject - UPVC DOORS & WINDOWS WORKS
A3: Item No. | B3: Description of works | C3: UOM | D3: Qty | E3: Rate / Sqm | F3: Amount (Rs.)
B5: Derived items for Sl.No. 7 (Finishing Works)
A6: 1 | B6: UPVC WORKS | D6: 0 | F6: =ROUND(E6*D6,0) -> 0
B7: Wind Pressure consideration:1.5Kpa (including factor of safety), fastners shall be of Hilti or fischer make, Water & Smoke test to be done, Glass shall come with Protection film which shall be removed during handing over. Actual Measurement to be taken at site for Windows/Doors opening. | D7: 0 | F7: =ROUND(E7*D7,0) -> 0
A8: 1.1 | B8: Providing and fixing in position glazed 2.5 track UPVC sliding doors provided with mosquito mesh of fiberglass mesh from saint gobain as per the drawing enclosed complete at all levels., consisting of sliding system, outer frames, shutter frames, all frame & shutter sections well reinforced as specified in the technical specifications etc assembled and fitted properly complete at all levels, The glass shall be of 6mm thk Clear toughened glass including anchoring frames as approved, fixing and other accessories, self locking handle of multi point locking as per the client/architect approval., heavy duty rollers and other hardware as required and as approved and all incidental work complete as per drawings and specifications. All the UPVC sections shall be finished in a fully automatic plant equipped for such work as per the specifications. Weather sealant of Dow corning/Momentive to be applied on the periphery of the window on both sides.Weather strip at every panel sides that restricts entry of mosquito and maintain temparature inside rooms, Shop drawing to be approved by the client prior to procurement/ supply of assembled widows to site. The EPDM gasket should be oven cured and neatly mitre joint at junctions.The drain/weep hole and its cover is also placed at required intervals that not allows water stagnates on trackes between and drains smoothly out. The complete system is well protected with films till final hand over. | D8: 0 | F8: =ROUND(E8*D8,0) -> 0
A9: 1.1.1 | B9: SD1 2100x2400 mm | C9: Sqm | D9: 3833.025 | E9: 4662 | F9: =E9*D9 -> 17869563
A10: 1.1.2 | B10: SD2 1800x2400 mm | C10: Sqm | D10: 4833.36 | E10: 4662 | F10: =E10*D10 -> 22533124
A11: 1.1.3 | B11: SD3 1600x2400 mm | C11: Sqm | D11: 1497.44 | E11: 4662 | F11: =E11*D11 -> 6981065.3
A12: 1.1.4 | B12: SD4 1500x2400 mm | C12: Sqm | D12: 312.375 | E12: 4662 | F12: =E12*D12 -> 1456292.2
A13: 1.1.5 | B13: SD4a 1525x2450 mm | C13: Sqm | D13: 14.945 | E13: 4662 | F13: =E13*D13 -> 69673.59
A14: 1.2 | B14: Providing & fixing 2.5 track UPVC glazed Sliding panel window consisting of 2 glazed panels with 6mm thk Clear glass and mosquito mesh and the window should have a provision for fixing of exhaust fan, all frame & shutter sections well reinforced as specified in the technical specifications etc as per the drawing enclosed complete at all levels. All the UPVC sections shall be finished in a fully automatic plant equipped for such work as per the specifications. Weather sealant of Dowcorning / Momentive to be applied on the periphery of the window on both sides.Weather strip at every panel sides that restricts entry of mosquito and maintain temparature inside rooms All Windows to be approved hardware by the architect/client. The movement of the sliding shutter should have smooth movement. colour ofthe single point lock to be as per the approvel of the client/architect. shop drawings to be approved prior to start of procurement/fabrication of windows. The EPDM gasket should be oven cured and neatly mitre joint at junctions.The drain/weep hole and its cover is also placed at required intervals that not allows water stagnates on trackes between and drains smoothly out. The complete system is well protected with films till final hand over. | D14: 0 | F14: =E14*D14 -> 0
A15: 1.2.1 | B15: KW1 1200x1300 mm | C15: Sqm | D15: 1577.16 | E15: 4662 | F15: =E15*D15 -> 7352719.9
A16: 1.2.2 | B16: KW2 1100x1300mm | C16: Sqm | D16: 45.76 | E16: 4662 | F16: =E16*D16 -> 213333.12
A17: 1.3 | B17: Providing & fixing of UPVC glazed window consisting of 2 glazed panels with 6 mm thk Clear glass at the bottom & top glass louvers as per the drawing enclosed complete at all levels. All the UPVC sections shall be finished in a fully automatic plant equipped for such work as per the specifications. all frame & shutter sections well reinforced as specified in the technical specifications etc Weather sealant of Dowcorning/Momentive to be applied on the periphery of the window on both sides. All Windows to be approved hardware by the architect/client. .Weather strip at every panel sides that restricts entry of mosquito and maintain temparature inside rooms. colour of the single point lock to be as per the approval of the client/architect. shop drawings to be approved prior to start of procurement/fabrication of windows. The EPDM gasket should be oven cured.and neatly mitre joint at junctions.The drain/weep hole and its cover is also placed at required intervals that not allows water stagnates on trackes between and drains smoothly out. The complete system is well protected with films till final hand over. Location: Staircase Areas | D17: 0 | F17: =E17*D17 -> 0
A18: 1.3.1 | B18: SW-1500X1500mm | C18: Sqm | D18: 904.5 | E18: 4662 | F18: =E18*D18 -> 4216779
A19: 1.3.2 | B19: SW1-1200X1500mm | C19: Sqm | D19: 358.2 | E19: 4662 | F19: =E19*D19 -> 1669928.4
A20: 1.3.3 | B20: SW3 - 900x1500mm | C20: Sqm | D20: 1.35 | E20: 4662 | F20: =E20*D20 -> 6293.7
A21: 1.3.4 | B21: SW1A 1200x1500mm | C21: Sqm | D21: 396 | E21: 4662 | F21: =E21*D21 -> 1846152
A22: 1.3.5 | B22: SW1B 1200x1500mm | C22: Sqm | D22: 3.6 | E22: 4662 | F22: =E22*D22 -> 16783.2
A23: 1.4 | B23: Providing & fixing 2.5track UPVC glazed window consisting of 2 glazed panels(Above portion opneable and bottom fixed, as per drawings) with 6mm thk Plain glass for windows for sliding portion and 6mm toughned clear glass for fixed portion. Mosquito mesh of fiberglass mesh from saint gobain to be fixed as per the drawing enclosed complete at all levels. All the UPVC sections shall be finished in a fully automatic plant equipped for such work as per the specifications. all frame & shutter sections well reinforced as specified in the technical specifications etc., Weather sealant of Dowcorning /Momentive to be applied on the periphery of the window on both sides. All Windows to be approved hardware by the architect/client. The movement of the sliding shutter should have smooth movement. colour ofthe single point lock to be as per the approval of the client/architect. Weather strip at every panel sides that restricts entry of mosquito and maintain temparature inside rooms shop drawings to be approved prior to start of procurement /fabrication of windows. The EPDM gasket should be oven cured and neatly mitre joint at junctions.The drain/weep hole and its cover is also placed at required intervals that not allows water stagnates on trackes between and drains smoothly out. The complete system is well protected with films till final hand over. | D23: 0 | F23: =E23*D23 -> 0
A24: 1.4.1 | B24: W1 2100x2325mm | C24: Sqm | D24: 810.495 | E24: 4662 | F24: =E24*D24 -> 3778527.7
A25: 1.4.2 | B25: W2 1800x2325 mm | C25: Sqm | D25: 133.92 | E25: 4662 | F25: =E25*D25 -> 624335.04
A26: 1.4.3 | B26: W3 1600x2325mm | C26: Sqm | D26: 777.48 | E26: 4662 | F26: =E26*D26 -> 3624611.8
A27: 1.4.4 | B27: W4 1500x2325mm | C27: Sqm | D27: 4083.8625 | E27: 4662 | F27: =E27*D27 -> 19038967
A28: 1.4.5 | B28: W4A 1525x2325mm | C28: Sqm | D28: 882.86063 | E28: 4662 | F28: =E28*D28 -> 4115896.2
A29: 1.4.6 | B29: W5 1400x2325mm | C29: Sqm | D29: 289.695 | E29: 4662 | F29: =E29*D29 -> 1350558.1
A30: 1.4.7 | B30: W6 1200x2325mm | C30: Sqm | D30: 345.96 | E30: 4662 | F30: =E30*D30 -> 1612865.5
A31: 1.4.8 | B31: W6A 1200x1500mm | C31: Sqm | D31: 39.6 | E31: 4662 | F31: =E31*D31 -> 184615.2
A32: 1.4.9 | B32: W7 500x1200mm | C32: Sqm | D32: 45 | E32: 4662 | F32: =E32*D32 -> 209790
A33: 1.4.10 | B33: W8 500x1200mm | C33: Sqm | D33: 39.6 | E33: 4662 | F33: =E33*D33 -> 184615.2
A34: 1.4.11 | B34: W9 1400X1200 mm | C34: Sqm | D34: 1.68 | E34: 4662 | F34: =E34*D34 -> 7832.16
A35: 1.4.12 | B35: W10 1500x1500mm | C35: Sqm | D35: 92.25 | E35: 4662 | F35: =E35*D35 -> 430069.5
A36: 1.5 | B36: Providing and fixing of UPVC ventilators with Architraves that rests at Internal flush with wall tiles of approved colour and sections. The ventilator should have a provision for fixing of exhaust fan and with fixed frosted glass louvers (4mm thickness), with all necessary accessories like handles, weep holes/covers, SS hinges, lock, screws etc., complete at all levels as pe architect/Client approval. Weather sealant outside/Sanitary grade selant at inside around frames / architraves of Dow corning/Momentive to be applied on the periphery of the window on both sides. | D36: 0 | F36: =E36*D36 -> 0
A37: 1.5.1 | B37: V1 750x1200 mm | C37: Sqm | D37: 1905.3 | E37: 4662 | F37: =E37*D37 -> 8882508.6
A38: 1.5.2 | B38: V3 600x750mm | C38: Sqm | D38: 88.2 | E38: 4662 | F38: =E38*D38 -> 411188.4
A39: 1.5.3 | B39: V2 600x900 mm | C39: Sqm | D39: 113.94 | E39: 4662 | F39: =E39*D39 -> 531188.28
B40: Total Amount (Excl GST) | D40: =SUM(D7:D39) -> 23427.558 | F40: =SUM(F7:F39) -> 1.0921928e+08

Sheet Working_UPVC
A2: DERIVED ITEMS
E3: As per LOA | K3: Current Variation | M3: As per VO#02
A4: Item No. | B4: Description of works | C4: UOM | D4: Rate | E4: Quantity | H4: Amount (Rs.) | K4: Quantity | M4: Quantity | O4: Amount
E5: Ph - 1 | F5: Ph -2 | G5: Total Qty | H5: Ph - 1 | I5: Ph -2 | J5: Total | K5: Ph - 1 | L5: Ph -2 | M5: Ph - 1 | N5: Ph -2 | O5: Ph - 1 | P5: Ph -2 | Q5: Sqm | R5: Nos
A6: 7 | B6: UPVC WORKS | E6: 0 | F6: 0 | G6: =SUM(E6:F6) -> 0 | H6: =ROUND(D6*E6,0) -> 0 | I6: =ROUND(D6*F6,0) -> 0 | J6: =SUM(H6:I6) -> 0
B7: Wind Pressure consideration:1.5Kpa (including factor of safety), fastners shall be of Hilti or fischer make, Water & Smoke test to be done, Glass shall come with Protection film which shall be removed during handing over. Actual Measurement to be taken at site for Windows/Doors opening. | E7: 0 | F7: 0 | G7: =SUM(E7:F7) -> 0 | H7: =ROUND(D7*E7,0) -> 0 | I7: =ROUND(D7*F7,0) -> 0 | J7: =SUM(H7:I7) -> 0 | Q7: =N7+M7 -> 0
A8: 7.1 | B8: Providing and fixing in position glazed 2.5 track UPVC sliding doors provided with mosquito mesh of fiberglass mesh from saint gobain as per the drawing enclosed complete at all levels., consisting of sliding system, outer frames, shutter frames, all frame & shutter sections well reinforced as specified in the technical specifications etc assembled and fitted properly complete at all levels, The glass shall be of 6mm thk Clear toughened glass including anchoring frames as approved, fixing and other accessories, self locking handle of multi point locking as per the client/architect approval., heavy duty rollers and other hardware as required and as approved and all incidental work complete as per drawings and specifications. All the UPVC sections shall be finished in a fully automatic plant equipped for such work as per the specifications. Weather sealant of Dow corning/Momentive to be applied on the periphery of the window on both sides.Weather strip at every panel sides that restricts entry of mosquito and maintain temparature inside rooms, Shop drawing to be approved by the client prior to procurement/ supply of assembled widows to site. The EPDM gasket should be oven cured and neatly mitre joint at junctions.The drain/weep hole and its cover is also placed at required intervals that not allows water stagnates on trackes between and drains smoothly out. The complete system is well protected with films till final hand over. | E8: 0 | F8: 0 | G8: =SUM(E8:F8) -> 0 | H8: =ROUND(D8*E8,0) -> 0 | I8: =ROUND(D8*F8,0) -> 0 | J8: =SUM(H8:I8) -> 0 | Q8: =N8+M8 -> 0
A9: 7.1.1 | B9: SD1 2100x2400 mm | D9: 0 | E9: 0 | F9: 0 | G9: =SUM(E9:F9) -> 0 | H9: =ROUND(D9*E9,0) -> 0 | I9: =ROUND(D9*F9,0) -> 0 | J9: =SUM(H9:I9) -> 0 | Q9: =N9+M9 -> 0
A10: a | B10: Floor -1 | C10: Sqm | D10: 4662 | E10: 111.55 | F10: 65.96 | G10: =SUM(E10:F10) -> 177.51 | H10: =$D10*E10 -> 520046.1 | I10: =$D10*F10 -> 307505.52 | J10: =SUBTOTAL(9,H10:I10) -> 827551.62 | K10: =M10-E10 -> -0.67 | L10: =N10-F10 -> 0 | M10: 110.88 | N10: 65.96 | O10: =M10*D10 -> 516922.56 | P10: =N10*D10 -> 307505.52 | Q10: =N10+M10 -> 176.84 | R10: =Q10/(2.1*2.4) -> 35.087302
A11: b | B11: Floor -2 | C11: Sqm | D11: 4662 | E11: 131.92 | F11: 61.11 | G11: =SUM(E11:F11) -> 193.03 | H11: =$D11*E11 -> 615011.04 | I11: =$D11*F11 -> 284894.82 | J11: =SUBTOTAL(9,H11:I11) -> 899905.86 | K11: =M11-E11 -> -0.88 | L11: =N11-F11 -> 0 | M11: 131.04 | N11: 61.11 | O11: =M11*D11 -> 610908.48 | P11: =N11*D11 -> 284894.82 | Q11: =N11+M11 -> 192.15 | R11: =Q11/(2.1*2.4) -> 38.125
A12: c | B12: Floor -3 | C12: Sqm | D12: 4662 | E12: 131.92 | F12: 61.11 | G12: =SUM(E12:F12) -> 193.03 | H12: =$D12*E12 -> 615011.04 | I12: =$D12*F12 -> 284894.82 | J12: =SUBTOTAL(9,H12:I12) -> 899905.86 | K12: =M12-E12 -> -0.88 | L12: =N12-F12 -> 0 | M12: 131.04 | N12: 61.11 | O12: =M12*D12 -> 610908.48 | P12: =N12*D12 -> 284894.82 | Q12: =N12+M12 -> 192.15 | R12: =Q12/(2.1*2.4) -> 38.125
A13: d | B13: Floor -4 | C13: Sqm | D13: 4662 | E13: 131.92 | F13: 61.11 | G13: =SUM(E13:F13) -> 193.03 | H13: =$D13*E13 -> 615011.04 | I13: =$D13*F13 -> 284894.82 | J13: =SUBTOTAL(9,H13:I13) -> 899905.86 | K13: =M13-E13 -> -0.88 | L13: =N13-F13 -> 0 | M13: 131.04 | N13: 61.11 | O13: =M13*D13 -> 610908.48 | P13: =N13*D13 -> 284894.82 | Q13: =N13+M13 -> 192.15 | R13: =Q13/(2.1*2.4) -> 38.125
A14: e | B14: Floor -5 | C14: Sqm | D14: 4662 | E14: 131.92 | F14: 61.11 | G14: =SUM(E14:F14) -> 193.03 | H14: =$D14*E14 -> 615011.04 | I14: =$D14*F14 -> 284894.82 | J14: =SUBTOTAL(9,H14:I14) -> 899905.86 | K14: =M14-E14 -> -0.88 | L14: =N14-F14 -> 0 | M14: 131.04 | N14: 61.11 | O14: =M14*D14 -> 610908.48 | P14: =N14*D14 -> 284894.82 | Q14: =N14+M14 -> 192.15 | R14: =Q14/(2.1*2.4) -> 38.125
A15: f | B15: Floor -6 | C15: Sqm | D15: 4662 | E15: 198.85 | F15: 61.11 | G15: =SUM(E15:F15) -> 259.96 | H15: =$D15*E15 -> 927038.7 | I15: =$D15*F15 -> 284894.82 | J15: =SUBTOTAL(9,H15:I15) -> 1211933.5 | K15: =M15-E15 -> -2.29 | L15: =N15-F15 -> 0 | M15: 196.56 | N15: 61.11 | O15: =M15*D15 -> 916362.72 | P15: =N15*D15 -> 284894.82 | Q15: =N15+M15 -> 257.67 | R15: =Q15/(2.1*2.4) -> 51.125
A16: g | B16: Floor -7 | C16: Sqm | D16: 4662 | E16: 198.85 | F16: 61.11 | G16: =SUM(E16:F16) -> 259.96 | H16: =$D16*E16 -> 927038.7 | I16: =$D16*F16 -> 284894.82 | J16: =SUBTOTAL(9,H16:I16) -> 1211933.5 | K16: =M16-E16 -> -2.29 | L16: =N16-F16 -> 0 | M16: 196.56 | N16: 61.11 | O16: =M16*D16 -> 916362.72 | P16: =N16*D16 -> 284894.82 | Q16: =N16+M16 -> 257.67 | R16: =Q16/(2.1*2.4) -> 51.125
A17: h | B17: Floor -8 | C17: Sqm | D17: 4662 | E17: 198.85 | F17: 61.11 | G17: =SUM(E17:F17) -> 259.96 | H17: =$D17*E17 -> 927038.7 | I17: =$D17*F17 -> 284894.82 | J17: =SUBTOTAL(9,H17:I17) -> 1211933.5 | K17: =M17-E17 -> -2.29 | L17: =N17-F17 -> 0 | M17: 196.56 | N17: 61.11 | O17: =M17*D17 -> 916362.72 | P17: =N17*D17 -> 284894.82 | Q17: =N17+M17 -> 257.67 | R17: =Q17/(2.1*2.4) -> 51.125
A18: i | B18: Floor -9 | C18: Sqm | D18: 4662 | E18: 198.85 | F18: 61.11 | G18: =SUM(E18:F18) -> 259.96 | H18: =$D18*E18 -> 927038.7 | I18: =$D18*F18 -> 284894.82 | J18: =SUBTOTAL(9,H18:I18) -> 1211933.5 | K18: =M18-E18 -> -2.29 | L18: =N18-F18 -> 0 | M18: 196.56 | N18: 61.11 | O18: =M18*D18 -> 916362.72 | P18: =N18*D18 -> 284894.82 | Q18: =N18+M18 -> 257.67 | R18: =Q18/(2.1*2.4) -> 51.125
A19: j | B19: Floor -10 | C19: Sqm | D19: 4662 | E19: 198.85 | F19: 61.11 | G19: =SUM(E19:F19) -> 259.96 | H19: =$D19*E19 -> 927038.7 | I19: =$D19*F19 -> 284894.82 | J19: =SUBTOTAL(9,H19:I19) -> 1211933.5 | K19: =M19-E19 -> -2.29 | L19: =N19-F19 -> 0 | M19: 196.56 | N19: 61.11 | O19: =M19*D19 -> 916362.72 | P19: =N19*D19 -> 284894.82 | Q19: =N19+M19 -> 257.67 | R19: =Q19/(2.1*2.4) -> 51.125
A20: k | B20: Floor -11 | C20: Sqm | D20: 4662 | E20: 198.85 | F20: 61.11 | G20: =SUM(E20:F20) -> 259.96 | H20: =$D20*E20 -> 927038.7 | I20: =$D20*F20 -> 284894.82 | J20: =SUBTOTAL(9,H20:I20) -> 1211933.5 | K20: =M20-E20 -> -2.29 | L20: =N20-F20 -> 0 | M20: 196.56 | N20: 61.11 | O20: =M20*D20 -> 916362.72 | P20: =N20*D20 -> 284894.82 | Q20: =N20+M20 -> 257.67 | R20: =Q20/(2.1*2.4) -> 51.125
A21: l | B21: Floor -12 | C21: Sqm | D21: 4662 | E21: 198.85 | F21: 61.11 | G21: =SUM(E21:F21) -> 259.96 | H21: =$D21*E21 -> 927038.7 | I21: =$D21*F21 -> 284894.82 | J21: =SUBTOTAL(9,H21:I21) -> 1211933.5 | K21: =M21-E21 -> -2.29 | L21: =N21-F21 -> 0 | M21: 196.56 | N21: 61.11 | O21: =M21*D21 -> 916362.72 | P21: =N21*D21 -> 284894.82 | Q21: =N21+M21 -> 257.67 | R21: =Q21/(2.1*2.4) -> 51.125
... A28: s | B28: Floor -19 | C28: Sqm | D28: 4662 | E28: 198.85 | F28: 61.11 | G28: =SUM(E28:F28) -> 259.96 | H28: =$D28*E28 -> 927038.7 | I28: =$D28*F28 -> 284894.82 | J28: =SUBTOTAL(9,H28:I28) -> 1211933.5 | K28: =M28-E28 -> -2.29 | L28: =N28-F28 -> 0 | M28: 196.56 | N28: 61.11 | O28: =M28*D28 -> 916362.72 | P28: =N28*D28 -> 284894.82 | Q28: =N28+M28 -> 257.67 | R28: =Q28/(2.1*2.4) -> 51.125
A29: t | B29: Floor -20 | C29: Sqm | D29: 4662 | E29: 0 | F29: 61.11 | G29: =SUM(E29:F29) -> 61.11 | H29: =$D29*E29 -> 0 | I29: =$D29*F29 -> 284894.82 | J29: =SUBTOTAL(9,H29:I29) -> 284894.82 | K29: =M29-E29 -> 0 | L29: =N29-F29 -> 0 | N29: 61.11 | O29: =M29*D29 -> 0 | P29: =N29*D29 -> 284894.82 | Q29: =N29+M29 -> 61.11 | R29: =Q29/(2.1*2.4) -> 12.125
A30: u | B30: Floor -21 | C30: Sqm | D30: 4662 | E30: 0 | F30: 35.89 | G30: =SUM(E30:F30) -> 35.89 | H30: =$D30*E30 -> 0 | I30: =$D30*F30 -> 167319.18 | J30: =SUBTOTAL(9,H30:I30) -> 167319.18 | K30: =M30-E30 -> 0 | L30: =N30-F30 -> 0 | N30: 35.89 | O30: =M30*D30 -> 0 | P30: =N30*D30 -> 167319.18 | Q30: =N30+M30 -> 35.89 | R30: =Q30/(2.1*2.4) -> 7.1210317
A31: v | B31: Floor -22 | C31: Sqm | D31: 4662 | E31: 0 | F31: 35.89 | G31: =SUM(E31:F31) -> 35.89 | H31: =$D31*E31 -> 0 | I31: =$D31*F31 -> 167319.18 | J31: =SUBTOTAL(9,H31:I31) -> 167319.18 | K31: =M31-E31 -> 0 | L31: =N31-F31 -> 0 | N31: 35.89 | O31: =M31*D31 -> 0 | P31: =N31*D31 -> 167319.18 | Q31: =N31+M31 -> 35.89 | R31: =Q31/(2.1*2.4) -> 7.1210317
A32: w | B32: Terrace Floor | C32: Sqm | D32: 4662 | E32: 0 | F32: 0 | G32: =SUM(E32:F32) -> 0 | H32: =$D32*E32 -> 0 | I32: =$D32*F32 -> 0 | J32: =SUBTOTAL(9,H32:I32) -> 0 | K32: =M32-E32 -> 0 | L32: =N32-F32 -> 0 | O32: =M32*D32 -> 0 | P32: =N32*D32 -> 0 | Q32: =N32+M32 -> 0
A33: 7.1.2 | B33: SD2 1800x2400 mm | D33: 0 | E33: 0 | F33: 0 | G33: =SUM(E33:F33) -> 0 | H33: =ROUND(D33*E33,0) -> 0 | I33: =ROUND(D33*F33,0) -> 0 | J33: =SUM(H33:I33) -> 0 | K33: =M33-E33 -> 0 | L33: =N33-F33 -> 0 | O33: =M33*D33 -> 0 | P33: =N33*D33 -> 0 | Q33: =N33+M33 -> 0
A34: a | B34: Floor -1 | C34: Sqm | D34: 4662 | E34: 45.59 | F34: 27.16 | G34: =SUM(E34:F34) -> 72.75 | H34: =$D34*E34 -> 212540.58 | I34: =$D34*F34 -> 126619.92 | J34: =SUBTOTAL(9,H34:I34) -> 339160.5 | K34: =M34-E34 -> -2.3 | L34: =N34-F34 -> 0 | M34: 43.29 | N34: 27.16 | O34: =M34*D34 -> 201817.98 | P34: =N34*D34 -> 126619.92 | Q34: =N34+M34 -> 70.45
A35: b | B35: Floor -2 | C35: Sqm | D35: 4662 | E35: 93.12 | F35: 27.16 | G35: =SUM(E35:F35) -> 120.28 | H35: =$D35*E35 -> 434125.44 | I35: =$D35*F35 -> 126619.92 | J35: =SUBTOTAL(9,H35:I35) -> 560745.36 | K35: =M35-E35 -> -1.95 | L35: =N35-F35 -> 0 | M35: 91.17 | N35: 27.16 | O35: =M35*D35 -> 425034.54 | P35: =N35*D35 -> 126619.92 | Q35: =N35+M35 -> 118.33
A36: c | B36: Floor -3 | C36: Sqm | D36: 4662 | E36: 93.12 | F36: 27.16 | G36: =SUM(E36:F36) -> 120.28 | H36: =$D36*E36 -> 434125.44 | I36: =$D36*F36 -> 126619.92 | J36: =SUBTOTAL(9,H36:I36) -> 560745.36 | K36: =M36-E36 -> -6.27 | L36: =N36-F36 -> 0 | M36: 86.85 | N36: 27.16 | O36: =M36*D36 -> 404894.7 | P36: =N36*D36 -> 126619.92 | Q36: =N36+M36 -> 114.01
A37: d | B37: Floor -4 | C37: Sqm | D37: 4662 | E37: 93.12 | F37: 27.16 | G37: =SUM(E37:F37) -> 120.28 | H37: =$D37*E37 -> 434125.44 | I37: =$D37*F37 -> 126619.92 | J37: =SUBTOTAL(9,H37:I37) -> 560745.36 | K37: =M37-E37 -> -6.27 | L37: =N37-F37 -> 0 | M37: 86.85 | N37: 27.16 | O37: =M37*D37 -> 404894.7 | P37: =N37*D37 -> 126619.92 | Q37: =N37+M37 -> 114.01
A38: e | B38: Floor -5 | C38: Sqm | D38: 4662 | E38: 93.12 | F38: 27.16 | G38: =SUM(E38:F38) -> 120.28 | H38: =$D38*E38 -> 434125.44 | I38: =$D38*F38 -> 126619.92 | J38: =SUBTOTAL(9,H38:I38) -> 560745.36 | K38: =M38-E38 -> -6.27 | L38: =N38-F38 -> 0 | M38: 86.85 | N38: 27.16 | O38: =M38*D38 -> 404894.7 | P38: =N38*D38 -> 126619.92 | Q38: =N38+M38 -> 114.01
A39: f | B39: Floor -6 | C39: Sqm | D39: 4662 | E39: 137.74 | F39: 27.16 | G39: =SUM(E39:F39) -> 164.9 | H39: =$D39*E39 -> 642143.88 | I39: =$D39*F39 -> 126619.92 | J39: =SUBTOTAL(9,H39:I39) -> 768763.8 | K39: =M39-E39 -> -3.37 | L39: =N39-F39 -> 0 | M39: 134.37 | N39: 27.16 | O39: =M39*D39 -> 626432.94 | P39: =N39*D39 -> 126619.92 | Q39: =N39+M39 -> 161.53
A40: g | B40: Floor -7 | C40: Sqm | D40: 4662 | E40: 137.74 | F40: 27.16 | G40: =SUM(E40:F40) -> 164.9 | H40: =$D40*E40 -> 642143.88 | I40: =$D40*F40 -> 126619.92 | J40: =SUBTOTAL(9,H40:I40) -> 768763.8 | K40: =M40-E40 -> -3.37 | L40: =N40-F40 -> 0 | M40: 134.37 | N40: 27.16 | O40: =M40*D40 -> 626432.94 | P40: =N40*D40 -> 126619.92 | Q40: =N40+M40 -> 161.53
A41: h | B41: Floor -8 | C41: Sqm | D41: 4662 | E41: 137.74 | F41: 27.16 | G41: =SUM(E41:F41) -> 164.9 | H41: =$D41*E41 -> 642143.88 | I41: =$D41*F41 -> 126619.92 | J41: =SUBTOTAL(9,H41:I41) -> 768763.8 | K41: =M41-E41 -> -3.37 | L41: =N41-F41 -> 0 | M41: 134.37 | N41: 27.16 | O41: =M41*D41 -> 626432.94 | P41: =N41*D41 -> 126619.92 | Q41: =N41+M41 -> 161.53
A42: i | B42: Floor -9 | C42: Sqm | D42: 4662 | E42: 137.74 | F42: 27.16 | G42: =SUM(E42:F42) -> 164.9 | H42: =$D42*E42 -> 642143.88 | I42: =$D42*F42 -> 126619.92 | J42: =SUBTOTAL(9,H42:I42) -> 768763.8 | K42: =M42-E42 -> -3.37 | L42: =N42-F42 -> 0 | M42: 134.37 | N42: 27.16 | O42: =M42*D42 -> 626432.94 | P42: =N42*D42 -> 126619.92 | Q42: =N42+M42 -> 161.53
A43: j | B43: Floor -10 | C43: Sqm | D43: 4662 | E43: 137.74 | F43: 27.16 | G43: =SUM(E43:F43) -> 164.9 | H43: =$D43*E43 -> 642143.88 | I43: =$D43*F43 -> 126619.92 | J43: =SUBTOTAL(9,H43:I43) -> 768763.8 | K43: =M43-E43 -> -3.37 | L43: =N43-F43 -> 0 | M43: 134.37 | N43: 27.16 | O43: =M43*D43 -> 626432.94 | P43: =N43*D43 -> 126619.92 | Q43: =N43+M43 -> 161.53
A44: k | B44: Floor -11 | C44: Sqm | D44: 4662 | E44: 137.74 | F44: 27.16 | G44: =SUM(E44:F44) -> 164.9 | H44: =$D44*E44 -> 642143.88 | I44: =$D44*F44 -> 126619.92 | J44: =SUBTOTAL(9,H44:I44) -> 768763.8 | K44: =M44-E44 -> -3.37 | L44: =N44-F44 -> 0 | M44: 134.37 | N44: 27.16 | O44: =M44*D44 -> 626432.94 | P44: =N44*D44 -> 126619.92 | Q44: =N44+M44 -> 161.53
A45: l | B45: Floor -12 | C45: Sqm | D45: 4662 | E45: 137.74 | F45: 27.16 | G45: =SUM(E45:F45) -> 164.9 | H45: =$D45*E45 -> 642143.88 | I45: =$D45*F45 -> 126619.92 | J45: =SUBTOTAL(9,H45:I45) -> 768763.8 | K45: =M45-E45 -> -3.37 | L45: =N45-F45 -> 0 | M45: 134.37 | N45: 27.16 | O45: =M45*D45 -> 626432.94 | P45: =N45*D45 -> 126619.92 | Q45: =N45+M45 -> 161.53
... A56: w | B56: Terrace Floor | C56: Sqm | D56: 4662 | E56: 0 | F56: 0 | G56: =SUM(E56:F56) -> 0 | H56: =$D56*E56 -> 0 | I56: =$D56*F56 -> 0 | J56: =SUBTOTAL(9,H56:I56) -> 0 | K56: =M56-E56 -> 0 | L56: =N56-F56 -> 0 | M56: 0 | N56: 0 | O56: =M56*D56 -> 0 | P56: =N56*D56 -> 0 | Q56: =N56+M56 -> 0
A57: 7.1.3 | B57: SD3 1600x2400 mm | D57: 0 | E57: 0 | F57: 0 | G57: =SUM(E57:F57) -> 0 | H57: =ROUND(D57*E57,0) -> 0 | I57: =ROUND(D57*F57,0) -> 0 | J57: =SUM(H57:I57) -> 0 | K57: =M57-E57 -> 0 | L57: =N57-F57 -> 0 | O57: =M57*D57 -> 0 | P57: =N57*D57 -> 0 | Q57: =N57+M57 -> 0
A58: a | B58: Floor -1 | C58: Sqm | D58: 4662 | E58: 77.6 | F58: 27.16 | G58: =SUM(E58:F58) -> 104.76 | H58: =$D58*E58 -> 361771.2 | I58: =$D58*F58 -> 126619.92 | J58: =SUBTOTAL(9,H58:I58) -> 488391.12 | K58: =M58-E58 -> 3.04 | L58: =N58-F58 -> 0 | M58: 80.64 | N58: 27.16 | O58: =M58*D58 -> 375943.68 | P58: =N58*D58 -> 126619.92 | Q58: =N58+M58 -> 107.8
A59: b | B59: Floor -2 | C59: Sqm | D59: 4662 | E59: 54.32 | F59: 19.4 | G59: =SUM(E59:F59) -> 73.72 | H59: =$D59*E59 -> 253239.84 | I59: =$D59*F59 -> 90442.8 | J59: =SUBTOTAL(9,H59:I59) -> 343682.64 | K59: =M59-E59 -> 3.28 | L59: =N59-F59 -> 0 | M59: 57.6 | N59: 19.4 | O59: =M59*D59 -> 268531.2 | P59: =N59*D59 -> 90442.8 | Q59: =N59+M59 -> 77
A60: c | B60: Floor -3 | C60: Sqm | D60: 4662 | E60: 60.14 | F60: 19.4 | G60: =SUM(E60:F60) -> 79.54 | H60: =$D60*E60 -> 280372.68 | I60: =$D60*F60 -> 90442.8 | J60: =SUBTOTAL(9,H60:I60) -> 370815.48 | K60: =M60-E60 -> -2.54 | L60: =N60-F60 -> 0 | M60: 57.6 | N60: 19.4 | O60: =M60*D60 -> 268531.2 | P60: =N60*D60 -> 90442.8 | Q60: =N60+M60 -> 77
A61: d | B61: Floor -4 | C61: Sqm | D61: 4662 | E61: 60.14 | F61: 19.4 | G61: =SUM(E61:F61) -> 79.54 | H61: =$D61*E61 -> 280372.68 | I61: =$D61*F61 -> 90442.8 | J61: =SUBTOTAL(9,H61:I61) -> 370815.48 | K61: =M61-E61 -> -2.54 | L61: =N61-F61 -> 0 | M61: 57.6 | N61: 19.4 | O61: =M61*D61 -> 268531.2 | P61: =N61*D61 -> 90442.8 | Q61: =N61+M61 -> 77
A62: e | B62: Floor -5 | C62: Sqm | D62: 4662 | E62: 60.14 | F62: 19.4 | G62: =SUM(E62:F62) -> 79.54 | H62: =$D62*E62 -> 280372.68 | I62: =$D62*F62 -> 90442.8 | J62: =SUBTOTAL(9,H62:I62) -> 370815.48 | K62: =M62-E62 -> -2.54 | L62: =N62-F62 -> 0 | M62: 57.6 | N62: 19.4 | O62: =M62*D62 -> 268531.2 | P62: =N62*D62 -> 90442.8 | Q62: =N62+M62 -> 77
A63: f | B63: Floor -6 | C63: Sqm | D63: 4662 | E63: 83.42 | F63: 19.4 | G63: =SUM(E63:F63) -> 102.82 | H63: =$D63*E63 -> 388904.04 | I63: =$D63*F63 -> 90442.8 | J63: =SUBTOTAL(9,H63:I63) -> 479346.84 | K63: =M63-E63 -> 16.42 | L63: =N63-F63 -> 0 | M63: 99.84 | N63: 19.4 | O63: =M63*D63 -> 465454.08 | P63: =N63*D63 -> 90442.8 | Q63: =N63+M63 -> 119.24
A64: g | B64: Floor -7 | C64: Sqm | D64: 4662 | E64: 83.42 | F64: 19.4 | G64: =SUM(E64:F64) -> 102.82 | H64: =$D64*E64 -> 388904.04 | I64: =$D64*F64 -> 90442.8 | J64: =SUBTOTAL(9,H64:I64) -> 479346.84 | K64: =M64-E64 -> -2.78 | L64: =N64-F64 -> 0 | M64: 80.64 | N64: 19.4 | O64: =M64*D64 -> 375943.68 | P64: =N64*D64 -> 90442.8 | Q64: =N64+M64 -> 100.04
A65: h | B65: Floor -8 | C65: Sqm | D65: 4662 | E65: 83.42 | F65: 19.4 | G65: =SUM(E65:F65) -> 102.82 | H65: =$D65*E65 -> 388904.04 | I65: =$D65*F65 -> 90442.8 | J65: =SUBTOTAL(9,H65:I65) -> 479346.84 | K65: =M65-E65 -> -2.78 | L65: =N65-F65 -> 0 | M65: 80.64 | N65: 19.4 | O65: =M65*D65 -> 375943.68 | P65: =N65*D65 -> 90442.8 | Q65: =N65+M65 -> 100.04
A66: i | B66: Floor -9 | C66: Sqm | D66: 4662 | E66: 83.42 | F66: 19.4 | G66: =SUM(E66:F66) -> 102.82 | H66: =$D66*E66 -> 388904.04 | I66: =$D66*F66 -> 90442.8 | J66: =SUBTOTAL(9,H66:I66) -> 479346.84 | K66: =M66-E66 -> -2.78 | L66: =N66-F66 -> 0 | M66: 80.64 | N66: 19.4 | O66: =M66*D66 -> 375943.68 | P66: =N66*D66 -> 90442.8 | Q66: =N66+M66 -> 100.04
A67: j | B67: Floor -10 | C67: Sqm | D67: 4662 | E67: 83.42 | F67: 19.4 | G67: =SUM(E67:F67) -> 102.82 | H67: =$D67*E67 -> 388904.04 | I67: =$D67*F67 -> 90442.8 | J67: =SUBTOTAL(9,H67:I67) -> 479346.84 | K67: =M67-E67 -> -2.78 | L67: =N67-F67 -> 0 | M67: 80.64 | N67: 19.4 | O67: =M67*D67 -> 375943.68 | P67: =N67*D67 -> 90442.8 | Q67: =N67+M67 -> 100.04
A68: k | B68: Floor -11 | C68: Sqm | D68: 4662 | E68: 83.42 | F68: 19.4 | G68: =SUM(E68:F68) -> 102.82 | H68: =$D68*E68 -> 388904.04 | I68: =$D68*F68 -> 90442.8 | J68: =SUBTOTAL(9,H68:I68) -> 479346.84 | K68: =M68-E68 -> -2.78 | L68: =N68-F68 -> 0 | M68: 80.64 | N68: 19.4 | O68: =M68*D68 -> 375943.68 | P68: =N68*D68 -> 90442.8 | Q68: =N68+M68 -> 100.04
A69: l | B69: Floor -12 | C69: Sqm | D69: 4662 | E69: 83.42 | F69: 19.4 | G69: =SUM(E69:F69) -> 102.82 | H69: =$D69*E69 -> 388904.04 | I69: =$D69*F69 -> 90442.8 | J69: =SUBTOTAL(9,H69:I69) -> 479346.84 | K69: =M69-E69 -> -2.78 | L69: =N69-F69 -> 0 | M69: 80.64 | N69: 19.4 | O69: =M69*D69 -> 375943.68 | P69: =N69*D69 -> 90442.8 | Q69: =N69+M69 -> 100.04
... A80: w | B80: Terrace Floor | C80: Sqm | D80: 4662 | E80: 0 | F80: 0 | G80: =SUM(E80:F80) -> 0 | H80: =$D80*E80 -> 0 | I80: =$D80*F80 -> 0 | J80: =SUBTOTAL(9,H80:I80) -> 0 | K80: =M80-E80 -> 0 | L80: =N80-F80 -> 0 | M80: 0 | N80: 0 | O80: =M80*D80 -> 0 | P80: =N80*D80 -> 0 | Q80: =N80+M80 -> 0
A81: 7.1.4 | B81: SD4 1500x2400 mm | D81: 0 | E81: 0 | F81: 0 | G81: =SUM(E81:F81) -> 0 | H81: =ROUND(D81*E81,0) -> 0 | I81: =ROUND(D81*F81,0) -> 0 | J81: =SUM(H81:I81) -> 0 | K81: =M81-E81 -> 0 | L81: =N81-F81 -> 0 | O81: =M81*D81 -> 0 | P81: =N81*D81 -> 0 | Q81: =N81+M81 -> 0
A82: a | B82: Floor -1 | C82: Sqm | D82: 4662 | E82: 3.88 | F82: 14.55 | G82: =SUM(E82:F82) -> 18.43 | H82: =$D82*E82 -> 18088.56 | I82: =$D82*F82 -> 67832.1 | J82: =SUBTOTAL(9,H82:I82) -> 85920.66 | K82: =M82-E82 -> 14.36 | L82: =N82-F82 -> 0 | M82: 18.24 | N82: 14.55 | O82: =M82*D82 -> 85034.88 | P82: =N82*D82 -> 67832.1 | Q82: =N82+M82 -> 32.79
A83: b | B83: Floor -2 | C83: Sqm | D83: 4662 | E83: 0 | F83: 11.64 | G83: =SUM(E83:F83) -> 11.64 | H83: =$D83*E83 -> 0 | I83: =$D83*F83 -> 54265.68 | J83: =SUBTOTAL(9,H83:I83) -> 54265.68 | K83: =M83-E83 -> 21.75 | L83: =N83-F83 -> 0 | M83: 21.75 | N83: 11.64 | O83: =M83*D83 -> 101398.5 | P83: =N83*D83 -> 54265.68 | Q83: =N83+M83 -> 33.39
A84: c | B84: Floor -3 | C84: Sqm | D84: 4662 | E84: 0 | F84: 11.64 | G84: =SUM(E84:F84) -> 11.64 | H84: =$D84*E84 -> 0 | I84: =$D84*F84 -> 54265.68 | J84: =SUBTOTAL(9,H84:I84) -> 54265.68 | K84: =M84-E84 -> 7.275 | L84: =N84-F84 -> 0 | M84: 7.275 | N84: 11.64 | O84: =M84*D84 -> 33916.05 | P84: =N84*D84 -> 54265.68 | Q84: =N84+M84 -> 18.915
A85: d | B85: Floor -4 | C85: Sqm | D85: 4662 | E85: 0 | F85: 11.64 | G85: =SUM(E85:F85) -> 11.64 | H85: =$D85*E85 -> 0 | I85: =$D85*F85 -> 54265.68 | J85: =SUBTOTAL(9,H85:I85) -> 54265.68 | K85: =M85-E85 -> 7.275 | L85: =N85-F85 -> 0 | M85: 7.275 | N85: 11.64 | O85: =M85*D85 -> 33916.05 | P85: =N85*D85 -> 54265.68 | Q85: =N85+M85 -> 18.915
A86: e | B86: Floor -5 | C86: Sqm | D86: 4662 | E86: 0 | F86: 11.64 | G86: =SUM(E86:F86) -> 11.64 | H86: =$D86*E86 -> 0 | I86: =$D86*F86 -> 54265.68 | J86: =SUBTOTAL(9,H86:I86) -> 54265.68 | K86: =M86-E86 -> 14.475 | L86: =N86-F86 -> 0 | M86: 14.475 | N86: 11.64 | O86: =M86*D86 -> 67482.45 | P86: =N86*D86 -> 54265.68 | Q86: =N86+M86 -> 26.115
A87: f | B87: Floor -6 | C87: Sqm | D87: 4662 | E87: 17.46 | F87: 11.64 | G87: =SUM(E87:F87) -> 29.1 | H87: =$D87*E87 -> 81398.52 | I87: =$D87*F87 -> 54265.68 | J87: =SUBTOTAL(9,H87:I87) -> 135664.2 | K87: =M87-E87 -> 26.175 | L87: =N87-F87 -> 0 | M87: 43.635 | N87: 11.64 | O87: =M87*D87 -> 203426.37 | P87: =N87*D87 -> 54265.68 | Q87: =N87+M87 -> 55.275
A88: g | B88: Floor -7 | C88: Sqm | D88: 4662 | E88: 17.46 | F88: 11.64 | G88: =SUM(E88:F88) -> 29.1 | H88: =$D88*E88 -> 81398.52 | I88: =$D88*F88 -> 54265.68 | J88: =SUBTOTAL(9,H88:I88) -> 135664.2 | K88: =M88-E88 -> -2.91 | L88: =N88-F88 -> 0 | M88: 14.55 | N88: 11.64 | O88: =M88*D88 -> 67832.1 | P88: =N88*D88 -> 54265.68 | Q88: =N88+M88 -> 26.19
A89: h | B89: Floor -8 | C89: Sqm | D89: 4662 | E89: 17.46 | F89: 11.64 | G89: =SUM(E89:F89) -> 29.1 | H89: =$D89*E89 -> 81398.52 | I89: =$D89*F89 -> 54265.68 | J89: =SUBTOTAL(9,H89:I89) -> 135664.2 | K89: =M89-E89 -> -2.91 | L89: =N89-F89 -> 0 | M89: 14.55 | N89: 11.64 | O89: =M89*D89 -> 67832.1 | P89: =N89*D89 -> 54265.68 | Q89: =N89+M89 -> 26.19
A90: i | B90: Floor -9 | C90: Sqm | D90: 4662 | E90: 17.46 | F90: 11.64 | G90: =SUM(E90:F90) -> 29.1 | H90: =$D90*E90 -> 81398.52 | I90: =$D90*F90 -> 54265.68 | J90: =SUBTOTAL(9,H90:I90) -> 135664.2 | K90: =M90-E90 -> -2.91 | L90: =N90-F90 -> 0 | M90: 14.55 | N90: 11.64 | O90: =M90*D90 -> 67832.1 | P90: =N90*D90 -> 54265.68 | Q90: =N90+M90 -> 26.19
A91: j | B91: Floor -10 | C91: Sqm | D91: 4662 | E91: 17.46 | F91: 11.64 | G91: =SUM(E91:F91) -> 29.1 | H91: =$D91*E91 -> 81398.52 | I91: =$D91*F91 -> 54265.68 | J91: =SUBTOTAL(9,H91:I91) -> 135664.2 | K91: =M91-E91 -> -2.91 | L91: =N91-F91 -> 0 | M91: 14.55 | N91: 11.64 | O91: =M91*D91 -> 67832.1 | P91: =N91*D91 -> 54265.68 | Q91: =N91+M91 -> 26.19
A92: k | B92: Floor -11 | C92: Sqm | D92: 4662 | E92: 17.46 | F92: 11.64 | G92: =SUM(E92:F92) -> 29.1 | H92: =$D92*E92 -> 81398.52 | I92: =$D92*F92 -> 54265.68 | J92: =SUBTOTAL(9,H92:I92) -> 135664.2 | K92: =M92-E92 -> -2.91 | L92: =N92-F92 -> 0 | M92: 14.55 | N92: 11.64 | O92: =M92*D92 -> 67832.1 | P92: =N92*D92 -> 54265.68 | Q92: =N92+M92 -> 26.19
A93: l | B93: Floor -12 | C93: Sqm | D93: 4662 | E93: 17.46 | F93: 11.64 | G93: =SUM(E93:F93) -> 29.1 | H93: =$D93*E93 -> 81398.52 | I93: =$D93*F93 -> 54265.68 | J93: =SUBTOTAL(9,H93:I93) -> 135664.2 | K93: =M93-E93 -> -2.91 | L93: =N93-F93 -> 0 | M93: 14.55 | N93: 11.64 | O93: =M93*D93 -> 67832.1 | P93: =N93*D93 -> 54265.68 | Q93: =N93+M93 -> 26.19
... A104: w | B104: Terrace Floor | C104: Sqm | D104: 4662 | E104: 0 | F104: 0 | G104: =SUM(E104:F104) -> 0 | H104: =$D104*E104 -> 0 | I104: =$D104*F104 -> 0 | J104: =SUBTOTAL(9,H104:I104) -> 0 | K104: =M104-E104 -> 0 | L104: =N104-F104 -> 0 | M104: 0 | N104: 0 | O104: =M104*D104 -> 0 | P104: =N104*D104 -> 0 | Q104: =N104+M104 -> 0
A105: 7.2 | B105: Providing & fixing 2.5 track UPVC glazed Sliding panel window consisting of 2 glazed panels with 6mm thk Clear glass and mosquito mesh and the window should have a provision for fixing of exhaust fan, all frame & shutter sections well reinforced as specified in the technical specifications etc as per the drawing enclosed complete at all levels. All the UPVC sections shall be finished in a fully automatic plant equipped for such work as per the specifications. Weather sealant of Dowcorning / Momentive to be applied on the periphery of the window on both sides.Weather strip at every panel sides that restricts entry of mosquito and maintain temparature inside rooms All Windows to be approved hardware by the architect/client. The movement of the sliding shutter should have smooth movement. colour ofthe single point lock to be as per the approvel of the client/architect. shop drawings to be approved prior to start of procurement/fabrication of windows. The EPDM gasket should be oven cured and neatly mitre joint at junctions.The drain/weep hole and its cover is also placed at required intervals that not allows water stagnates on trackes between and drains smoothly out. The complete system is well protected with films till final hand over. | D105: 0 | E105: 0 | F105: 0 | G105: =SUM(E105:F105) -> 0 | H105: =ROUND(D105*E105,0) -> 0 | I105: =ROUND(D105*F105,0) -> 0 | J105: =SUM(H105:I105) -> 0 | K105: =M105-E105 -> 0 | L105: =N105-F105 -> 0 | O105: =M105*D105 -> 0 | P105: =N105*D105 -> 0 | Q105: =N105+M105 -> 0
A106: 7.2.1 | B106: KW1 1200x1300 mm | D106: 0 | E106: 0 | F106: 0 | G106: =SUM(E106:F106) -> 0 | H106: =ROUND(D106*E106,0) -> 0 | I106: =ROUND(D106*F106,0) -> 0 | J106: =SUM(H106:I106) -> 0 | K106: =M106-E106 -> 0 | L106: =N106-F106 -> 0 | O106: =M106*D106 -> 0 | P106: =N106*D106 -> 0 | Q106: =N106+M106 -> 0
A107: a | B107: Floor -1 | C107: Sqm | D107: 4662 | E107: 36.86 | F107: 22.31 | G107: =SUM(E107:F107) -> 59.17 | H107: =$D107*E107 -> 171841.32 | I107: =$D107*F107 -> 104009.22 | J107: =SUBTOTAL(9,H107:I107) -> 275850.54 | K107: =M107-E107 -> 0.58 | L107: =N107-F107 -> 0 | M107: 37.44 | N107: 22.31 | O107: =M107*D107 -> 174545.28 | P107: =N107*D107 -> 104009.22 | Q107: =N107+M107 -> 59.75
A108: b | B108: Floor -2 | C108: Sqm | D108: 4662 | E108: 56.26 | F108: 22.31 | G108: =SUM(E108:F108) -> 78.57 | H108: =$D108*E108 -> 262284.12 | I108: =$D108*F108 -> 104009.22 | J108: =SUBTOTAL(9,H108:I108) -> 366293.34 | K108: =M108-E108 -> -0.1 | L108: =N108-F108 -> 0 | M108: 56.16 | N108: 22.31 | O108: =M108*D108 -> 261817.92 | P108: =N108*D108 -> 104009.22 | Q108: =N108+M108 -> 78.47
A109: c | B109: Floor -3 | C109: Sqm | D109: 4662 | E109: 56.26 | F109: 22.31 | G109: =SUM(E109:F109) -> 78.57 | H109: =$D109*E109 -> 262284.12 | I109: =$D109*F109 -> 104009.22 | J109: =SUBTOTAL(9,H109:I109) -> 366293.34 | K109: =M109-E109 -> -0.1 | L109: =N109-F109 -> 0 | M109: 56.16 | N109: 22.31 | O109: =M109*D109 -> 261817.92 | P109: =N109*D109 -> 104009.22 | Q109: =N109+M109 -> 78.47
A110: d | B110: Floor -4 | C110: Sqm | D110: 4662 | E110: 56.26 | F110: 22.31 | G110: =SUM(E110:F110) -> 78.57 | H110: =$D110*E110 -> 262284.12 | I110: =$D110*F110 -> 104009.22 | J110: =SUBTOTAL(9,H110:I110) -> 366293.34 | K110: =M110-E110 -> -0.1 | L110: =N110-F110 -> 0 | M110: 56.16 | N110: 22.31 | O110: =M110*D110 -> 261817.92 | P110: =N110*D110 -> 104009.22 | Q110: =N110+M110 -> 78.47
A111: e | B111: Floor -5 | C111: Sqm | D111: 4662 | E111: 56.26 | F111: 22.31 | G111: =SUM(E111:F111) -> 78.57 | H111: =$D111*E111 -> 262284.12 | I111: =$D111*F111 -> 104009.22 | J111: =SUBTOTAL(9,H111:I111) -> 366293.34 | K111: =M111-E111 -> -0.1 | L111: =N111-F111 -> 0 | M111: 56.16 | N111: 22.31 | O111: =M111*D111 -> 261817.92 | P111: =N111*D111 -> 104009.22 | Q111: =N111+M111 -> 78.47
A112: f | B112: Floor -6 | C112: Sqm | D112: 4662 | E112: 88.27 | F112: 22.31 | G112: =SUM(E112:F112) -> 110.58 | H112: =$D112*E112 -> 411514.74 | I112: =$D112*F112 -> 104009.22 | J112: =SUBTOTAL(9,H112:I112) -> 515523.96 | K112: =M112-E112 -> -4.03 | L112: =N112-F112 -> 0 | M112: 84.24 | N112: 22.31 | O112: =M112*D112 -> 392726.88 | P112: =N112*D112 -> 104009.22 | Q112: =N112+M112 -> 106.55
A113: g | B113: Floor -7 | C113: Sqm | D113: 4662 | E113: 88.27 | F113: 22.31 | G113: =SUM(E113:F113) -> 110.58 | H113: =$D113*E113 -> 411514.74 | I113: =$D113*F113 -> 104009.22 | J113: =SUBTOTAL(9,H113:I113) -> 515523.96 | K113: =M113-E113 -> -4.03 | L113: =N113-F113 -> 0 | M113: 84.24 | N113: 22.31 | O113: =M113*D113 -> 392726.88 | P113: =N113*D113 -> 104009.22 | Q113: =N113+M113 -> 106.55
A114: h | B114: Floor -8 | C114: Sqm | D114: 4662 | E114: 88.27 | F114: 22.31 | G114: =SUM(E114:F114) -> 110.58 | H114: =$D114*E114 -> 411514.74 | I114: =$D114*F114 -> 104009.22 | J114: =SUBTOTAL(9,H114:I114) -> 515523.96 | K114: =M114-E114 -> -4.03 | L114: =N114-F114 -> 0 | M114: 84.24 | N114: 22.31 | O114: =M114*D114 -> 392726.88 | P114: =N114*D114 -> 104009.22 | Q114: =N114+M114 -> 106.55
A115: i | B115: Floor -9 | C115: Sqm | D115: 4662 | E115: 88.27 | F115: 22.31 | G115: =SUM(E115:F115) -> 110.58 | H115: =$D115*E115 -> 411514.74 | I115: =$D115*F115 -> 104009.22 | J115: =SUBTOTAL(9,H115:I115) -> 515523.96 | K115: =M115-E115 -> -4.03 | L115: =N115-F115 -> 0 | M115: 84.24 | N115: 22.31 | O115: =M115*D115 -> 392726.88 | P115: =N115*D115 -> 104009.22 | Q115: =N115+M115 -> 106.55
A116: j | B116: Floor -10 | C116: Sqm | D116: 4662 | E116: 88.27 | F116: 22.31 | G116: =SUM(E116:F116) -> 110.58 | H116: =$D116*E116 -> 411514.74 | I116: =$D116*F116 -> 104009.22 | J116: =SUBTOTAL(9,H116:I116) -> 515523.96 | K116: =M116-E116 -> -4.03 | L116: =N116-F116 -> 0 | M116: 84.24 | N116: 22.31 | O116: =M116*D116 -> 392726.88 | P116: =N116*D116 -> 104009.22 | Q116: =N116+M116 -> 106.55
A117: k | B117: Floor -11 | C117: Sqm | D117: 4662 | E117: 88.27 | F117: 22.31 | G117: =SUM(E117:F117) -> 110.58 | H117: =$D117*E117 -> 411514.74 | I117: =$D117*F117 -> 104009.22 | J117: =SUBTOTAL(9,H117:I117) -> 515523.96 | K117: =M117-E117 -> -4.03 | L117: =N117-F117 -> 0 | M117: 84.24 | N117: 22.31 | O117: =M117*D117 -> 392726.88 | P117: =N117*D117 -> 104009.22 | Q117: =N117+M117 -> 106.55
A118: l | B118: Floor -12 | C118: Sqm | D118: 4662 | E118: 88.27 | F118: 22.31 | G118: =SUM(E118:F118) -> 110.58 | H118: =$D118*E118 -> 411514.74 | I118: =$D118*F118 -> 104009.22 | J118: =SUBTOTAL(9,H118:I118) -> 515523.96 | K118: =M118-E118 -> -4.03 | L118: =N118-F118 -> 0 | M118: 84.24 | N118: 22.31 | O118: =M118*D118 -> 392726.88 | P118: =N118*D118 -> 104009.22 | Q118: =N118+M118 -> 106.55
... A129: w | B129: Terrace Floor | C129: Sqm | D129: 4662 | E129: 0 | F129: 0 | G129: =SUM(E129:F129) -> 0 | H129: =$D129*E129 -> 0 | I129: =$D129*F129 -> 0 | J129: =SUBTOTAL(9,H129:I129) -> 0 | K129: =M129-E129 -> 0 | L129: =N129-F129 -> 0 | M129: 0 | N129: 0 | O129: =M129*D129 -> 0 | P129: =N129*D129 -> 0 | Q129: =N129+M129 -> 0
A130: 7.3 | B130: Providing & fixing 2.5track UPVC glazed Sliding window consisting of 2 glazed panels with 6 mm thk Clear glass as per the drawing enclosed complete at all levels. All the UPVC sections shall be finished in a fully automatic plant equipped for such work as per the specifications. all frame & shutter sections well reinforced as specified in the technical specifications etc Weather sealant of Dowcorning/Momentive to be applied on the periphery of the window on both sides. All Windows to be approved hardware by the architect/client. .Weather strip at every panel sides that restricts entry of mosquito and maintain temparature inside roomsThe movement of the sliding shutter should have smooth movement. colour ofthe single point lock to be as per the approval of the client/architect. shop drawings to be approved prior to start of procurement/fabrication of windows. The EPDM gasket should be oven cured.and neatly mitre joint at junctions.The drain/weep hole and its cover is also placed at required intervals that not allows water stagnates on trackes between and drains smoothly out. The complete system is well protected with films till final hand over. Location: Staircase Areas | D130: 0 | E130: 0 | F130: 0 | G130: =SUM(E130:F130) -> 0 | H130: =ROUND(D130*E130,0) -> 0 | I130: =ROUND(D130*F130,0) -> 0 | J130: =SUM(H130:I130) -> 0 | K130: =M130-E130 -> 0 | L130: =N130-F130 -> 0 | O130: =M130*D130 -> 0 | P130: =N130*D130 -> 0 | Q130: =N130+M130 -> 0
A131: 7.3.1 | B131: SW-1500X1200mm | D131: 0 | E131: 0 | F131: 0 | G131: =SUM(E131:F131) -> 0 | H131: =ROUND(D131*E131,0) -> 0 | I131: =ROUND(D131*F131,0) -> 0 | J131: =SUM(H131:I131) -> 0 | K131: =M131-E131 -> 0 | L131: =N131-F131 -> 0 | O131: =M131*D131 -> 0 | P131: =N131*D131 -> 0 | Q131: =N131+M131 -> 0
A132: a | B132: Basement floor | C132: Sqm | D132: 4662 | E132: 1.94 | F132: 1.94 | G132: =SUM(E132:F132) -> 3.88 | H132: =$D132*E132 -> 9044.28 | I132: =$D132*F132 -> 9044.28 | J132: =SUBTOTAL(9,H132:I132) -> 18088.56 | K132: =M132-E132 -> -1.94 | L132: =N132-F132 -> -1.94 | M132: 0 | N132: 0 | O132: =M132*D132 -> 0 | P132: =N132*D132 -> 0 | Q132: =N132+M132 -> 0
A133: b | B133: Ground floor | C133: Sqm | D133: 4662 | E133: 19.4 | F133: 6.79 | G133: =SUM(E133:F133) -> 26.19 | H133: =$D133*E133 -> 90442.8 | I133: =$D133*F133 -> 31654.98 | J133: =SUBTOTAL(9,H133:I133) -> 122097.78 | K133: =M133-E133 -> -19.4 | L133: =N133-F133 -> -6.79 | M133: 0 | N133: 0 | O133: =M133*D133 -> 0 | P133: =N133*D133 -> 0 | Q133: =N133+M133 -> 0
A134: c | B134: Floor -1 | C134: Sqm | D134: 4662 | E134: 45.59 | F134: 9.7 | G134: =SUM(E134:F134) -> 55.29 | H134: =$D134*E134 -> 212540.58 | I134: =$D134*F134 -> 45221.4 | J134: =SUBTOTAL(9,H134:I134) -> 257761.98 | K134: =M134-E134 -> -45.59 | L134: =N134-F134 -> -9.7 | M134: 0 | N134: 0 | O134: =M134*D134 -> 0 | P134: =N134*D134 -> 0 | Q134: =N134+M134 -> 0
A135: d | B135: Floor -2 | C135: Sqm | D135: 4662 | E135: 47.53 | F135: 9.7 | G135: =SUM(E135:F135) -> 57.23 | H135: =$D135*E135 -> 221584.86 | I135: =$D135*F135 -> 45221.4 | J135: =SUBTOTAL(9,H135:I135) -> 266806.26 | K135: =M135-E135 -> -47.53 | L135: =N135-F135 -> -9.7 | M135: 0 | N135: 0 | O135: =M135*D135 -> 0 | P135: =N135*D135 -> 0 | Q135: =N135+M135 -> 0
A136: e | B136: Floor -3 | C136: Sqm | D136: 4662 | E136: 47.53 | F136: 9.7 | G136: =SUM(E136:F136) -> 57.23 | H136: =$D136*E136 -> 221584.86 | I136: =$D136*F136 -> 45221.4 | J136: =SUBTOTAL(9,H136:I136) -> 266806.26 | K136: =M136-E136 -> -47.53 | L136: =N136-F136 -> -9.7 | M136: 0 | N136: 0 | O136: =M136*D136 -> 0 | P136: =N136*D136 -> 0 | Q136: =N136+M136 -> 0
A137: f | B137: Floor -4 | C137: Sqm | D137: 4662 | E137: 47.53 | F137: 9.7 | G137: =SUM(E137:F137) -> 57.23 | H137: =$D137*E137 -> 221584.86 | I137: =$D137*F137 -> 45221.4 | J137: =SUBTOTAL(9,H137:I137) -> 266806.26 | K137: =M137-E137 -> -47.53 | L137: =N137-F137 -> -9.7 | M137: 0 | N137: 0 | O137: =M137*D137 -> 0 | P137: =N137*D137 -> 0 | Q137: =N137+M137 -> 0
A138: g | B138: Floor -5 | C138: Sqm | D138: 4662 | E138: 47.53 | F138: 9.7 | G138: =SUM(E138:F138) -> 57.23 | H138: =$D138*E138 -> 221584.86 | I138: =$D138*F138 -> 45221.4 | J138: =SUBTOTAL(9,H138:I138) -> 266806.26 | K138: =M138-E138 -> -47.53 | L138: =N138-F138 -> -9.7 | M138: 0 | N138: 0 | O138: =M138*D138 -> 0 | P138: =N138*D138 -> 0 | Q138: =N138+M138 -> 0
A139: h | B139: Floor -6 | C139: Sqm | D139: 4662 | E139: 47.53 | F139: 9.7 | G139: =SUM(E139:F139) -> 57.23 | H139: =$D139*E139 -> 221584.86 | I139: =$D139*F139 -> 45221.4 | J139: =SUBTOTAL(9,H139:I139) -> 266806.26 | K139: =M139-E139 -> -47.53 | L139: =N139-F139 -> -9.7 | M139: 0 | N139: 0 | O139: =M139*D139 -> 0 | P139: =N139*D139 -> 0 | Q139: =N139+M139 -> 0
A140: i | B140: Floor -7 | C140: Sqm | D140: 4662 | E140: 47.53 | F140: 9.7 | G140: =SUM(E140:F140) -> 57.23 | H140: =$D140*E140 -> 221584.86 | I140: =$D140*F140 -> 45221.4 | J140: =SUBTOTAL(9,H140:I140) -> 266806.26 | K140: =M140-E140 -> -47.53 | L140: =N140-F140 -> -9.7 | M140: 0 | N140: 0 | O140: =M140*D140 -> 0 | P140: =N140*D140 -> 0 | Q140: =N140+M140 -> 0
A141: j | B141: Floor -8 | C141: Sqm | D141: 4662 | E141: 47.53 | F141: 9.7 | G141: =SUM(E141:F141) -> 57.23 | H141: =$D141*E141 -> 221584.86 | I141: =$D141*F141 -> 45221.4 | J141: =SUBTOTAL(9,H141:I141) -> 266806.26 | K141: =M141-E141 -> -47.53 | L141: =N141-F141 -> -9.7 | M141: 0 | N141: 0 | O141: =M141*D141 -> 0 | P141: =N141*D141 -> 0 | Q141: =N141+M141 -> 0
A142: k | B142: Floor -9 | C142: Sqm | D142: 4662 | E142: 47.53 | F142: 9.7 | G142: =SUM(E142:F142) -> 57.23 | H142: =$D142*E142 -> 221584.86 | I142: =$D142*F142 -> 45221.4 | J142: =SUBTOTAL(9,H142:I142) -> 266806.26 | K142: =M142-E142 -> -47.53 | L142: =N142-F142 -> -9.7 | M142: 0 | N142: 0 | O142: =M142*D142 -> 0 | P142: =N142*D142 -> 0 | Q142: =N142+M142 -> 0
A143: l | B143: Floor -10 | C143: Sqm | D143: 4662 | E143: 47.53 | F143: 9.7 | G143: =SUM(E143:F143) -> 57.23 | H143: =$D143*E143 -> 221584.86 | I143: =$D143*F143 -> 45221.4 | J143: =SUBTOTAL(9,H143:I143) -> 266806.26 | K143: =M143-E143 -> -47.53 | L143: =N143-F143 -> -9.7 | M143: 0 | N143: 0 | O143: =M143*D143 -> 0 | P143: =N143*D143 -> 0 | Q143: =N143+M143 -> 0
... A156: y | B156: Terrace Floor | C156: Sqm | D156: 4662 | E156: 0 | F156: 0 | G156: =SUM(E156:F156) -> 0 | H156: =$D156*E156 -> 0 | I156: =$D156*F156 -> 0 | J156: =SUBTOTAL(9,H156:I156) -> 0 | K156: =M156-E156 -> 0 | L156: =N156-F156 -> 0 | M156: 0 | N156: 0 | O156: =M156*D156 -> 0 | P156: =N156*D156 -> 0 | Q156: =N156+M156 -> 0
A157: 7.3.2 | B157: SW1-900X1200mm | D157: 0 | E157: 0 | F157: 0 | G157: =SUM(E157:F157) -> 0 | H157: =ROUND(D157*E157,0) -> 0 | I157: =ROUND(D157*F157,0) -> 0 | J157: =SUM(H157:I157) -> 0 | K157: =M157-E157 -> 0 | L157: =N157-F157 -> 0 | O157: =M157*D157 -> 0 | P157: =N157*D157 -> 0 | Q157: =N157+M157 -> 0
A158: a | B158: Basement floor | C158: Sqm | D158: 4662 | E158: 0 | F158: 3.88 | G158: =SUM(E158:F158) -> 3.88 | H158: =$D158*E158 -> 0 | I158: =$D158*F158 -> 18088.56 | J158: =SUBTOTAL(9,H158:I158) -> 18088.56 | K158: =M158-E158 -> 0 | L158: =N158-F158 -> -3.88 | M158: 0 | N158: 0 | O158: =M158*D158 -> 0 | P158: =N158*D158 -> 0 | Q158: =N158+M158 -> 0
A159: b | B159: Ground floor | C159: Sqm | D159: 4662 | E159: 22.31 | F159: 5.82 | G159: =SUM(E159:F159) -> 28.13 | H159: =$D159*E159 -> 104009.22 | I159: =$D159*F159 -> 27132.84 | J159: =SUBTOTAL(9,H159:I159) -> 131142.06 | K159: =M159-E159 -> -22.31 | L159: =N159-F159 -> -5.82 | M159: 0 | N159: 0 | O159: =M159*D159 -> 0 | P159: =N159*D159 -> 0 | Q159: =N159+M159 -> 0
...

Sheet NT_01
A3: BOQ FOR NON TENDERED ITEMS #01
A4: Item No. | B4: Description of works | C4: UOM | D4: Qty | E4: Rate | F4: Amount (Rs.)
A5: B | B5: NT Items
A6: B.1 | B6: Additional aluminium formwork for nib walls (Extra rate over and above existing BOQ line item)
A7: B.1.1 | B7: Extra rate over and above existing BOQ line item for mobilisation, providing and demobilisation of Additional aluminium modular formwork due to design change for nib walls. | C7: LS | D7: 1 | E7: 10,00,000 | F7: 10,00,000
A8: Total Amount (Excl GST) | F8: 1000000

Sheet NT_02
A1: Project : Provident Ecopolitan-Phase-01
A2: Subject : BOQ for NT Items #02
A4: Sl.No | B4: Description | C4: Unit | D4: Qty | E4: Rate | F4: Amount | G4: Remarks
B6: NT-Items Set # 02 Phase-01
A7: 1 | B7: Providing & filling Plumbing Groove with M15 Grade 1:2:4 in Kitchen,Utility & Toilets,Width considered 50 to 75MM Complete as directed by the Architects / Engineer in charge. | C7: Rmt | D7: 22830.033 | E7: 170 | F7: =$D7*E7 -> 3881105.6
A8: 2 | B8: Providing & fixing Reinforcement Steel of 8mm Dia (150mm deep)TMT bar with Hilti HY 200 R chemical including drilling of required size hole and fixing complete in all respect for all height and depths ( Reinforcement steel Excluded) | C8: Nos | D8: 127 | E8: 212 | F8: =$D8*E8 -> 26924
A9: 3 | B9: Providing & fixing Reinforcement Steel of 10mm dia (150mm deep)TMT bar with Hilti HY 200 R chemical including drilling of required size hole and fixing complete in all respect for all height and depths ( Reinforcement steel Excluded) | C9: Nos | D9: 138 | E9: 250 | F9: =$D9*E9 -> 34500
A10: 4 | B10: Providing & fixing Reinforcement Steel of 12mm Dia (150mm deep)TMT bar with Hilti HY 200 R chemical including drilling of required size hole and fixing complete in all respect for all height and depths ( Reinforcement steel Excluded) | C10: Nos | D10: 134 | E10: 365 | F10: =$D10*E10 -> 48910
A11: 5 | B11: Providing & fixing Reinforcement Steel of 16mm Dia (150mm deep)TMT bar with Hilti HY 200 R chemical including drilling of required size hole and fixing complete in all respect for all height and depths ( Reinforcement steel Excluded) | C11: Nos | D11: 318 | E11: 535 | F11: =$D11*E11 -> 170130
A12: 6 | B12: Providing & fixing Reinforcement Steel of 20mm Dia (150mm deep)TMT bar with Hilti HY 200 R chemical including drilling of required size hole and fixing complete in all respect for all height and depths ( Reinforcement steel Excluded) | C12: Nos | D12: 220 | E12: 780 | F12: =$D12*E12 -> 171600
A13: 7 | B13: Additional Staging for Slab Shuttering Works as perAnnexure 2C, Statement of Bid Clarifications. | C13: Cum | D13: 11665.632 | E13: 185 | F13: =$D13*E13 -> 2158142
A14: 8 | B14: Providing and Fixing of Anchor Bolts for MS Railings Hilti HSV-R2 M12X100 SS A2 as per Bid Statement clarifications mentioned in Sl No 63 page-70 | C14: Nos | D14: 9984 | E14: 205 | F14: =$D14*E14 -> 2046720
A15: 9 | B15: Providing and fixing gypsum board cornice of 10 mm thickness, fixed on a framework of aluminium sections up to 200mmx200mm in internal flats for concealing firefighting lines inside flats as per design and drawing. The work shall include all necessary supports, fasteners, jointing, etc | C15: Rmt | D15: 9719.015 | E15: 385 | F15: =$D15*E15 -> 3741820.8
A16: 10 | B16: Cleaning the surface area to ensure that it is free from oil, grease, dirt and contaminants, all loose materials to be removed and roughen the pipe with wire brush. Apply FOSROC SBR LATEX or equivalent for pipe and the bore for better adhesion between the pipe and concrete member. Place the backer rod in the gap between the core and the pipe, push the backer rod to the required depth and fill the bore with FOSROC CONBEXTRA GP2 or equivalent -Upto 110mm dia of Pipe with dia of core upto 125mm (Bore packing) | C16: No | D16: 4134 | E16: 340 | F16: =$D16*E16 -> 1405560
A17: 11 | B17: Cleaning the surface area to ensure that it is free from oil, grease, dirt and contaminants, all loose materials to be removed and roughen the pipe with wire brush. Apply FOSROC SBR LATEX or equivalent for pipe and the bore for better adhesion between the pipe and concrete member. Place the backer rod in the gap between the core and the pipe, push the backer rod to the required depth and fill the bore with FOSROC CONBEXTRA GP2 or equivalent -Upto 75mm dia of Pipe with dia of core upto 125mm (Bore packing) | C17: No | D17: 4677 | E17: 300 | F17: =$D17*E17 -> 1403100
A18: 12 | B18: Cleaning the surface area to ensure that it is free from oil, grease, dirt and contaminants, all loose materials to be removed and roughen the pipe with wire brush. Apply FOSROC SBR LATEX or equivalent for pipe and the bore for better adhesion between the pipe and concrete member. Place the backer rod in the gap between the core and the pipe, push the backer rod to the required depth and fill the bore with FOSROC CONBEXTRA GP2 or equivalent -Upto 40mm dia of Pipe with dia of core upto 50mm(Bore packing) | C18: No | D18: 3979 | E18: 265 | F18: =$D18*E18 -> 1054435
A19: 13 | B19: Providing & laying a 1.2mm thick HDPE membrane of approved make, having a self-adhesive HDPE membrane 1. Elongation as per ASTM D 412 shall be > 400% 2. Puncture Resistance as per ASTM E 154 modified shall be > 600N 3. Tensile strength as per ASTM D 412 shall be > 17 MPa 4. Peel adhesion to concrete as per ASTM D 903 shall be 2.5N/mm. 5. UV resistance of min. 45 days and conforming to BS 8102:2009 as per the manufacturer's recommendation. Surface Preparation: 1. The membrane to be fixed on the other side wall, with anchor nails, adhesive tapes/termination bars as per the manufacturer's recommendation 2. The lapping of the membrane is to be done as per factory-made selvedges and as per the manufacturer's recommendation 3. The Membrane to be terminated at the surface level with a recommended detail The mode of measurement will be applied surface area. | C19: =[8]ABS!$C$9 -> Sqm | D19: 113 | E19: 920 | F19: =$D19*E19 -> 103960
A20: 14 | B20: Providing & fixing Toilet washbasin counter 18 to 20mm thk. polished Granite slab of approved shade for toilet counters, with 75 mm facia (from counter top to facia bottom)to cover MS angle support structure as per the instructions of Client / the Engineer. The Rate includes supporting MS structure as per the drawing & a coat of zinc chromate primer & 2 coats of Synthetic Enamel paint of approved make & color with all leads and lifts at all levels and heights and as directed by Client / the Engineer. Counter Size - 625 x 525mm | C20: No's | D20: 2035 | E20: 4500 | F20: =$D20*E20 -> 9157500
B21: Total Amount (Excl GST) | F21: =SUM(F7:F20) -> 25404407

Sheet NT_03
A1: Project : Provident Ecopolitan-Phase-01
A2: Subject : BOQ for NT Items #03
A4: Sl.No | B4: Description | C4: Unit | D4: Qty | G4: Rate | H4: Amount | K4: Remarks
B6: NT-Items Set # 03 | D6: PH-1 | E6: PH-2 | F6: TOTAL | H6: PH-1 | I6: PH-2 | J6: TOTAL
A7: 1 | B7: Providing and fixing of openable and fixed duct with aluminium 30x30x1.3 square tube system with 3mm ACP Covering and mid stiffner for dark grey ACP by 19x19 L angle for MBR Balcony PHE rain water Duct of two different sizes(L Shape (250+250)*2630) and (250*2630mm).Rate inclusive of silicon filling in the wall and sheet joints. All details as per mock up approved at site. | C7: Sqm | D7: 275.55 | E7: 34.19 | F7: =D7+E7 -> 309.74 | G7: =ROUND(1790*1.15,2) -> 2058.5 | H7: =$D7*G7 -> 567219.68 | I7: =E7*G7 -> 70380.115 | J7: =H7+I7 -> 637599.79 | K7: The Rates are finalized with the Specialized Vendor M/s Priya Engineering. The agreed Payment Terms will be Back to back.
A8: =A7+1 -> 2 | B8: Providing and fixing of openable duct with aluminium 30x30x1.3 square tube & 19x19x1.5 mm architrave system with 3mm ACP Covering and mid stiffner for ACP by 19x19 L angle for opening in Balcony.Rate inclusive of silicon filling in the wall and sheet joints. All details as per mock up approved at site. | C8: Sqm | D8: 2379.926 | E8: 10.6515 | F8: =D8+E8 -> 2390.5775 | G8: =ROUND(2251*1.15,0) -> 2589 | H8: =$D8*G8 -> 6161628.4 | I8: =E8*G8 -> 27576.734 | J8: =H8+I8 -> 6189205.1
A9: 3 | B9: Extra rate for tiles unloading at Site for all type of tiles and Sizes | C9: Sqm | D9: 137455.41 | E9: 46714.304 | F9: =D9+E9 -> 184169.71 | G9: 9.1 | H9: =$D9*G9 -> 1250844.2 | I9: =E9*G9 -> 425100.17 | J9: =H9+I9 -> 1675944.4
B10: Total Amount (Excl GST) | H10: =SUM(H7:H9) -> 7979692.3 | I10: =SUM(I7:I9) -> 523057.02 | J10: =SUM(J7:J9) -> 8502749.3
H13: 23319824

Sheet Compound Wall Works
B1: PROJECT: | C1: PROVIDENT ECOPOLITAN
B2: SUBJECT: | C2: EXTERNAL DRAIN AND COMPOUND WALL WORKS BOQ (FOR ENTIRE PROJECT)
B4: SI NO | C4: DESCRIPTION | D4: UOM | E4: QTY | F4: RATE | G4: AMOUNT
B5: A | C5: EXCAVATION WORKS
B6: 1 | C6: Excavation in all types of soil including dense soil, disintegrated/ weathered/ soft rock (Poclainable) for catch pits, trenches,drains, etc., by mechanical means including manual excavation for levelling, dressing the edges, with all leads and lifts. Dewatering of both ground and surface water, removal of slurry generated while excavation and keeping the area free of water with necessary shoring, strutting, required for keeping earth in position etc., Note:PCC area shall be considered for measurement (Working space & provision of slopes if required for execution shall not be paid separately).
B7: i | C7: Depth upto 1.50m | D7: Cum | E7: 1285.76 | F7: 243 | G7: =ROUND(E7*F7,0) -> 312440
B8: ii | C8: From 1.50m to 3.0m | D8: Cum | E8: 708.42 | F8: 243 | G8: =ROUND(E8*F8,0) -> 172146
B9: iii | C9: From 3.0m to 6.0m | D9: Cum | E9: 3890.36 | F9: 243 | G9: =ROUND(E9*F9,0) -> 945357
B10: 2 | C10: Specification & scope of work same as 1 but for Excavation in Hard rock / boulders (more than 1/2 Cum in size -Un poclainable) by chiselling/ wedging to required level for Raft, Footings of columns, Retaining walls, Core walls, catch pits, Lift pits,STP,UG tanks, trenches for drains, etc. to the required depth including all leads and lifts, dressing, grading, cleaning, excavating loose pockets directed and disposing etc. as per detailed specification and conforming to safety rules of Authority during the progress of work. Note: The percentage of voids to be deducted from stack measurement is 40% for hardrock or Initial levels will be taken before blasting hard rock and final levels will be taken after achieving required levels in presence of PIC. Note:PCC area shall be considered for measurement (Working space & provision of slopes if required for execution shall not be paid separately. Mode of measurement shall be by joint measurements/ levels before and after excavation). | D10: Cum | E10: 5 | F10: 2774 | G10: =ROUND(E10*F10,0) -> 13870
B11: 3 | C11: Supply and filling in foundations and the area wherever specified with approved good quality filling materials in plinths, area development etc. wherever specified in layers of not exceeding 200 mm thick including breaking clods,storing,transportation ,double handling, watering, compacting each layer with vibratory compactor and at unaccessible places with wooden/steel rammers to achieve 95% proctor density at optimum moisture content, all leads and lifts, bailing/ pumping out of water to keep site dry while backfilling; cost shall include conveyance of all materials, labour, machinery etc. complete as directed. The rate to includes loading, unloading, hire and fuel charges for tools and plants and other incidental charges etc., complete. | F11: 0 | G11: =ROUND(E11*F11,0) -> 0
B12: i | C12: With excavated earth available at site | D12: Cum | E12: 1767.99 | F12: 150 | G12: =ROUND(E12*F12,0) -> 265199
B13: 4 | C13: Carting away surplus earth/excavated material/debris/rock and like materials outside the plot and disposing off the same to the designated areas identified by the local authorities / project managers for dumping of such material, including spreading, compacting etc.,as per the norms by the local authorities. Mode of measurement- where measurement is not possible by level. i) Soil - truck measurement less 20% for voids. ii) Hard Rock - truck measurement less 50% for voids iii) Debris - truck measurement less 30% for voids. | D13: Cum | E13: 4121.54 | F13: 278 | G13: =ROUND(E13*F13,0) -> 1145788
B14: B | C14: PCC WORKS | F14: 0
B15: 1 | C15: Providing and laying Plain Cement Concrete M10 grade (1:3:6) following to the minimum depth 100mm to 150mm using graded granite aggregate of 20mm and down size, including all material at site, machine mixing, compacted by wooden or cast iron rammers, curing, shuttering wherever necessary and all labour charges etc., and other necessary charges required to complete. | D15: Cum | E15: 159.26 | F15: 6027 | G15: =ROUND(E15*F15,0) -> 959860
B16: 2 | C16: Providing and laying Plum concrete using lean concrete of grade M5 wherever specified using cement, fine aggregates, 40mm down size metal and boulders of 150mm (proportion 60: 40 for concrete : boulder) including sub grade base preparation, levelling, laying and placing of concrete and boulders in sequential manner to achieve a solid mass including all leads and lifts, rough finishing at the top surface, curing and temporary formwork if necessary etc., complete at all levels as directed by Client / the Engineer and as per drawings. | D16: Cum | E16: 5 | F16: 5787 | G16: =ROUND(E16*F16,0) -> 28935
B17: C | C17: RCC WORKS | F17: 0
B18: 1 | C18: Providing and laying Ready mix concrete (RMC )of specified grade at all levels and heights using ordinary Portland cement of grade 53 from approved manufacturer, Manufacture sand, 20mm and down size coarse aggregates, necessary admixtures approved by Consultants (Conplast SP 430SRV from Fosroc or equivalent), including all leads and lifts, pumping using line pump , vibrating/ compacting, curing as directed excluding the cost of shuttering and centring. The mix proportion of cement with that of GGBS shall be confirming to latest IS standards. For all grades of concrete manufactured/produced, minimum cement content in the concrete shall be 310 kg per cubic metre of concrete. Also, irrespective of the grade of concrete, the maximum cement content shall not be more than 500 kg per cubic metre of concrete. These limitations shall apply for all types of cements of all strengths. | F18: 0 | G18: =ROUND(E18*F18,0) -> 0
B19: a | C19: M30 Concrete | F19: 0
B20: i | C20: Raft / Footing | D20: Cum | E20: 571.99 | F20: 6835 | G20: =ROUND(E20*F20,0) -> 3909552
B21: ii | C21: Drain Wall | D21: Cum | E21: 735.74 | F21: 6835 | G21: =ROUND(E21*F21,0) -> 5028783
B22: iv | C22: Column | D22: Cum | E22: 22.68 | F22: 6835 | G22: =ROUND(E22*F22,0) -> 155018
B23: v | C23: Tie/coping beam | D23: Cum | E23: 34.85 | F23: 6835 | G23: =ROUND(E23*F23,0) -> 238200
B24: D | C24: REINFORCEMENT STEEL | F24: 0
B25: 1 | C25: Supplying, Collecting, fabricating & fixing in position reinforcement for RCC work with high yield strength ribbed cold twisted tor steel (HYSD) bar of various diameters and grade of steel at all levels conforming to IS specification including transporting from yard, decoiling, straightening, cutting, bending, hoisting, fabricating, and placing in position according to drawings and binding the reinforcement with GI annealed binding wire of double fold of 18 gauge and providing PVC cover blocks, for placing the reinforcements in position and for maintaining the cover specified and/or according to relevant IS including dewatering wherever necessary. The rate shall include cost of binding wire, chairs, spacers which will not be measured separately for payment etc complete all as per design, specifications and drawings, with all lead & lift for all materials & labour and as directed, at all heights & locations. | F25: 0 | G25: =ROUND(E25*F25,0) -> 0
C26: Quantity of steel as per drawing and with authorised overlaps only shall be measured and paid for. Contractor shall prepare bar bending schedule and fabrication shall be carried out as per bar bending schedules. (Note: All testing (including physical & chemical) and quality assurances shall be as per the tender conditions/ Specifications and no extra shall be paid for the same.) | F26: 0 | G26: =ROUND(E26*F26,0) -> 0
B27: i | C27: Grade of reinforced steel - Fe 500 | D27: MT | E27: 123.64 | F27: 69511 | G27: =ROUND(E27*F27,0) -> 8594340
B28: E | C28: SHUTTERING WORKS | F28: 0
B29: 1 | C29: Providing, fabricating and erecting formwork with 12mm tk Plywood at all levels and heights as indicated in the drawing including strutting, propping with acceptable staging system, bracing etc. and removal or de shuttering of all form work materials (Shuttering and deshutering works shall confirm to IS 4990 ( 2011) or latest IS standards).The formwork shall be in such a way that the concrete work shall be true to line and level, free from honeycombing, pinholes and surface irregularities. The joints shall be tight and intact to avoid loss of mortar / concrete /slurry. Care shall be taken to see that the form work shall be coated with mould oil ( as suggested by IS ) before use. The form work shall be cleaned for saw dust, dirt and mud etc. before pouring concrete. Cost to include PVC spacers, providing opening for cut outs or openings etc. complete with all consumables. | F29: 0 | G29: =ROUND(E29*F29,0) -> 0
B30: i | C30: Raft / Footing | D30: Sqm | E30: 705.65 | F30: 761 | G30: =ROUND(E30*F30,0) -> 537000
B31: ii | C31: Drain Wall | D31: Sqm | E31: 7357.35 | F31: 761 | G31: =ROUND(E31*F31,0) -> 5598943
B32: iii | C32: Column | D32: Sqm | E32: 378 | F32: 761 | G32: =ROUND(E32*F32,0) -> 287658
B33: iv | C33: Tie beam | D33: Sqm | E33: 348.5 | F33: 761 | G33: =ROUND(E33*F33,0) -> 265209
B34: F | C34: MISCELLANEOUS WORKS | F34: 0
B35: 1 | C35: Supplying and fixing of perforated SFRC manhole cover & frame of heavy Duty confirming to IS 12592: 2002. The frame of manhole shall be firmly embeded to concrete alignment on top of masonry/concrete, the work shall include making good the same in cement mortar etc., complete in all respects. Size: 600mm x 600mm (clear internal dimension) | D35: Nos | E35: 90 | F35: 5330 | G35: =ROUND(E35*F35,0) -> 479700
B36: 2 | C36: Supply & laying of Precast RCC Perforated cover slab of 75mm thick along the storm water drain portions across the vehicle movement . The work includes concreting the slab with providing holes(25dia PVC pipe to be inserted while casting the slab), lifting hooks. The rate includes complete works but not limited with by providing necessary formwork and reinforcement steel as per the provided reference drawing and as per the instruction of Engineer In-charge. Edge angle shall be measured and paid separately. | D36: Sqm | E36: 1002.43 | F36: 4810 | G36: =ROUND(E36*F36,0) -> 4821688
B37: G | C37: FINISHING WORKS | F37: 0
B38: 1 | C38: Providing and Constructing of Solid Cement Concrete Block Masonry Work at all levels in cement mortar 1:6 (1Cement:6 Manufactured Sand) using standard sizes of 400mm X 200mm X 200mm of solid cement concrete blocks of thickness , with a minimum compressive strength of 35 Kg/Sq Cm conforming to IS 2185, including all scaffolding, staging, wastages, labour, curing, all Lead & lifts, raking, 10mm joints should be pointed neatly, cleaning surroundings at all time, using proper tools (block cutting machine, spirit level, Right angle (BIG) and tackles, etc. complete and as directed and as per specification & drawings and as per the directions of Engineer-in Charge. | D38: Sqm | E38: 601.89 | F38: 1469 | G38: =ROUND(E38*F38,0) -> 884176
B39: 2 | C39: Preparing the surface, providing & applying Sponge finish Plastering for external walls in two layers with base coat 12mm thick in CM 1:6 (1cement :6 Manufactured sand) & finishing coat 8mm thick in CM 1:4 (1cement :4 Manufactured sand) laid in panels with jointless finish as per design including Water Proofing Compound 2% by weight for both coats of approved make, cement punning of cornices/projection/grooves, hacking ,drip mould of all shape and sizes, fixing of 200 mm wide GI plaster Rhombus shaped mesh Arpitha or equivalent approved make in the junctions of the masonry & R.C.C work, over electrical conduiting if exceeds one number & wherever applicable as per manufacturer's specifications and plastering the mesh in CM 1:3. The work shall include cost of materials, hacking, labour, curing,approved waterproofing chemical, all lead and lifts at all levels, loading and unloading, scaffolding and all other incidental charges ,cleaning surroundings at all time ,using proper tools (spirit level,Right angle (BIG) and tackles, etc. , complete and as directed by the Engineer-in-charge. | D39: Sqm | E39: 1332.76 | F39: 776 | G39: =ROUND(E39*F39,0) -> 1034222
B40: 3 | C40: Texture Scratch Finish: Providing and applying synthetic textured finish (3 mm thick) trowel finish textured coat comprising of minimum 4 coats out of which the base coat shall be of acrylic texture of 3 mm thick with silicious aggregates & a coat of Primer as bonding layer between texture and Paint, the final 2 coats shall comprise of acrylic weather proof emulsion, all in approved colour and texture to external wall faces including preparation of surface, appropriate primer coat, grooves 16mm, etc. applied as per manufacturer's instructions complete & Client / the Engineer instructions, as required. All materials shall be of Asian/ Berger/ Nerolac/equivalent make. The finish shall be colourfast, water repellant, resistant to condensate formation, cover hairline cracks/ crazing, UV & alkali resistant & ensure good breathability for the substrate all to the satisfaction of the Client / the Engineer. The surface to be painted shall be made free from any loose paint, dust, grease and any fungus, algae or moss, on it shall got be removed thoroughly by vigorous wire brushing and cleaning with water. Any surface imperfection such as holes, dents, pin holes, slurries , cracks shall be corrected by filling with external wall putty. The rate includes cost of all materials, labour, scaffolding, Platforms, gondola, ladders charges, storing & safeguarding the labour in all heights. Nothing extra shall be payable for repairing & touch-ups till handing over due to poor workmenship, to the satisfaction of Client / the Engineer. | D40: Sqm | E40: 1590.71 | F40: 391 | G40: =ROUND(E40*F40,0) -> 621968
B41: 4 | C41: Supplying, fabricating and erecting Structural steel members in position at all levels and at all heights as specified in the drawings made out of standard MS sections conforming to IS 226/2062/800. Cost to include fabricating necessary Gusset Plates, Stiffener plates, Chequered plates, Brackets, Bolts, Cleats, seating angles, MS Flats, MS grating and consumables etc., to the required size, shape, alignment etc, as per the drawings. The rate shall include for necessary anchors, anchoring arrangements to the walls and fixing on concrete bed/as per site condition,Cost to include welding of members using structural steel welding electrodes as per IS 814/816/817, a coat of anti corrosive primer (non flammable) to the exposed surfaces, testing as per IS 7307 (PART 1), necessary equipments, tools and tackles, staging, scaffolding required etc., complete. The rate to include two coats of enamel paint over a coat of zinc chromate primer.Complete as per the drawings. Location: For MS Compound wall | D41: MT | E41: 35 | F41: 137033 | G41: =ROUND(E41*F41,0) -> 4796155
B42: 5 | C42: Providing and fixing of 50mm dia weep hole at 2m c/c horizontal & 1m c/c vertical staggered. Providing & placing in position weep holes with upto 500mm long 50mm dia porus drain pipe clad with 200 GSM geotextile as per detailed drawings. Rates including making the Filter media using aggregates and enclosed with wirenet, geotextile etc. | D42: Nos | E42: 1350 | F42: 743 | G42: =ROUND(E42*F42,0) -> 1003050
C43: TOTAL AMOUNT (Excl GST) | G43: =SUM(G5:G42) -> 42099257

Sheet Ext Dev. Works
A1: PROJECT : PROVIDENT ECOPOLITAN
A2: SUBJECT: EXTERNAL DEVELOPMENT WORKS
A4: Sl No | B4: Description Of Work | C4: Uom | D4: Qty | E4: Rate | F4: Amount (Rs.) | G4: Remarks
A5: A | B5: ROADS / PAVEMENTS & MISCELLANEOUS WORKS and ASSOCIATED STRUCTURE WORKS
A6: 1 | B6: Excavation for road / pathway / pavements works in all lateritic sand/lateritic clay/silty lime sand/ dense soil, disintegrated/ weathered/ soft rock etc (Poclainable) to depth & dressing to camber & disposing the surplus earth within the site premises as directed by Engineer In charge complete at all levels. Obtaining approval from Mining department is in Contractor's scope. | C6: Cum | D6: 6980 | E6: 243 | F6: =$D6*E6 -> 1696140 | G6: Obtaining Mining Approval and Royalty are in Client's scope and the same is not included. Actual excavated earth shall be measured and paid.
A7: 2 | B7: Excavation in all types of soil including dense soil, disintegrated/ weathered/ soft rock (Poclainable) for catch pits, trenches,drains, etc., by mechanical means including manual excavation for levelling, dressing the edges, with all leads and lifts. Dewatering of both ground and surface water, removal of slurry generated while excavation and keeping the area free of water with necessary shoring, strutting, required for keeping earth in position etc., Note:PCC area shall be considered for measurement (Working space & provision of slopes if required for execution shall not be paid separately). Obtaining approval from Mining department is in Contractor's scope. | E7: 0 | F7: =ROUND(D7*E7,0) -> 0 | G7: Obtaining Mining Approval and Royalty are in Client's scope and the same is not included. Actual excavated earth shall be measured and paid. Dewatering, Shoring & Strutting are not included in the quoted rates.
A8: i | B8: Depth Upto 1.5m | C8: Cum | D8: 1832 | E8: 243 | F8: =$D8*E8 -> 445176
A9: ii | B9: Depth from 1.5m to 3m | C9: Cum | D9: 338 | E9: 243 | F9: =$D9*E9 -> 82134
A10: 3 | B10: Sub base preparation & Compaction: Preparation of subgrade after trimming to the required cambers and gradients, watering, compacting the same using 8-10 T vibratory power roller (5-6 Times rolling) to achieve 97% proctor density CBR which shall be more than 8 for subgrade at exisiting level/cuttingarea, failing which contractor shall redo the subgrade as per the relevent codes and instructions from consultant. (NOTE: Surface shall be checked for CBR which shall be minimum 30 failing which contractor shall redo the subgrade as per the relavent codes and instructions from consultants) | C10: Sqm | D10: 15054 | E10: 85 | F10: =$D10*E10 -> 1279590 | G10: If procter density CBR is not acheivable due to soil conditions then redoing the subgrade and bringing different soil and materials shall be paid additionally.
A11: =A10+1 -> 4 | B11: Supply and filling in foundations/Pathways/Roads/ etc wherever required and the area wherever specified with approved good quality filling materials in plinths, area development etc. wherever specified in layers of not exceeding 200 mm thick including breaking clods, storing, transportation ,double handling, watering, compacting each layer with vibratory compactor and at unaccessible places with wooden/steel rammers to achieve 95% proctor density at optimum moisture content, all leads and lifts, bailing/ pumping out of water to keep site dry while backfilling; cost shall include conveyance of all materials, labour, machinery etc. complete as directed. The rate to includes loading, unloading, hire and fuel charges for tools and plants and other incidental charges etc., complete. | E11: 0 | F11: =$D11*E11 -> 0
A12: i | B12: With excavated earth available at site | C12: Cum | D12: =4188+1362 -> 5550 | E12: 150 | F12: =$D12*E12 -> 832500
A13: ii | B13: With approved quality earth brought from outside | C13: Cum | D13: =100+100 -> 200 | E13: 700 | F13: =$D13*E13 -> 140000
A14: 5 | B14: Preperation of subgrade after trimming to the required cambers and gradients, watering, compacting the same using 8-10 T vibratory power roller (5-6 Times rolling) to achieve required density. (NOTE: Surface shall be checked for CBR which shall be minimum 30 failing which contractor shall redo the subgrade as per the relavent codes and instructions from consultants) | C14: Sqm | D14: 775 | E14: 85 | F14: =$D14*E14 -> 65875
A15: =A14+1 -> 6 | B15: Carting away surplus Excavated earth & disposing off the same to the designated areas identified with necessary approvals for dumping as per the norms of local authorities.Rate including cost of necessary royality charges ,lead & lift complete at all leavels. Mode of measurement- where measurement is not possible by level. i) Soil - truck measurement less 20% for voids. ii) Hard Rock - truck measurement less 50% for voids | C15: Cum | D15: 700 | E15: 278 | F15: =$D15*E15 -> 194600 | G15: Royalty is not included.
A16: =A15+1 -> 7 | B16: Providing Pre-constructional anti- termite treatment and creating a chemical barrier to the building by injecting chemical emulsion of required concentrations under grade slab and Grade beam, around the Plinth, Plinth filling, trenches, junction of wall and floor, Retaining / side walls of basement floor, external perimeter of building, surrounding of pipes, expansion joints, below UG sump and etc.as per instructions of chemical manufacturer and all as directed. The treatment shall be carried out strictly in accordance with the technical specification and conforming to IS 6313 or equivalent BS specification. The chemical to be used as insecticides for the treatment shall be 50% EC (Imidacloprid 30.5 SC)and the application shall be dilute one part of chemical 50% EC with 49 parts of water to get 1% emulsion and strictly in accordance with the manufacturer's specification. | C16: Sqm | D16: 342 | E16: 96 | F16: =$D16*E16 -> 32832
A17: =A16+1 -> 8 | B17: Providing and spreading the aggregates using 40/20mm and downsize aggregates including all lead, lift, incidental charges, etc., complete. | C17: Cum | D17: 47 | E17: 2083 | F17: =$D17*E17 -> 97901
A18: 9 | B18: Granular sub-base Providing and laying granular sub-base consisting of sand, murum, crushed stone and gravel mixed in proportions as specified below: Sieve designation % by weight passing 75mm 100 53mm 80-100 26.5mm 55-90 9.5mm 35-65 4.75mm 25-55 2.36mm 20-40 0.425mm 10-25 0.075mm 3-10 for sub grade to a compacted specified thickness laid in double layer using good quality graded materials from approved source and mixed in the specified proportion including cost and conveyance of all materials, stacking and mixing in the specified proportion, spreading after mixing to required camber, levelling, watering with all leads to obtain moisture levels of mix between 1% above and 2% below the optimum moisture content at the time of compaction and compacting each layer with suitable vibratory power machine/ to obtain the required proctor density and minimum CBR to be achieved-30, including all labour, charges for all tools and plants employed and all their incidental charges etc. all complete as per specifications and as directed engineer-incharge. | C18: Cum | D18: 1890 | E18: 2730 | F18: =$D18*E18 -> 5159700
A19: =A18+1 -> 10 | B19: WMM - Providing, laying, spreading and compacting graded stones aggregate to Wet mix macadam specifications including pre mixing the material with water at OMC in mechanical mix plant carriage of mixed materials by tipper to site, laying in uniform layers with sub-base/base course on well prepared surface and compacting with vibratory roller to achieve the desired density complete as per specifications/ MoRT&H, as directed by PIC . | C19: Cum | D19: 1750 | E19: 2830 | F19: =$D19*E19 -> 4952500
A20: 11 | B20: Providing and laying Plain Cement Concrete M10 grade (1:3:6) following to the minimum depth 100mm to 150mm using graded granite aggregate of 20mm and down size, including all material at site, machine mixing, compacted by wooden or cast iron rammers, curing, shuttering wherever necessary and all labour charges etc., and other necessary charges required to complete. | C20: Cum | D20: =343+466 -> 809 | E20: 6055 | F20: =$D20*E20 -> 4898495 | G20: Shuttering required beyond 100mm thick shall be measured and paid under formwork separately.
A21: 12 | B21: SHUTTERING WORKS- Providing, fabricating and erecting formwork with plywood at all levels and heights as indicated in the drawing including strutting, propping with acceptable staging system, bracing etc. and removal or de shuttering of all form work materials (Shuttering and deshutering works shall confirm to IS 4990 ( 2011) or latest IS standards).The formwork shall be in such a way that the concrete work shall be true to line and level, free from honeycombing, pinholes and surface irregularities. The joints shall be tight and intact to avoid loss of mortar / concrete /slurry. Care shall be taken to see that the form work shall be coated with mould oil ( as suggested by IS ) before use. The form work shall be cleaned for saw dust, dirt and mud etc. before pouring concrete. Cost to include PVC spacers, providing opening for cut outs or openings etc. complete with all consumables. | C21: Sqm | D21: 4287 | E21: 800 | F21: =$D21*E21 -> 3429600 | G21: Plywood / PP material shall be used.
A22: 13 | B22: Providing & laying plant mixed design mix reinforced cement concrete Using M30 Grade for pavement confirming to grades as specified in (IS 456 - 2000) and as per specifications mentioned below at all levels using 20mm & down size aggregates, fine aggregates, OPC, necessary admixtures approved by Consultants, including designing the mix, trial cubes, accelerated curing, weigh batching, mechanical mixing, transporting, pumping and placing at all levels, excluding the cost of steel reinforcement. The cement concrete mix shall be laid and finished with screed board vibrator, vacum dewatering process and finally finished by floating, brooming with wire brush etc. complete as per specifications and directions of Engineer-in-charge.All side forms shall be of mild steel. The steel forms shall be of M.S. Channel sections and their depth shall be equal to the thickness of the pavement.,. Curing of the same needs to be done till the 7 days after the completion of the concreting. | C22: Cum | D22: 1045 | E22: 8031 | F22: =$D22*E22 -> 8392395 | G22: Quoted as per existing approved mix design with GGBS.
A23: 14 | B23: READYMIX CONCRETE Providing and laying Ready mix concrete (RMC )of specified grade at all levels and heights using ordinary Portland cement of grade 53 from approved manufacturer, Manufacture sand, 20mm and down size coarse aggregates, necessary admixtures approved by Consultants (Conplast SP 430SRV from Fosroc or equivalent), including all leads and lifts, pumping using line pump , vibrating/ compacting, curing as directed excluding the cost of shuttering and centring. The mix proportion of cement with that of GGBS shall be confirming to latest IS standards. For all grades of concrete manufactured/produced, minimum cement content in the concrete shall be 310 kg per cubic metre of concrete. Also, irrespective of the grade of concrete, the maximum cement content shall not be more than 500 kg per cubic metre of concrete. These limitations shall apply for all types of cements of all strengths. | E23: 0 | F23: =$D23*E23 -> 0 | G23: Quoted as per existing approved mix design with GGBS.
A24: i | B24: M 20 Grade | C24: Cum | D24: 30 | E24: 6765 | F24: =$D24*E24 -> 202950
A25: ii | B25: M 25 Grade | C25: Cum | D25: 575 | E25: 6969 | F25: =$D25*E25 -> 4007175
A26: iii | B26: M 30 Grade | C26: Cum | D26: 165 | E26: 7094 | F26: =$D26*E26 -> 1170510
A27: 15 | B27: Providing and laying 125 gsm guage polythene paper/Polythene sheet as a moisture barrier to the required levels, including supply, loading and unloading, storing, transportation, laying, sealing of junctions and overlaps, all leads and lifts, etc.,complete below concrete. | C27: Sqm | D27: 6765 | E27: 45 | F27: =$D27*E27 -> 304425 | G27: Sealing Junction is not included.
A28: =A27+1 -> 16 | B28: Providing and mixing hybrid polymeric macro-fibers composed of a single filament polyolefin based fiber with structural functions and a fibrillated polypropylene macro-fiber to reduce concrete plastic shrinkage with special coating to ensure its uniform dispersion in the concrete and good adhesion with concrete, to increase the concrete bending resistance, ductility, fatigue strength and durability. hybrid polymeric macro fibres in concrete at the rate of 1.0 kg/cum as per manufacturers specifications. | C28: Kgs | D28: 1015 | E28: 366 | F28: =$D28*E28 -> 371490
A29: =A28+1 -> 17 | B29: Providing, supplying and sprinkling evenly on a concrete laid surface using ready mixed non-metallic monolithic floor hardening compound (Non Ferrous Hardner Ironite 3) with very hard granulates of mineral origin over concrete road surface when the concrete in green and touch dry condition at the rate of 3 to 5 Kg/Sqm based on the site requirements shall posses the following properties, it shall possess a compressive strength of 60N/mm2, improves the abrasion resistance of concrete by 225% when tested as per guidelines in IS:1237 - 1980. when tested as per IS: 516-1959 as per specification and instructions of the manufacturer including levelling, smoothening by mechanical / power float, finishing, curing etc. all complete. | C29: Kgs | D29: 33825 | E29: 21 | F29: =$D29*E29 -> 710325 | G29: Mechanical / Power float is not included in this item which shallbe be part Item no.13
A30: =A29+1 -> 18 | B30: Charges towards cutting grooves of specified size at required joints as per drawing with necessary cleaning, filling, finishing and curing the grooves using pourable grade Polysulphide Sealants of approved makes specified . Rate to include for all tools and tackles, all lead and lift etc complete. Size - 4mm X 30 mm | C30: Rmt | D30: 3637 | E30: 345 | F30: =$D30*E30 -> 1254765
A31: 19 | B31: REINFORCEMENT STEEL - Supplying, Collecting, fabricating & fixing in position reinforcement steel for RCC work with high yield strength ribbed cold twisted tor steel (HYSD) bar of various diameters and grade of steel at all levels conforming to IS specification including transporting from yard, decoiling, straightening, cutting, bending, hoisting, fabricating, and placing in position according to drawings and binding the reinforcement with GI annealed binding wire of double fold of 18 gauge and providing PVC cover blocks, for placing the reinforcements in position and for maintaining the cover specified and/or according to relevant IS including dewatering wherever necessary. The rate shall include cost of binding wire, chairs, spacers which will not be measured separately for payment etc complete all as per design, specifications and drawings, with all lead & lift for all materials & labour and as directed, at all heights & locations. | E31: 0 | F31: =$D31*E31 -> 0 | G31: All embeded steel shall be measured and paid. Dewatering shall be paid separately.
B32: Quantity of steel as per drawing and with authorised overlaps only shall be measured and paid for. Contractor shall prepare bar bending schedule and fabrication shall be carried out as per bar bending schedules. (Note: All testing (including physical & chemical) and quality assurances shall be as per the tender conditions/ Specifications and no extra shall be paid for the same.) Grade of reinforced steel - Fe 500 | C32: MT | D32: =40+58 -> 98 | E32: 70511 | F32: =$D32*E32 -> 6910078 | G32: All embeded steel shall be measured and paid. Dewatering shall be paid separately.
A33: =A31+1 -> 20 | B33: Providing and Fixing of 12 dia Dowel bar: 600mm long, 300mm c/c including including bituminuous paint/plastic sheeting 0.2 to 0.4mm thk cover for dowel bar at movement joints. | C33: Nos | D33: 676 | E33: 137 | F33: =$D33*E33 -> 92612 | G33: Reinforcement steel is not included which shall be measured under Item.No.19
A34: 21 | B34: Supplying, fabricating and erecting Structural steel members in position at all levels and at all heights as specified in the drawings made out of standard MS sections conforming to IS 226/2062/800. Scope include fabricating necessary Gusset Plates, Stiffener plates, Chequered plates, Brackets, Bolts, Cleats, seating angles, MS Flats, MS grating , MS seating structure and consumables etc., to the required size, shape, alignment etc, as per the drawings. The rate shall include for necessary anchoring arrangements to the walls and fixing on concrete bed,Cost to include welding of members using structural steel welding electrodes as per IS 814/816/817, a coat of anti corrosive primer (non flammable) to the exposed surfaces, testing as per IS 7307 (PART 1), necessary equipments, tools and tackles, staging, scaffolding required etc., complete. The rate to include two coats of enamel paint over a coat of zinc chromate primer.Complete as per the drawings. | C34: MT | D34: =110 -> 110 | E34: 149609 | F34: =$D34*E34 -> 16456990 | G34: Supply & fixing of Anchor bolts are not included which shall be measured and paid separately. Curved/circular/parabolic / irregular shapes are in considered in the quoted rate which shall be paid additionally.
A35: 22 | B35: Providing, fabrication and fixing of GI Chain link mesh 50*50*8 Gauge wire welded to Box/Pipes as per drawing. Rate is inclusive of material, fabrication, wastages, overlap, placing in position, welding,two coats of enamel paint over a one coat of zinc chromate primer etc, complete in all respects as directed by site incharge. Note: MS Frame work will be measured and paid seperately. | C35: Sqm | D35: 1051 | E35: 806 | F35: =$D35*E35 -> 847106
A36: =A35+1 -> 23 | B36: Providing and laying of Precast concrete Cobbles of size 100 x 100 x 80mm thick, shot blasted, Grey/black colour, Make: Super Tiles /equivalent interlocking pavers laid over 50mm thk 'M' sand bed and compacting with plate vibrator having 3tons compaction force thereby forcing part of sand underneath to come up in between joints, final compaction of paver surface joints into its final level. pattern as per landscape architects details. The cost including of all materials at site, wastages, all labour charges, cutting the pavers using machine tools at ends or trims and other charges as required to complete. | C36: Sqm | D36: 1697 | E36: 2875 | F36: =$D36*E36 -> 4878875 | G36: Basic price of Paver: Rs.1076.4/Sqm
A37: =A36+1 -> 24 | B37: Infill : Providing and laying 100mm thk, coloured concrete, Grey colour with Sandscape finish. Maintain mix characteristics for coloured concrete requiring a matching finish. Use the same source, brand, type, and color of cement, supplementary cementitious materials, aggregates, and admixtures for coloured concrete throughout the project. Use constant cement content, supplementary cementitious material content, and water/ cementitious materials ratio to maintain consistent color. Obtain engineer approval for coloured concrete mixes before placing coloured concrete. Vendor shall provide a finished coloured concrete sample from the previous project having minimum dimensions of 600x600x40mm size for landscape architect's approval. cost including of all materials at site, wastages, Power trowel finishing, colour pigment, required machinery, creating panels, grooves etc, all labour charges and other charges required to complete. | C37: Sqm | D37: 2013 | E37: 2595 | F37: =$D37*E37 -> 5223735 | G37: Grey color with Sandscape finish of Running Brick / Classic Grey pattern.
A38: =A37+1 -> 25 | B38: Pedastrain Pathway and Carparking : Providing and laying of Precast concrete pavers of size 100x200x80mm thick, shot blasted, Grey colour, Make: Super Tiles /equivalent interlocking pavers laid over 50mm thk 'M' sand bed and compacting with plate vibrator having 3tons compaction force thereby forcing part of sand underneath to come up in between joints, final compaction of paver surface joints into its final level. pattern as per landscape architects details. The cost including of all materials at site, wastages, all labour charges, cutting the pavers using machine tools at ends or trims and other charges as required to complete. | C38: Sqm | D38: 6380 | E38: 1522 | F38: =$D38*E38 -> 9710360 | G38: Basic price of Paver: Rs.861.12/Sqm
A39: =A38+1 -> 26 | B39: Precast Flush Kerbs Rate including of the following:- a) Excavating trench of 300 mm wide in all kind of soil excluding soft/ hard rocks to a depth of 300 mm including using the selected /approved excavated materials for back filling, well compacting and backfilling to the required space & level the surplus earth inside the site premises b) Providing and laying PCC 1:4:8 for foundation of size 275 mm wide and 50 mm base and 75 mm deep side haunch (as per drawing) using graded granite aggregate of 20 mm and down size & M Sand, including mixing, compacted by wooden or cast iron rammers, curing etc., complete. c) Supply of precast concrete kerb Make: SuperTiles/Sobha/Equivalent. d) Handling of precast concrete kerb to place of work for fixing. e) Fixing kerb in excavated trench as per the drawing (including PCC) f) Refilling earth on both the sides with proper compaction g) Finishing the joints with CM 1:4 h) Painting the kerb with a coat of primer & 2 coats of enamel paint of approved shade & make. The rates including making drainage opening wherever required | E39: 0 | F39: =$D39*E39 -> 0 | G39: Basic price of Kerb: Rs.450/Rmt
A40: i | B40: 150mm x 450mm x 600mm (Splay kerb) | C40: Rmt | D40: 1355 | E40: 1234 | F40: =$D40*E40 -> 1672070
A41: ii | B41: 150mm x 450mm x 600mm (Flush kerb) | C41: Rmt | D41: 581 | E41: 1234 | F41: =$D41*E41 -> 716954
A42: 27 | B42: Saucer Drain Rate inclusive of the following: a) Supply of precast concrete Saucer Drain of size:300mm wide and 125mm deep b) Pointing at Joints with CM 1:3 over 30mm thk M Sand with compaction c) Handling of precast concrete kerb to place of work for fixing. d) Fixing saucer drain in excavated trench as per the drawing e) Refilling earth on both the sides with proper compaction f) Finishing the joints with CM 1:3 Make: Super Tiles/Equivalent. | C42: Rmt | D42: 954 | E42: 1234 | F42: =$D42*E42 -> 1177236 | G42: Basic price of Kerb: Rs.450/Rmt
A43: =A42+1 -> 28 | B43: Providing and constructing at all levels Solid concrete block masonry of suitable heights as per design or as directed with precast cement concrete Solid blocks of approved quality and make confirming to ISI code No.2185 with a crushing strength of not less than 35 Kg/Sq.cm in CM 1:4 mix consolidated 10mm thick with necessary scaffolding, ladders, platforms and staging, curing and all lead & lift complete. plant required for the execution of the work. Bearing blocks of concrete or bricks in mortar courses will have to be introduced where required. | C43: Cum | D43: 93 | E43: 8757 | F43: =$D43*E43 -> 814401 | G43: Locally available Solid Blocks considered. No Brands
A44: =A43+1 -> 29 | B44: Providing and Constructing of 200mm thk Solid Cement Concrete Block Masonry work at all levels in cement mortar 1:6 (1Cement: 6 Manufactured Sand) using standard sizes of 400mm X 200mm X 200mm of solid cement concrete blocks of thickness, with a minimum compressive strength of 35 Kg/Sq Cm conforming to IS 2185, including all scaffolding, staging, wastages, labour, curing, all Lead & lifts, raking, pointing the joints to at least 10mm depth, cleaning surroundings at all time, using proper tools (block cutting machine, spirit level, Right angle (BIG) and tackles, etc. complete and as directed and as per specification & drawings and as per the directions of Client / the Engineer. | C44: Sqm | D44: 198 | E44: 1569 | F44: =$D44*E44 -> 310662 | G44: Locally available Solid Blocks considered. No Brands
A45: =A44+1 -> 30 | B45: Providing and Constructing of 150mm thk Solid Cement Concrete Block Masonry work at all levels in cement mortar 1:6 (1Cement:6 Manufactured Sand) using standard sizes of 400mm X 200mm X 150mm of solid cement concrete blocks of thickness, with a minimum compressive strength of 35 Kg/Sq Cm conforming to IS 2185, including all scaffolding, staging, wastages, labour, curing, all Lead & lifts, raking, pointing the joints to at least 10mm depth, cleaning surroundings at all time, using proper tools (block cutting machine, spirit level, Right angle (BIG) and tackles, etc. complete and as directed and as per specification & drawings and as per the directions of Client / the Engineer. | C45: Sqm | D45: 56 | E45: 1376 | F45: =$D45*E45 -> 77056 | G45: Locally available Solid Blocks considered. No Brands
A46: =A45+1 -> 31 | B46: Providing and constructing at all levels SS Masonry work of suitable heights as per design or as directed with cement mortar 1:6 mix using granite size stone in courses not less than 200 mm high with edges of the stone hammer dressed and bond stones at two meter apart in each course with finish in line and level including curing, weep holes, scaffolding etc. complete all as per specifications. | C46: Cum | D46: 43 | E46: 11500 | F46: =$D46*E46 -> 494500
A47: =A46+1 -> 32 | B47: Providing and laying of 50mm thick DPC, Cement Concrete 1:3:6 with aggregate of 20mm down graded machine crushed HBG metal shall be used. Where specified approved water admixture (100 ml/one bag of cement of conplast X 421 IC of m/s fosroc or equivalent) shall be mixed . Including cost of shuttering, all operational, incidental works labour charges etc., complete for finished item of work. | C47: Cum | D47: 5 | E47: 6670 | F47: =$D47*E47 -> 33350
A48: =A47+1 -> 33 | B48: Preparing the surface, providing & applying Sponge finish Plastering for external walls in two layers with base coat 12mm thick in CM 1:6 (1cement : 6 Manufactured sand) & finishing coat 8mm thick in CM 1:4 (1cement : 4 Manufactured sand) laid in panels with jointless finish as per design including Water Proofing Compound 2% by weight for both coats of approved make, cement punning of cornices / projection / grooves, hacking, drip mould of all shape and sizes, fixing of 200 mm wide GI plaster Rhombus shaped mesh Arpitha or equivalent approved make in the junctions of the masonry & R.C.C work, over electrical conduiting if exceeds one number & wherever applicable as per manufacturer's specifications and plastering the mesh in CM 1:3. The work shall include cost of materials, labour, curing, approved waterproofing chemical, all lead and lifts at all levels, loading and unloading, scaffolding and all other incidental charges ,cleaning surroundings at all time ,using proper tools (spirit level, Right angle (BIG) and tackles, etc. , complete and as directed by the Client / the Engineer. The rate to include providing grooves of 25 x 10mm or plaster drip mould bands of size 40 x 20mm wide if any, wherever required as per the drawings etc., complete. | C48: Sqm | D48: 2232 | E48: 776 | F48: =$D48*E48 -> 1732032 | G48: Grooves and Bands are not included which shall be paid separately. 150mm wide GI Mesh considered
A49: =A48+1 -> 34 | B49: Prepare the surface, hacking, providing and applying Internal plastering to all internal RCC / Masonry surface, walls etc. at all levels, in cement mortar 1:6, 12mm thick, sponge finished, PVC rings as plaster thickness fixing for round openings, to line with necessary scaffolding, curing,etc, complete. including all lead and lifts. Cost to include supplying and Fixing Plaster GI Rhombus shaped mesh 200 mm wide (for concrete and block joints) and over electrical conduiting if exceeds one number made out of galvanized iron of nominal thickness 0.35mm with a zinc coating of 120 gms / Sqm of Arpitha or equivalent make, GI exposed corner beads (For exposed corners) made out of galvanized iron of nominal thickness 0.50 mm with zinc coating of size 45mm x 45mm of Arpitha or equivalent make, as protector for plastered wall and column corners/edges, including cutting grooves, rate to include the groove cutting for conduiting if required, plastering the mesh for both in CM 1:3 (concrete/masonry, grooves, electrical conduits), including tying in position by using Galvanised nails / washer / screws etc at the Column corners, wall corners wherever called for required size. and cost of necessary staging,etc., complete. | C49: Sqm | D49: 254 | E49: 483 | F49: =$D49*E49 -> 122682 | G49: Grooves and Bands are not included which shall be paid separately. 150mm wide GI Mesh considered. Corner bead, Groove cutting and Cement mortar filling are included which shall be paid separately.
A50: =A49+1 -> 35 | B50: Providing, applying, Rough plastering at all levels (neat uniform rakings) in CM 1:6, (1cement :6 Manufactured sand) 8mm thick for walls, fixing tiles, granite slabs, marble etc. to line and plumb for walls including scartching the surface to receive the tiles for Dado backing, curing for 7 days, cleaning surroundings at all time, using proper tools (Spirit level, Right angle (BIG) and tackles, etc. complete at all levels. | C50: Sqm | D50: 29 | E50: 445 | F50: =$D50*E50 -> 12905 | G50: 150mm wide GI Mesh considered. Corner bead, Groove cutting and Cement mortar filling are included which shall be paid separately.
A51: =A50+1 -> 36 | B51: Texture Scratch Finish: Providing and applying synthetic textured finish (3 mm thick) trowel finish textured coat comprising of minimum 4 coats out of which the base coat shall be of acrylic texture of 3 mm thick with silicious aggregates & a coat of Primer as bonding layer between texture and Paint, the final 2 coats shall comprise of acrylic weather proof emulsion, all in approved colour and texture to external wall faces including preparation of surface, appropriate primer coat, grooves 16mm, etc. applied as per manufacturer's instructions complete & Client / the Engineer instructions, as required. All materials shall be of Asian/ Berger/ Nerolac/equivalent make. The finish shall be colourfast, water repellant, resistant to condensate formation, cover hairline cracks/ crazing, UV & alkali resistant & ensure good breathability for the substrate all to the satisfaction of the Client / the Engineer. The surface to be painted shall be made free from any loose paint, dust, grease and any fungus, algae or moss, on it shall got be removed thoroughly by vigorous wire brushing and cleaning with water. Any surface imperfection such as holes, dents, pin holes, slurries , cracks shall be corrected by filling with external wall putty. The rate includes cost of all materials, labour, scaffolding, Platforms, gondola, ladders charges, storing & safeguarding the labour in all heights. Nothing extra shall be payable for repairing & touch-ups till handing over due to poor workmenship, to the satisfaction of Client / the Engineer. | C51: Sqm | D51: 997 | E51: 391 | F51: =$D51*E51 -> 389827 | G51: Basic price applicable as per Civil Agreement
A52: =A51+1 -> 37 | B52: Internal Wall Painting:Providing and applying Acrylic emulsion paint for interior walls with 2 coats of Birla or equivalent white wall putty + 1 coat of w/b primer and two coats of acrylic emulsion paint of asian make or equivalent, for walls of approved colour. And preparing the surface by cleaning/sanding, filling up the cracks with crack filler, erecting and dismantling of scaffolding as & when it is required, finishing the surface with roller etc., complete. Note: Contractor shall arrange for his own scaffolding materials, ladders, LDPE sheets that requires protection for door, window, switch box, MS Railing works, etc., legs of the ladders shall be covered properly with gunny bags so that floor does not get damaged. Floor shall be properly covered with plastic sheets to avoid spillage of paint while applying etc., complete with all leads & lifts at all levels complete and as per the instructions of the Client / the Engineer. Nothing extra shall be payable for repairing & touch-ups till handing over due to poor workmenship, to the satisfaction of Client / the Engineer. | C52: Sqm | D52: 273 | E52: 205 | F52: =$D52*E52 -> 55965 | G52: Smooth putty considered. Coarse putty shall be paid separately.
A53: =A52+1 -> 38 | B53: Providing & Laying of Anti skid ceramic tiles (as per Product standardization) or equivalent reputed make of approved size (300mmX300mm), thickness as manufacturer, in approved colours/shades to floor in required position set with average thickness of 4mm thk polymer modified tile adhesive (acheived using 8mm toothed trowel applicator), matching the design patterns, using necessary tools & tackles Joints to run continuous horizontally and vertically with 2mm spacers, levelling, lining, pointing with cementitious based polymer grouting of the joints of balendura /laticrete or equivalent make to the required contrast colour of the tile (as per technical specification standardization), rubbing, washing, cleaning and protecting finished surface from scratches, damage, stains and other damages at level with, 750/1000 GSM - 2mm thick self adhesive sheet Floor guard make or equivalent, joints to be taped, should remain intact till handing over, removed & disposed out of site after completion etc. with all leads & lifts at all levels and heights and all as per the instructions of Client / the Engineer complete. | C53: Sqm | D53: =79+10 -> 89 | E53: 1516 | F53: =$D53*E53 -> 134924 | G53: Basic price applicable as per Civil Agreement. PVC Sheet / Bubble guard sheet protection considered.
A54: =A53+1 -> 39 | B54: Providing, cutting to required size and laying of Anti-skid ceramic tiles of size 300mm x 600mm for dadoing of approved colour and shade over average thickness of 3mm thk polymer modified tile adhesive, which is achieved through 6 mm toothed trowel, with 2mm spacers including PVC Edge beading (the exposed corners of door/ledge wall with matching PVC corner beadings from Arpitha make or Equivalent laid to horizontal pattern/Staggered pattern as per drawing) material, labour, machinery, Cutting charges and pointing with the matching colour tile grout of cementitious based polymer grouting for wall, and (all around wall floor joints with matching colour sanitary grade silicone sealant or matching colour Epoxy grout 2 to 3 mm haunching of balendura/laticrete), Cleaning, soap washing, cleaning of debris at all time ,using proper tools (Spirit level, Right angle) making tile round cuttings using advanced machines without any chipped edges for the plumbing outlet points, and tackles etc complete, with all leads & lifts at all levels and heights and all as per the instructions of Client / the Engineer. | C54: Sqm | D54: 29 | E54: 1641 | F54: =$D54*E54 -> 47589 | G54: Basic price applicable as per Civil Agreement
A55: =A54+1 -> 40 | B55: Providing and laying Cement Screed Concrete Flooring of 35mm average thickness with cement concrete 1:2:4 using 12mm and down graded aggregates to be finished smooth in order to achieve proper level to receive tile flooring, includes compacting, curing, etc., complete at all levels with all leads and lifts, and as per the instructions of Client / the Engineer. | C55: Sqm | D55: 89 | E55: 381 | F55: =$D55*E55 -> 33909
A56: =A55+1 -> 41 | B56: Providing & fixing 20mm thk. polished Granite slab (with chamfering at one corner to avoid sharp edge and thereby utilising more space) of approved shade for (counters), with 40 mm lipping (with miter joint - pencil rounded) to cover MS angle support structure (MS bracket/angle a coat of anti corrossive Zinc-Chromate primer and 2 coats of Black/White colour Satin Enamel Paint) all as per the details in the drawings, line groove of 2 x 2 mm for water droplet below the counter, cutting groove in wall finishing, making holes for pipes and basins making provision for fixing bolts, brackets and nuts, sealing the joints of all sanitary ware (Sink/Bowl & granite) and granite & tile joints using sanitary grade matching colour Silicone sealant, curing, surface protection, cleaning when ever instructed, pointing of joints using cementitious grout of approved make & polishing, etc complete with all leads & lifts at all levels as per specifications given in the drawings, and as per the instructions of Client / the Engineer. The Rate includes supporting MS structure as per the drawing & a coat of zinc chromate primer & 2 coats of Synthetic Enamel paint of approved make & color with all leads and lifts at all levels and heights and as directed by Client / the Engineer. Note: Plan area shall be measured for payment. | C56: Sqm | D56: 8 | E56: 8245 | F56: =$D56*E56 -> 65960 | G56: Actual area including fascia without deducting Openings (Wash basin & Tape) shall be measured and paid. Anchor Bolts shall be measured and paid separately.
A57: =A56+1 -> 42 | B57: Supplying , providing and fixing in position first Engineered/Solid wood frames (Not sandwiched but soild framesof single wood) of size 100x45mm, 32mm thick Marine grade Flush shutters with solid infill as per approved specifications phenol bonded with both side cladded with 1mm thick laminate of approved shade, Front Architrvae ,Back Mould all sizes all as per design shown on the drawing including cost of beading , wood lipping and if any,complete. The rate should be inclusive of PU polish for frame and laminate for shutter to approved shade & complete.Door Hardware & Iron mongery shall be under the scope of Doors vendor for smooth installation, All to be approved hardware by the architect/client. The job shall be completed in all aspects as shown in the architecture drawing and as specified by the Engineer including all other necessary related works as specified and as directed. Nail less architrave fixing using Laquered glue in groove/veneer system fixing. The rate inclusive of providing (a) Ball bearing butt hinges (b) Locks (c) Door Stopper,(d) Concealed Drop seal below door ,e) Tower bolt f) handles etc as per drawing.As per standards, specification and directed by the Engineer-in-charge. Size : 900mm x 2100mm | C57: Nos | D57: 1 | E57: 13700 | F57: =$D57*E57 -> 13700 | G57: Basic price - 12000/No (all inclusive)
A58: =A57+1 -> 43 | B58: Supplying , providing and fixing in position first Engineered/Solid wood frames (Not sandwiched but soild framesof single wood) of size 100x45mm, 30mm thick Marine grade Flush shutters with solid infill as per approved specifications phenol bonded with both side cladded with 1mm thick laminate of approved shade, Front Architrvae ,Back Mould all sizes all as per design shown on the drawing including cost of beading , wood lipping and if any,complete. The rate should be inclusive of PU polish for frame and laminate for shutter to approved shade & complete.Door Hardware & Iron mongery shall be under the scope of Doors vendor for smooth installation, All to be approved hardware by the architect/client. The job shall be completed in all aspects as shown in the architecture drawing and as specified by the Engineer including all other necessary related works as specified and as directed.Nail less architrave fixing using Laquered glue in groove/veneer system fixing..The rate inclusive of providing (a) Ball bearing butt hinges (b) Locks (c) Door Stopper, d)Tower bolt e) handles etc as per drawing.As per standards, specification and directed by the Engineer-in-charge. Size: (750mm x 2100mm) | C58: Nos | D58: 1 | E58: 12597 | F58: =$D58*E58 -> 12597 | G58: Basic price - 11000/No (all inclusive)
A59: =A58+1 -> 44 | B59: Providing and applying the APEX weather proof exterior emulsion(water based 100% acrylic) or approved equivalent grade paint to all type of cement plasters, concrete, exterior walls, ceiling etc. or surface / sub straits(which are subjected to continuous seepage and dampness. The surface to be painted shall be made free from any loose paint, dust, grease and any fungus, algae or moss, on it shall got be removed thoroughly by vigorous wire brushing and cleaning with water. Then one coat of exterior grade wall primer be applied after which any surface imperfection such as holes, dents, pin holes, slurries, cracks shall be corrected by filling with external wall putty. Thereafter second coat of exterior grade wall primer and again surface imperfection to be corrected. Thereafter Apex weatherproof exterior emulsion paint to be applied in two coats. All materials shall be of Asian/ Berger/ Nerolac/equivalent make. The color and pattern/ color combination of the paint shall be got approved from Client / the Engineer. Contractor has to submit photographs of building with colour combinations for sample selection. The stock of the quantity for all material as manufacturer’s theoretical consumption (per unit of actual wall surface area) shall be made available at site before commencement of the painting work. The rate includes cost of all materials, labour, scaffolding, Platforms, gondola, ladders charges, storing & safeguarding the labour in all heights. Nothing extra shall be payable for repairing & touch-ups till handing over due to poor workmenship, to the satisfaction of Client / the Engineer. | C59: Sqm | D59: 274 | E59: 230 | F59: =$D59*E59 -> 63020
A60: =A59+1 -> 45 | B60: Coping: Providing and fixing in position 40mm thk, Flamed finish/Lather finish of Sera Granite /Royal Brown with grey colour for coping laid with a paper cut joint & over a bed of 20mm thick CM 1:4, set in cement slurry mixed with colour pigment to match the shade of the slab, joints neatly done, including machine cut straight edge with paper joints, smoothening the edges and complete all as per specifications, drawings & directions. Cost including of all materials at site, wastages, rounding/Nosing, chamfering, grooves if required, all labour charges, curing, chemical washing and all other necessary charges required to complete. | E60: 0 | F60: =$D60*E60 -> 0 | G60: Edge chamferring considered. No nosing
A61: i | B61: upto 180mm Wide | C61: Rmt | D61: 714 | E61: 1322 | F61: =$D61*E61 -> 943908
A62: ii | B62: 200mm wide | C62: Rmt | D62: 652 | E62: 1399 | F62: =$D62*E62 -> 912148
A63: iii | B63: 250mm wide | C63: Rmt | D63: 29 | E63: 1591 | F63: =$D63*E63 -> 46139
A64: iv | B64: 300mm wide | C64: Rmt | D64: 14 | E64: 1825 | F64: =$D64*E64 -> 25550
A65: iv | B65: 400mm wide | C65: Rmt | D65: 97 | E65: 2294 | F65: =$D65*E65 -> 222518
A66: v | B66: 450mm wide | C66: Rmt | D66: 49 | E66: 2528 | F66: =$D66*E66 -> 123872
A67: =A60+1 -> 46 | B67: Providing and applying Granite Texture Paint for Signage wall, painting two coats of approved quality/ colour/ shade over a coat of water based cement primer, on new surface to give an even shade to match as per building colour. cleaning the surface of all dirt, dust and foreign matter etc. The rate shall include the cost of material, labour, scaffolding, surface preparation etc., Complete all as per manufactures specifications & direction. | C67: Sqm | D67: 274 | E67: 391 | F67: =$D67*E67 -> 107134 | G67: =+G51 -> Basic price applicable as per Civil Agreement
A68: =A67+1 -> 47 | B68: Providing and fixing in position to pattern 40mm thk Granite cladding on walls/ RCC with manufacturer recommended adhesive and PVC spacers, with base coat of minimum 20mm thick CM 1:4, joints shall be treated with polymer based cement grout. And shall have the edges machine cut to precise sizes to produce very fine joints. Cost to include chasing of wall wherever required, surface preparation, grooves of approved size, chamfering, edge polishing, provision of electrical fixtures and services, labour, materials, wastages, curing, cleaning, all lead, lifts, necessary staging/scaffolding, polishing/finishing as specified, any other related works, etc., all complete as per drawing, specifications and as directed by the Client / the Engineer. | C68: Sqm | D68: 88 | E68: 5618 | F68: =$D68*E68 -> 494384 | G68: Basic price applicable as per Civil Agreement
A69: =A68+1 -> 48 | B69: Providing and applying fibre reinforced elastomeric liquid water proofing membrane with resilient acrylic polymers on top of concrete surface in three coats @10.76 litre/ 10 sqm. One coat of self-priming of elastomeric waterproofing liquid (dilution with water in the ratio of 3:1) and two coats of undiluted elastomeric waterproofing liquid (dry film thickness of complete application/system not less than 500 microns). The operation shall be carried out after scrapping and properly cleaning the surface to remove loose particles with wire brushes, complete in all respect as per the direction of Engineer-in-Charge. | C69: Sqm | D69: 500 | E69: 600 | F69: =$D69*E69 -> 300000
A70: =A69+1 -> 49 | B70: Providing and filling approved 50mm downsize Cinder in CM 1:8 proportion having high compressive strength with thermal / acoustic insulation properties, anti-corrosion of desired density. Cinder available from furnaces of steam boilers using coal fuel only shall be used and brick kiln cinder shall not be allowed. The cinder should be cleaned, free from dirt and wood ashes and shall pass through IS 3.35 sieve with 50% passing through IS 1.70 sieve and should not contain more than 10% of unburnt carbon and not more than 0.5% of acid soluble sulphates(SO). The cinder should be soaked in water before filling. Including Mixing, transportation, placing, compacting and finishing to the required level etc complete. density 800 Kg/Cum. The concrete shall be cured for 7 days. | C70: Cum | D70: 809 | E70: 5815 | F70: =$D70*E70 -> 4704335
A71: =A70+1 -> 50 | B71: Stepping stone: Providing and fixing in position 40mm thk, Sera Granite/Royal Brown/Silver Grey with grey colour for stepping. laid with a paper cut joint & over a well compacted 50mm thick gravel or M Sand bed. Including machine cut straight edge with paper joints, smoothening the edges and complete all as per specifications, drawings & directions. Cost including of all materials at site, wastages, rounding/nosing, grooves if any, chanfering etc, all labour charges, chemical washing and all other necessary charges required to complete. | C71: Sqm | D71: 19 | E71: 5818 | F71: =$D71*E71 -> 110542 | G71: =+G68 -> Basic price applicable as per Civil Agreement
A72: =A71+1 -> 51 | B72: Providing and fixing in position 40mm thk, flame finish / Sera Granite/Royal Brown/Silver Grey / black Granite with grey colour for flooring laid with a paper cut joint & over a bed of 20mm thick CM 1:4, set in cement slurry mixed with colour pigment to match the shade of the slab, joints neatly done, including machine cut straight edge with paper joints, smoothening the edges and complete all as per specifications, drawings & directions. Cost including of all materials at site, all labour charges, curing, chemical washing and all other necessary charges required to complete. | C72: Sqm | D72: 155 | E72: 5818 | F72: =$D72*E72 -> 901790 | G72: =+G71 -> Basic price applicable as per Civil Agreement
A73: =A72+1 -> 52 | B73: Providing and fixing of 16mm thk Anti-skid Heavy duty Vitrified Tiles for flooring using a size of tile, colour, approved shade, and patterns are given by the Architect's details and specifications. Make such as pavit or equivalent, laid over a bed of 20mm thick in C.M 1:4 set in cement slurry including jointing & pointing with white cement & colour pigment with matching the tiles shades. complete all as per technical specifications given by the manufacturer & directions. Cost including of all materials at site, all labour charges, curing, chemical washing and other charges required to complete. | C73: Sqm | D73: 399 | E73: 1791 | F73: =$D73*E73 -> 714609 | G73: =+G72 -> Basic price applicable as per Civil Agreement
A74: i | B74: Do as above item for Skiring - 100mm height | C74: Rmt | D74: 284 | E74: 260 | F74: =$D74*E74 -> 73840 | G74: =+G73 -> Basic price applicable as per Civil Agreement
A75: =A73+1 -> 53 | B75: Stage Band: Providing and fixing in position 40mm thk, 300mm wide, flamed finish black Granite band for flooring. laid with a paper cut joint & over a bed of 20mm thick CM 1:4, set in cement slurry mixed with colour pigment to match the shade of the slab, joints neatly done, including machine cut straight edge with paper joints, smoothening the edges and complete all as per specifications, drawings & directions. Cost including of all materials at site, all labour charges, curing, chemical washing and all other necessary charges required to complete. | C75: Rmt | D75: 13 | E75: 2250 | F75: =$D75*E75 -> 29250 | G75: =+G74 -> Basic price applicable as per Civil Agreement
A76: =A75+1 -> 54 | B76: Providing and laying 230mm tk Stone pitching to required slope, lines, joints and levels as per design requirements or landscape architects details and specification etc. The rate shall include the cost of material, labour, pointing charges if any, surface preparation and other necessary charges required to complete. | C76: Sqm | D76: 396 | E76: 1375 | F76: =$D76*E76 -> 544500
A77: =A76+1 -> 55 | B77: Providing and fixing in position 40mm thk, irregular size rough granite stone with grey colour (as per availability) for flooring etc. laid with a paper cut joint & over a bed of 20mm thick CM 1:4, set in cement slurry mixed with colour pigment to match the shade of the slab, joints neatly done, including machine cut straight edge, smoothening the edges and complete all as per specifications, drawings & directions. Cost including of all materials at site, all labour charges, curing, chemical washing and all other necessary charges required to complete. | C77: Sqm | D77: 73 | E77: 5618 | F77: =$D77*E77 -> 410114 | G77: =+G75 -> Basic price applicable as per Civil Agreement
A78: =A77+1 -> 56 | B78: Band: Providing and fixing in position 40mm thk, 200mm Wide, Flamed finish Royal Brown Granite laid with a paper cut joint & over a bed of 20mm thick CM 1:4, set in cement slurry mixed with colour pigment to match the shade of the slab, joints neatly done, including machine cut straight edge with paper joints, smoothening the edges and complete all as per specifications, drawings & directions. Cost including of all materials at site, all labour charges, curing, chemical washing and all other necessary charges required to complete. | C78: Rmt | D78: 191 | E78: 1970 | F78: =$D78*E78 -> 376270 | G78: =+G77 -> Basic price applicable as per Civil Agreement
A79: =A78+1 -> 57 | B79: Providing and fixing of 10mm thk Anti-skid Heavy duty Vitrified Tiles wooden finish for flooring using a tile of size (1200mm x 200mm or as per site requirement) for flooring using a tile of size, colour, approved shade, and patterns are given by the Architect's details and specifications. Make such as pavit or equivalent, laid over a bed of 20mm thick in C.M 1:4 set in cement slurry including jointing & pointing with white cement & colour pigment with matching the tiles shades. complete all as per technical specifications given by the manufacturer & directions. Cost including of all materials at site, all labour charges, curing, chemical washing and other charges required to complete. | C79: Sqm | D79: 345 | E79: 1791 | F79: =$D79*E79 -> 617895 | G79: =+G78 -> Basic price applicable as per Civil Agreement
A80: =A79+1 -> 58 | B80: Steps Tread: Providing and fixing in position 450mm wide, 40mm thk, Flamed finish Royal Brown Granite laid with a paper cut joint & over a bed of 20mm thick CM 1:4, set in cement slurry mixed with colour pigment to match the shade of the slab, joints neatly done, including machine cut straight edge with paper joints, smoothening the edges and complete all as per specifications, drawings & directions. Cost including of all materials at site, groove making, Rounding, all labour charges, curing, chemical washing and all other necessary charges required to complete. | C80: Sqm | D80: 85 | E80: 6118 | F80: =$D80*E80 -> 520030 | G80: =+G79 -> Basic price applicable as per Civil Agreement
A81: =A80+1 -> 59 | B81: Steps Riser: Providing and fixing in position 20mm thk, 150mm wide, Flamed finishRoyal Brown Granite laid with a paper cut joint & over a bed of 20mm thick CM 1:4, set in cement slurry mixed with colour pigment to match the shade of the slab, joints neatly done, including machine cut straight edge with paper joints, smoothening the edges and complete all as per specifications, drawings & directions. Cost including of all materials at site, grooves making, Rounding, all labour charges, curing, chemical washing and all other necessary charges required to complete. | C81: Sqm | D81: 31 | E81: 5618 | F81: =$D81*E81 -> 174158 | G81: =+G80 -> Basic price applicable as per Civil Agreement
A82: =A81+1 -> 60 | B82: Fencing with roof top: Providing and fixing of Nylon Mesh Make:Garware, mesh size of 2 Inch x 2 inch, 2.5mm thick tying rope with garware make net, 4 sides fencing and top cover, front portion to be left open, Color Green, UV Resistant Poles of 48.3mm OD MS Poles (Vertical & Horizontal) thickness 2mm, Primer & Enamel painted (Green Color), 15 Feet height, Base plate anchor system or grouting inside earth as per site condition. Vertical Pole to Pole Distance 10 Feet, Top & Bottom Horizontal Pipe Support. Note: MS Supports will be measured and paid seperately. | C82: Sqm | D82: 1314 | E82: 1050 | F82: =$D82*E82 -> 1379700
A83: =A82+1 -> 61 | B83: Providing and fixing in position at all heights "M.S Railing" for location specified as per detailed drawing and specifications including all necessary anchoring arrangements all joints to be fully smoothened before painting, a coat of anticorrossive primer etc,. Complete. Rate shall include application of one coat of zinc chromate primer and two coats of synthetic Matt enamel paint, base plate etc. All MS terminations in to the wall to be detailed with neat round MS rosette of 3 mm thickness etc., complete as per drawing. The rate is including all kind of materials, labour, tools, tackles and machinary, leads and lift, all locations etc. Contractor to take shop drawing approval before starting the work. | C83: Kgs | D83: 10515 | E83: 145 | F83: =$D83*E83 -> 1524675 | G83: Anchor Bolts shall be measured and paid separately.
A84: =A83+1 -> 62 | B84: Providing, supplying, grouting of base plate with specialised non shrink cementitious grout, of specified thickness with necessary staging, scaffolding, formwork support, mixing in proportions, pouring / pumping at all heights , levels, lines etc, curing , complete with a guarantee for minimum period of 15years from the date of completion at all levels and heights at specified location as directed by Engineer/ in-charge. 25mm thick | C84: Sqm | D84: 100 | E84: 1150 | F84: =$D84*E84 -> 115000
A85: =A84+1 -> 63 | B85: Pedestals - For Light poles | E85: 0 | F85: =$D85*E85 -> 0
A86: i | B86: Providing & construction of M20 Grade Concrete pedestals size as specified in drawing, for the Light poles including excavation, backfilling, PCC, M20 grade concrete, Formwork, Reinforcement etc., complete in all respects as directed by site incharge. Please note bolts, base plates etc. for fixing the light pole shall be supplied by electrical vendor and only installation has to be done by pedastal contractor. | E86: 0 | F86: =$D86*E86 -> 0 | G86: Reinforcement steel is not included which shall be measured under Item.No.19
A87: a | B87: 500mmx500mmx1150mm | C87: Nos | D87: 34 | E87: 5854 | F87: =$D87*E87 -> 199036
A88: b | B88: 500mmx500mmx1050mm | C88: Nos | D88: 69 | E88: 5175 | F88: =$D88*E88 -> 357075
B89: Total Amount (Excl GST) | F89: =SUM(F6:F88) -> 107750645
F92: 99000000
F94: =F89-F92 -> 8750644.7

Sheet RFA
A3: Sl NO | B3: Description | C3: Amount (Rs.) Excl GST
C4: As per Contract | D4: Current | G4: Revised WO
D5: Qty Variation | E5: NT & Derived Items | F5: Gross VO
A6: 1 | B6: Initial Contract | C6: 3165595306 | D6: 0 | E6: 0 | F6: 0 | G6: =C6 -> 3165595306 | J6: Sl.No | K6: Description | L6: Amount (Rs) | M6: Remarks
A7: 2 | B7: VO#01 | C7: =G6 -> 3165595306 | D7: 0 | E7: 0 | F7: 0 | G7: =F7+C7+1000000 -> 3166595306 | J7: 1 | K7: Value of Work Order | L7: =C7 -> 3165595306
A8: 3 | B8: VO#02 | C8: =G7 -> 3166595306 | D8: 0 | E8: 0 | F8: 0 | G8: =F8+C8+29515583 -> 3196110889 | J8: 2 | K8: Value of VO#01 | L8: =F7 -> 0 | M8: Additional Scope for Compound Wall & Sub Soil Drainage System
A9: 4 | B9: Present VO#03 | C9: =G8 -> 3196110889 | D9: =Summary_Final!D29+Summary_Final!D19 -> -31364949 | E9: =Summary_Final!D39+Summary_Final!D41+Summary_Final!D43+Summary_Final!D45 -> 2.0023971e+08 | F9: =D9+E9 -> 1.6887476e+08 | G9: =ROUNDUP(F9+C9,0) -> 3364985654 | K9: Revised contract value | L9: =SUM(L7:L8) -> 3165595306
